Workbook

Sheet FY 25
AH2: MORA | AQ2: ONA | BA2: MG | BM2: 80 | BN2: 80 | BO2: 80 | BP2: 80 | BQ2: 80 | BR2: 80 | BS2: 80 | BT2: 80 | BU2: 80 | BV2: 80 | BW2: 56
C3: 5124 | D3: 5134 | E3: 5145 | F3: 5147 | G3: 5164 | H3: 5166 | I3: 5173 | J3: 5174 | K3: 5175 | L3: 5176 | M3: 5208 | N3: 5209 | O3: 5211 | P3: 5227 | Q3: PC VA | R3: 5124 | S3: 5129 | T3: 5134 | U3: 5145 | V3: 5147 | W3: 5164 | X3: 5166 | Y3: 5173 | Z3: 5174 | AA3: 5175 | AB3: 5176 | AC3: 5208 | AD3: 5209 | AE3: 5211 | AF3: 5227 | AG3: PC MD | AH3: 2032 | AI3: 5051 | AJ3: 5052 | AK3: 5059 | AL3: 5140 | AM3: 5155 | AN3: 5187 | AO3: 5196 | AP3: MORA | AQ3: 5061 | AR3: 5062 | AS3: 5117 | AT3: 5118 | AU3: 5119 | AV3: 5151 | AW3: 5214 | AX3: 5215 | AY3: 5216 | AZ3: ONA | BA3: 5222 MD | BB3: 5189 MD | BC3: 5189 VA | BD3: 5222 VA | BE3: AFHS | BF3: VFHY | BG3: DV | BH3: NOFO | BI3: VOCA | BJ3: TVAP | BK3: G. Total | BL3: Hourly Rate | BM3: 45793 | BN3: 45807 | BO3: 45821 | BP3: 45835 | BQ3: 45849 | BR3: 45863 | BS3: 45877 | BT3: 45891 | BU3: 45905 | BV3: 45919 | BW3: 7 Days | BX3: Total | BY3: Balance
A4: 1 | B4: Jenna | Q4: =SUM(C4:P4) -> 0 | V4: =16619.68 -> 16619.68 | AG4: =SUM(R4:AF4) -> 16619.68 | AP4: =SUM(AH4:AO4) -> 0 | AZ4: =SUM(AQ4:AY4) -> 0 | BG4: 0 | BI4: 0 | BK4: =+Q4+AP4+AZ4+BE4+BH4+BI4+BJ4+BG4+AG4+BF4+BA4+BD4+BB4+BC4 -> 16619.68 | BL4: 24.0385 | BM4: 0 | BN4: 0 | BO4: =BO2*$BL$4 -> 1923.08 | BP4: =BP2*$BL$4 -> 1923.08 | BQ4: =BQ2*$BL$4 -> 1923.08 | BR4: =BR2*$BL$4 -> 1923.08 | BS4: =BS2*$BL$4 -> 1923.08 | BT4: =BT2*$BL$4 -> 1923.08 | BU4: =BU2*$BL$4 -> 1923.08 | BV4: =BV2*$BL$4 -> 1923.08 | BW4: =BW2*$BL$4 -> 1346.156 | BX4: =SUM(BM4:BW4) -> 16730.796 | BY4: =+BK4-BX4 -> -111.116
A5: 2 | B5: Abeer | Q5: =SUM(C5:P5) -> 0 | AG5: =SUM(R5:AF5) -> 0 | AP5: =SUM(AH5:AO5) -> 0 | BG5: 12973.01 | BI5: 947.92 | BJ5: 11917.33 | BK5: =+Q5+AP5+AZ5+BE5+BH5+BI5+BJ5+BG5+AG5+BF5+BA5+BD5+BB5+BC5 -> 25838.26 | BL5: 24.0385 | BM5: =$BM$2*$BL$6 -> 2048.08 | BN5: =$BM$2*$BL$6 -> 2048.08 | BO5: =$BM$2*$BL$6 -> 2048.08 | BP5: =$BM$2*$BL$6 -> 2048.08 | BQ5: =$BM$2*$BL$6 -> 2048.08 | BR5: =$BM$2*$BL$6 -> 2048.08 | BS5: =$BM$2*$BL$6 -> 2048.08 | BT5: =$BM$2*$BL$6 -> 2048.08 | ... BW5: =$BM$2*$BL$6 -> 2048.08 | BX5: =SUM(BM5:BW5) -> 22528.88 | BY5: =+BK5-BX5 -> 3309.38 | CA5: =+BL5*2080 -> 50000.08
A6: 3 | B6: ABI | Q6: =SUM(C6:P6) -> 0 | AG6: =SUM(R6:AF6) -> 0 | AP6: =SUM(AH6:AO6) -> 0 | AS6: 13753.82 | AT6: 15253.83 | AZ6: =SUM(AQ6:AY6) -> 29007.65 | BK6: =+Q6+AP6+AZ6+BE6+BH6+BI6+BJ6+BG6+AG6+BF6+BA6+BD6+BB6+BC6 -> 29007.65 | BL6: 25.601 | BM6: =$BM$2*$BL$6 -> 2048.08 | BN6: =$BM$2*$BL$6 -> 2048.08 | BO6: =$BM$2*$BL$6 -> 2048.08 | BP6: =$BM$2*$BL$6 -> 2048.08 | BQ6: =$BM$2*$BL$6 -> 2048.08 | BR6: =$BM$2*$BL$6 -> 2048.08 | BS6: =$BM$2*$BL$6 -> 2048.08 | BT6: =$BM$2*$BL$6 -> 2048.08 | ... BW6: =$BM$2*$BL$6 -> 2048.08 | BX6: =SUM(BM6:BW6) -> 22528.88 | BY6: =+BK6-BX6 -> 6478.77 | CA6: =+BL6*2080 -> 53250.08
A7: =+A6+1 -> 4 | B7: Aemal | Q7: =SUM(C7:P7) -> 0 | AG7: =SUM(R7:AF7) -> 0 | AP7: =SUM(AH7:AO7) -> 0 | AT7: 29538.41 | AZ7: =SUM(AQ7:AY7) -> 29538.41 | BK7: =+Q7+AP7+AZ7+BE7+BH7+BI7+BJ7+BG7+AG7+BF7+BA7+BD7+BB7+BC7 -> 29538.41 | BL7: 26.4423 | BM7: =+$BL$7*BM2 -> 2115.384 | BN7: =+$BL$7*BN2 -> 2115.384 | BO7: =+$BL$7*BO2 -> 2115.384 | BP7: =+$BL$7*BP2 -> 2115.384 | BQ7: =+$BL$7*BQ2 -> 2115.384 | BR7: =+$BL$7*BR2 -> 2115.384 | BS7: =+$BL$7*BS2 -> 2115.384 | BT7: =+$BL$7*BT2 -> 2115.384 | ... BW7: =+$BL$7*BW2 -> 1480.7688 | BX7: =SUM(BM7:BW7) -> 22634.609 | BY7: =+BK7-BX7 -> 6903.8012 | CA7: =+BL7*2080 -> 54999.984
A8: =+A7+1 -> 5 | B8: Ahmed Seyar Auobi | F8: 2240.39 | J8: 8644.19 | L8: 11000 | N8: 397.92 | O8: 1685.37 | Q8: =SUM(C8:P8) -> 23967.87 | AG8: =SUM(R8:AF8) -> 0 | AH8: 0 | AI8: 0 | AP8: =SUM(AH8:AO8) -> 0 | AZ8: =SUM(AQ8:AY8) -> 0 | BK8: =+Q8+AP8+AZ8+BE8+BH8+BI8+BJ8+BG8+AG8+BF8+BA8+BD8+BB8+BC8 -> 23967.87 | BL8: 24.0385 | BM8: =+$BL$8*BM2 -> 1923.08 | BN8: =+$BL$8*BN2 -> 1923.08 | BO8: =+$BL$8*BO2 -> 1923.08 | BP8: =+$BL$8*BP2 -> 1923.08 | BQ8: =+$BL$8*BQ2 -> 1923.08 | BR8: =+$BL$8*BR2 -> 1923.08 | BS8: =+$BL$8*BS2 -> 1923.08 | BT8: =+$BL$8*BT2 -> 1923.08 | ... BW8: =+$BL$8*BW2 -> 1346.156 | BX8: =SUM(BM8:BW8) -> 20576.956 | BY8: =+BK8-BX8 -> 3390.914 | CA8: =+BL8*2080 -> 50000.08
A9: =+A8+1 -> 6 | B9: Ajmal Amiri | G9: 2463.21 | N9: 23766.74 | Q9: =SUM(C9:P9) -> 26229.95 | AG9: =SUM(R9:AF9) -> 0 | AH9: 0 | AI9: 0 | AP9: =SUM(AH9:AO9) -> 0 | AZ9: =SUM(AQ9:AY9) -> 0 | BK9: =+Q9+AP9+AZ9+BE9+BH9+BI9+BJ9+BG9+AG9+BF9+BA9+BD9+BB9+BC9 -> 26229.95 | BL9: 25.601 | BM9: =$BL$9*BM2 -> 2048.08 | BN9: =$BL$9*BN2 -> 2048.08 | BO9: =$BL$9*BO2 -> 2048.08 | BP9: =$BL$9*BP2 -> 2048.08 | BQ9: =$BL$9*BQ2 -> 2048.08 | BR9: =$BL$9*BR2 -> 2048.08 | BS9: =$BL$9*BS2 -> 2048.08 | BT9: =$BL$9*BT2 -> 2048.08 | ... BW9: =$BL$9*BW2 -> 1433.656 | BX9: =SUM(BM9:BW9) -> 21914.456 | BY9: =+BK9-BX9 -> 4315.494 | CA9: =+BL9*2080 -> 53250.08
A10: =+A9+1 -> 7 | B10: Akilu Debalkew | H10: 10115.38 | J10: 375.5 | L10: 2405.77 | O10: 140.19 | P10: 9000 | Q10: =SUM(C10:P10) -> 22036.84 | AC10: 93.46 | AG10: =SUM(R10:AF10) -> 93.46 | AH10: 0 | AI10: 0 | AP10: =SUM(AH10:AO10) -> 0 | AZ10: =SUM(AQ10:AY10) -> 0 | BA10: 2000 | BC10: 1923.08 | BK10: =+Q10+AP10+AZ10+BE10+BH10+BI10+BJ10+BG10+AG10+BF10+BA10+BD10+BB10+BC10 -> 26053.38 | BL10: 24.0385 | BM10: =+$BL$10*BM2 -> 1923.08 | BN10: =+$BL$10*BN2 -> 1923.08 | BO10: =+$BL$10*BO2 -> 1923.08 | BP10: =+$BL$10*BP2 -> 1923.08 | BQ10: =+$BL$10*BQ2 -> 1923.08 | BR10: =+$BL$10*BR2 -> 1923.08 | BS10: =+$BL$10*BS2 -> 1923.08 | BT10: =+$BL$10*BT2 -> 1923.08 | ... BW10: =+$BL$10*BW2 -> 1346.156 | BX10: =SUM(BM10:BW10) -> 20576.956 | BY10: =+BK10-BX10 -> 5476.424 | CA10: =+BL10*2080 -> 50000.08
A11: =+A10+1 -> 8 | B11: Ajmal Khurram | Q11: =SUM(C11:P11) -> 0 | AG11: =SUM(R11:AF11) -> 0 | AK11: 33615.34 | AP11: =SUM(AH11:AO11) -> 33615.34 | AZ11: =SUM(AQ11:AY11) -> 0 | BK11: =+Q11+AP11+AZ11+BE11+BH11+BI11+BJ11+BG11+AG11+BF11+BA11+BD11+BB11+BC11 -> 33615.34 | BL11: 24.0385 | BM11: 0 | BN11: 0 | BO11: =+$BL$11*BO2 -> 1923.08 | BP11: =+$BL$11*BP2 -> 1923.08 | BQ11: =+$BL$11*BQ2 -> 1923.08 | BR11: =+$BL$11*BR2 -> 1923.08 | BS11: =+$BL$11*BS2 -> 1923.08 | BT11: =+$BL$11*BT2 -> 1923.08 | BU11: =+$BL$11*BU2 -> 1923.08 | BV11: =+$BL$11*BV2 -> 1923.08 | BW11: =+$BL$11*BW2 -> 1346.156 | BX11: =SUM(BM11:BW11) -> 16730.796 | BY11: =+BK11-BX11 -> 16884.544 | CA11: =+BL11*2080 -> 50000.08
A12: =+A11+1 -> 9 | B12: Anna Kurzer | Q12: =SUM(C12:P12) -> 0 | AG12: =SUM(R12:AF12) -> 0 | AK12: 20162.55 | AL12: 731 | AP12: =SUM(AH12:AO12) -> 20893.55 | AZ12: =SUM(AQ12:AY12) -> 0 | BA12: 8653.14 | BB12: 499.22 | BK12: =+Q12+AP12+AZ12+BE12+BH12+BI12+BJ12+BG12+AG12+BF12+BA12+BD12+BB12+BC12 -> 30045.91 | BL12: 33.2813 | BM12: =+$BL$12*BM2 -> 2662.504 | BN12: =+$BL$12*BN2 -> 2662.504 | BO12: =+$BL$12*BO2 -> 2662.504 | BP12: =+$BL$12*BP2 -> 2662.504 | BQ12: =+$BL$12*BQ2 -> 2662.504 | BR12: =+$BL$12*BR2 -> 2662.504 | BS12: =+$BL$12*BS2 -> 2662.504 | BT12: =+$BL$12*BT2 -> 2662.504 | ... BW12: =+$BL$12*BW2 -> 1863.7528 | BX12: =SUM(BM12:BW12) -> 28488.793 | BY12: =+BK12-BX12 -> 1557.1172 | CA12: =+BL12*2080 -> 69225.104
A13: =+A12+1 -> 10 | B13: Annie Phillips | F13: 7190.38 | I13: 53.45 | L13: 1000 | M13: 2199 | Q13: =SUM(C13:P13) -> 10442.83 | AG13: =SUM(R13:AF13) -> 0 | AH13: 0 | AI13: 0 | AP13: =SUM(AH13:AO13) -> 0 | AQ13: 156.31 | AV13: 23586.88 | AZ13: =SUM(AQ13:AY13) -> 23743.19 | BK13: =+Q13+AP13+AZ13+BE13+BH13+BI13+BJ13+BG13+AG13+BF13+BA13+BD13+BB13+BC13 -> 34186.02 | BL13: 32.6923 | BM13: =+$BL$13*BM2 -> 2615.384 | BN13: =+$BL$13*BN2 -> 2615.384 | BO13: =+$BL$13*BO2 -> 2615.384 | BP13: =+$BL$13*BP2 -> 2615.384 | BQ13: =+$BL$13*BQ2 -> 2615.384 | BR13: =+$BL$13*BR2 -> 2615.384 | BS13: =+$BL$13*BS2 -> 2615.384 | BT13: =+$BL$13*BT2 -> 2615.384 | ... BW13: =+$BL$13*BW2 -> 1830.7688 | BX13: =SUM(BM13:BW13) -> 27984.609 | BY13: =+BK13-BX13 -> 6201.4112 | CA13: =+BL13*2080 -> 67999.984
A14: =+A13+1 -> 11 | B14: Atakhleti | Q14: =SUM(C14:P14) -> 0 | AG14: =SUM(R14:AF14) -> 0 | AP14: =SUM(AH14:AO14) -> 0 | AZ14: =SUM(AQ14:AY14) -> 0 | BH14: =39347.44-40.09-6000 -> 33307.35 | BK14: =+Q14+AP14+AZ14+BE14+BH14+BI14+BJ14+BG14+AG14+BF14+BA14+BD14+BB14+BC14 -> 33307.35 | BL14: 32.7064 | BM14: =+$BL$14*BM2 -> 2616.512 | BN14: =+$BL$14*BN2 -> 2616.512 | BO14: =+$BL$14*BO2 -> 2616.512 | BP14: =+$BL$14*BP2 -> 2616.512 | BQ14: =+$BL$14*BQ2 -> 2616.512 | BR14: =+$BL$14*BR2 -> 2616.512 | BS14: =+$BL$14*BS2 -> 2616.512 | BT14: =+$BL$14*BT2 -> 2616.512 | ... BW14: =+$BL$14*BW2 -> 1831.5584 | BX14: =SUM(BM14:BW14) -> 27996.678 | BY14: =+BK14-BX14 -> 5310.6716 | CA14: =+BL14*2080 -> 68029.312
A15: =+A14+1 -> 12 | B15: Baig | Q15: =SUM(C15:P15) -> 0 | AG15: =SUM(R15:AF15) -> 0 | AP15: =SUM(AH15:AO15) -> 0 | AT15: 29843.76 | AZ15: =SUM(AQ15:AY15) -> 29843.76 | BK15: =+Q15+AP15+AZ15+BE15+BH15+BI15+BJ15+BG15+AG15+BF15+BA15+BD15+BB15+BC15 -> 29843.76 | BL15: 27.7771 | BM15: =+$BL$15*BM2 -> 2222.168 | BN15: =+$BL$15*BN2 -> 2222.168 | BO15: =+$BL$15*BO2 -> 2222.168 | BP15: =+$BL$15*BP2 -> 2222.168 | BQ15: =+$BL$15*BQ2 -> 2222.168 | BR15: =+$BL$15*BR2 -> 2222.168 | BS15: =+$BL$15*BS2 -> 2222.168 | BT15: =+$BL$15*BT2 -> 2222.168 | ... BW15: =+$BL$15*BW2 -> 1555.5176 | BX15: =SUM(BM15:BW15) -> 23777.198 | BY15: =+BK15-BX15 -> 6066.5624 | CA15: =+BL15*2080 -> 57776.368 | CB15: =+BL15*2080 -> 57776.368
A16: =+A15+1 -> 13 | B16: Barbara Callen | D16: 731.25 | H16: 5281.25 | I16: 1635.64 | J16: 966.58 | M16: 2112.5 | N16: 925 | O16: 1400 | P16: 4052.39 | Q16: =SUM(C16:P16) -> 17104.61 | Z16: 464.47 | AC16: 1400 | AD16: 2800 | AE16: 1400 | AG16: =SUM(R16:AF16) -> 6064.47 | AH16: 0 | AI16: 0 | AK16: 68.75 | AM16: 0 | AO16: 2127.87 | AP16: =SUM(AH16:AO16) -> 2196.62 | AQ16: 700 | AR16: 700 | AW16: 150 | AX16: 1725 | AY16: 1400 | AZ16: =SUM(AQ16:AY16) -> 4675 | BA16: 3250 | BB16: 687.5 | BC16: 687.5 | BD16: 1625 | BI16: 2368.41 | BK16: =+Q16+AP16+AZ16+BE16+BH16+BI16+BJ16+BG16+AG16+BF16+BA16+BD16+BB16+BC16 -> 38659.11 | BL16: 31.25 | BM16: =+$BL$16*BM2 -> 2500 | BN16: =+$BL$16*BN2 -> 2500 | BO16: =+$BL$16*BO2 -> 2500 | BP16: =+$BL$16*BP2 -> 2500 | BQ16: =+$BL$16*BQ2 -> 2500 | BR16: =+$BL$16*BR2 -> 2500 | BS16: =+$BL$16*BS2 -> 2500 | BT16: =+$BL$16*BT2 -> 2500 | ... BW16: =+$BL$16*BW2 -> 1750 | BX16: =SUM(BM16:BW16) -> 26750 | BY16: =+BK16-BX16 -> 11909.11 | CA16: =+BL16*2080 -> 65000
A17: =+A16+1 -> 14 | B17: Baryalai Rawan | Q17: =SUM(C17:P17) -> 0 | T17: 2345.89 | V17: 646.05 | Y17: 486.11 | AB17: 9574.88 | AC17: 7793.73 | AG17: =SUM(R17:AF17) -> 20846.66 | AH17: 3643.12 | AI17: 668.02 | AJ17: 8300.96 | AP17: =SUM(AH17:AO17) -> 12612.1 | AZ17: =SUM(AQ17:AY17) -> 0 | BK17: =+Q17+AP17+AZ17+BE17+BH17+BI17+BJ17+BG17+AG17+BF17+BA17+BD17+BB17+BC17 -> 33458.76 | BL17: 32.6923 | BM17: =+$BL$17*BM2 -> 2615.384 | BN17: =+$BL$17*BN2 -> 2615.384 | BO17: =+$BL$17*BO2 -> 2615.384 | BP17: =+$BL$17*BP2 -> 2615.384 | BQ17: =+$BL$17*BQ2 -> 2615.384 | BR17: =+$BL$17*BR2 -> 2615.384 | BS17: =+$BL$17*BS2 -> 2615.384 | BT17: =+$BL$17*BT2 -> 2615.384 | ... BW17: =+$BL$17*BW2 -> 1830.7688 | BX17: =SUM(BM17:BW17) -> 27984.609 | BY17: =+BK17-BX17 -> 5474.1512 | CA17: =+BL17*2080 -> 67999.984
A18: =+A17+1 -> 15 | B18: Bethelem | Q18: =SUM(C18:P18) -> 0 | AG18: =SUM(R18:AF18) -> 0 | AK18: 31625.12 | AP18: =SUM(AH18:AO18) -> 31625.12 | AZ18: =SUM(AQ18:AY18) -> 0 | BK18: =+Q18+AP18+AZ18+BE18+BH18+BI18+BJ18+BG18+AG18+BF18+BA18+BD18+BB18+BC18 -> 31625.12 | BL18: 24.0385 | BM18: =+$BL$18*BM2 -> 1923.08 | BN18: =+$BL$18*BN2 -> 1923.08 | BO18: =+$BL$18*BO2 -> 1923.08 | BP18: =+$BL$18*BP2 -> 1923.08 | BQ18: =+$BL$18*BQ2 -> 1923.08 | BR18: =+$BL$18*BR2 -> 1923.08 | BS18: =+$BL$18*BS2 -> 1923.08 | BT18: =+$BL$18*BT2 -> 1923.08 | ... BW18: =+$BL$18*BW2 -> 1346.156 | BX18: =SUM(BM18:BW18) -> 20576.956 | BY18: =+BK18-BX18 -> 11048.164 | CA18: =+BL18*2080 -> 50000.08
A19: =+A18+1 -> 16 | B19: Bob Elston | F19: =2948.9+562.5 -> 3511.4 | H19: 1374.99 | P19: 13000 | Q19: =SUM(C19:P19) -> 17886.39 | X19: 9906.25 | AG19: =SUM(R19:AF19) -> 9906.25 | AH19: 0 | AI19: 0 | AP19: =SUM(AH19:AO19) -> 0 | AW19: 1587.5 | AX19: 1506.25 | AZ19: =SUM(AQ19:AY19) -> 3093.75 | BA19: 3250 | BK19: =+Q19+AP19+AZ19+BE19+BH19+BI19+BJ19+BG19+AG19+BF19+BA19+BD19+BB19+BC19 -> 34136.39 | BL19: 31.25 | BM19: =+$BL$19*BM2 -> 2500 | BN19: =+$BL$19*BN2 -> 2500 | BO19: =+$BL$19*BO2 -> 2500 | BP19: =+$BL$19*BP2 -> 2500 | BQ19: =+$BL$19*BQ2 -> 2500 | BR19: =+$BL$19*BR2 -> 2500 | BS19: =+$BL$19*BS2 -> 2500 | BT19: =+$BL$19*BT2 -> 2500 | ... BW19: =+$BL$19*BW2 -> 1750 | BX19: =SUM(BM19:BW19) -> 26750 | BY19: =+BK19-BX19 -> 7386.39 | CA19: =+BL19*2080 -> 65000
A20: 17 | B20: TBH - Lia Russel | Q20: =SUM(C20:P20) -> 0 | AG20: =SUM(R20:AF20) -> 0 | BD20: 18750 | BK20: =+Q20+AP20+AZ20+BE20+BH20+BI20+BJ20+BG20+AG20+BF20+BA20+BD20+BB20+BC20 -> 18750 | BL20: =55000/2080 -> 26.442308 | BP20: =+BL20*BP2 -> 2115.3846 | BQ20: =+BP20 -> 2115.3846 | BR20: =+BQ20 -> 2115.3846 | BS20: =+BR20 -> 2115.3846 | BT20: =+BS20 -> 2115.3846 | BU20: =+BT20 -> 2115.3846 | BV20: =+BU20 -> 2115.3846 | BW20: =+BL20*56 -> 1480.7692 | BX20: =SUM(BM20:BW20) -> 16288.462 | BY20: =+BK20-BX20 -> 2461.5385 | CA20: =+BL20*2080 -> 55000
A21: 18 | B21: Christina | Q21: =SUM(C21:P21) -> 0 | AG21: =SUM(R21:AF21) -> 0 | AP21: =SUM(AH21:AO21) -> 0 | AT21: 26682.65 | AZ21: =SUM(AQ21:AY21) -> 26682.65 | BD21: 0 | BK21: =+Q21+AP21+AZ21+BE21+BH21+BI21+BJ21+BG21+AG21+BF21+BA21+BD21+BB21+BC21 -> 26682.65 | BL21: 25.601 | BM21: =+$BL$21*BM2 -> 2048.08 | BN21: =+$BL$21*BN2 -> 2048.08 | BO21: =+$BL$21*BO2 -> 2048.08 | BP21: =+$BL$21*BP2 -> 2048.08 | BQ21: =+$BL$21*BQ2 -> 2048.08 | BR21: =+$BL$21*BR2 -> 2048.08 | BS21: =+$BL$21*BS2 -> 2048.08 | BT21: =+$BL$21*BT2 -> 2048.08 | ... BW21: =+$BL$21*BW2 -> 1433.656 | BX21: =SUM(BM21:BW21) -> 21914.456 | BY21: =+BK21-BX21 -> 4768.194 | CA21: =+BL21*2080 -> 53250.08
A22: =+A21+1 -> 19 | B22: Cynthia Cole | Q22: =SUM(C22:P22) -> 0 | R22: 26915.7 | V22: 3416.98 | AG22: =SUM(R22:AF22) -> 30332.68 | AJ22: 2984.13 | AP22: =SUM(AH22:AO22) -> 2984.13 | AZ22: =SUM(AQ22:AY22) -> 0 | BI22: 0 | BJ22: 0 | BK22: =+Q22+AP22+AZ22+BE22+BH22+BI22+BJ22+BG22+AG22+BF22+BA22+BD22+BB22+BC22 -> 33316.81 | BL22: 30.5547 | BM22: =+$BL$22*BM2 -> 2444.376 | BN22: =+$BL$22*BN2 -> 2444.376 | BO22: =+$BL$22*BO2 -> 2444.376 | BP22: =+$BL$22*BP2 -> 2444.376 | BQ22: =+$BL$22*BQ2 -> 2444.376 | BR22: =+$BL$22*BR2 -> 2444.376 | BS22: =+$BL$22*BS2 -> 2444.376 | BT22: =+$BL$22*BT2 -> 2444.376 | ... BW22: =+$BL$22*BW2 -> 1711.0632 | BX22: =SUM(BM22:BW22) -> 26154.823 | BY22: =+BK22-BX22 -> 7161.9868 | CA22: =+BL22*2080 -> 63553.776
A23: =+A22+1 -> 20 | B23: Dagim McKonnen | Q23: =SUM(C23:P23) -> 0 | AG23: =SUM(R23:AF23) -> 0 | AK23: 31849.97 | AP23: =SUM(AH23:AO23) -> 31849.97 | AZ23: =SUM(AQ23:AY23) -> 0 | BK23: =+Q23+AP23+AZ23+BE23+BH23+BI23+BJ23+BG23+AG23+BF23+BA23+BD23+BB23+BC23 -> 31849.97 | BL23: 30.5547 | BM23: =+$BL$23*BM2 -> 2444.376 | BN23: =+$BL$23*BN2 -> 2444.376 | BO23: =+$BL$23*BO2 -> 2444.376 | BP23: =+$BL$23*BP2 -> 2444.376 | BQ23: =+$BL$23*BQ2 -> 2444.376 | BR23: =+$BL$23*BR2 -> 2444.376 | BS23: =+$BL$23*BS2 -> 2444.376 | BT23: =+$BL$23*BT2 -> 2444.376 | ... BW23: =+$BL$23*BW2 -> 1711.0632 | BX23: =SUM(BM23:BW23) -> 26154.823 | BY23: =+BK23-BX23 -> 5695.1468 | CA23: =+BL23*2080 -> 63553.776
A24: =+A23+1 -> 21 | B24: Desiree | Q24: =SUM(C24:P24) -> 0 | S24: 413.44 | U24: 683.51 | X24: 14021.38 | AE24: 1600 | AF24: 7051.92 | AG24: =SUM(R24:AF24) -> 23770.25 | AK24: 10396.92 | AL24: 800 | AO24: 1574.4 | AP24: =SUM(AH24:AO24) -> 12771.32 | AZ24: =SUM(AQ24:AY24) -> 0 | BA24: 3800 | BK24: =+Q24+AP24+AZ24+BE24+BH24+BI24+BJ24+BG24+AG24+BF24+BA24+BD24+BB24+BC24 -> 40341.57 | BL24: 36.5385 | BM24: =+$BL$24*BM2 -> 2923.08 | BN24: =+$BL$24*BN2 -> 2923.08 | BO24: =+$BL$24*BO2 -> 2923.08 | BP24: =+$BL$24*BP2 -> 2923.08 | BQ24: =+$BL$24*BQ2 -> 2923.08 | BR24: =+$BL$24*BR2 -> 2923.08 | BS24: =+$BL$24*BS2 -> 2923.08 | BT24: =+$BL$24*BT2 -> 2923.08 | ... BW24: =+$BL$24*BW2 -> 2046.156 | BX24: =SUM(BM24:BW24) -> 31276.956 | BY24: =+BK24-BX24 -> 9064.614 | CA24: =+BL24*2080 -> 76000.08
A25: =+A24+1 -> 22 | B25: Earnest | Q25: =SUM(C25:P25) -> 0 | AG25: =SUM(R25:AF25) -> 0 | AP25: =SUM(AH25:AO25) -> 0 | AT25: 26255.11 | AZ25: =SUM(AQ25:AY25) -> 26255.11 | BK25: =+Q25+AP25+AZ25+BE25+BH25+BI25+BJ25+BG25+AG25+BF25+BA25+BD25+BB25+BC25 -> 26255.11 | BL25: 24.0385 | BM25: =+$BL$25*BM2 -> 1923.08 | BN25: =+$BL$25*BN2 -> 1923.08 | BO25: =+$BL$25*BO2 -> 1923.08 | BP25: =+$BL$25*BP2 -> 1923.08 | BQ25: =+$BL$25*BQ2 -> 1923.08 | BR25: =+$BL$25*BR2 -> 1923.08 | BS25: =+$BL$25*BS2 -> 1923.08 | BT25: =+$BL$25*BT2 -> 1923.08 | ... BW25: =+$BL$25*BW2 -> 1346.156 | BX25: =SUM(BM25:BW25) -> 20576.956 | BY25: =+BK25-BX25 -> 5678.154 | CA25: =+BL25*2080 -> 50000.08
A26: =+A25+1 -> 23 | B26: Eftihia | Q26: =SUM(C26:P26) -> 0 | AG26: =SUM(R26:AF26) -> 0 | AP26: =SUM(AH26:AO26) -> 0 | AS26: 33624.85 | AZ26: =SUM(AQ26:AY26) -> 33624.85 | BK26: =+Q26+AP26+AZ26+BE26+BH26+BI26+BJ26+BG26+AG26+BF26+BA26+BD26+BB26+BC26 -> 33624.85 | BL26: 32.2571 | BM26: =+$BL$26*BM2 -> 2580.568 | BN26: =+$BL$26*BN2 -> 2580.568 | BO26: =+$BL$26*BO2 -> 2580.568 | BP26: =+$BL$26*BP2 -> 2580.568 | BQ26: =+$BL$26*BQ2 -> 2580.568 | BR26: =+$BL$26*BR2 -> 2580.568 | BS26: =+$BL$26*BS2 -> 2580.568 | BT26: =+$BL$26*BT2 -> 2580.568 | ... BW26: =+$BL$26*BW2 -> 1806.3976 | BX26: =SUM(BM26:BW26) -> 27612.078 | BY26: =+BK26-BX26 -> 6012.7724 | CA26: =+BL26*2080 -> 67094.768
A27: =+A26+1 -> 24 | B27: Egosia | Q27: =SUM(C27:P27) -> 0 | AG27: =SUM(R27:AF27) -> 0 | AL27: 26686.63 | AP27: =SUM(AH27:AO27) -> 26686.63 | AZ27: =SUM(AQ27:AY27) -> 0 | BK27: =+Q27+AP27+AZ27+BE27+BH27+BI27+BJ27+BG27+AG27+BF27+BA27+BD27+BB27+BC27 -> 26686.63 | BL27: 25.601 | BM27: =+$BL$27*BM2 -> 2048.08 | BN27: =+$BL$27*BN2 -> 2048.08 | BO27: =+$BL$27*BO2 -> 2048.08 | BP27: =+$BL$27*BP2 -> 2048.08 | BQ27: =+$BL$27*BQ2 -> 2048.08 | BR27: =+$BL$27*BR2 -> 2048.08 | BS27: =+$BL$27*BS2 -> 2048.08 | BT27: =+$BL$27*BT2 -> 2048.08 | ... BW27: =+$BL$27*BW2 -> 1433.656 | BX27: =SUM(BM27:BW27) -> 21914.456 | BY27: =+BK27-BX27 -> 4772.174 | CA27: =+BL27*2080 -> 53250.08
A28: =+A27+1 -> 25 | B28: Elizaabeth | Q28: =SUM(C28:P28) -> 0 | AG28: =SUM(R28:AF28) -> 0 | AM28: 29397.74 | AP28: =SUM(AH28:AO28) -> 29397.74 | AZ28: =SUM(AQ28:AY28) -> 0 | BK28: =+Q28+AP28+AZ28+BE28+BH28+BI28+BJ28+BG28+AG28+BF28+BA28+BD28+BB28+BC28 -> 29397.74 | BL28: 28.161 | BM28: =+$BL$28*BM2 -> 2252.88 | BN28: =+$BL$28*BN2 -> 2252.88 | BO28: =+$BL$28*BO2 -> 2252.88 | BP28: =+$BL$28*BP2 -> 2252.88 | BQ28: =+$BL$28*BQ2 -> 2252.88 | BR28: =+$BL$28*BR2 -> 2252.88 | BS28: =+$BL$28*BS2 -> 2252.88 | BT28: =+$BL$28*BT2 -> 2252.88 | ... BW28: =+$BL$28*BW2 -> 1577.016 | BX28: =SUM(BM28:BW28) -> 24105.816 | BY28: =+BK28-BX28 -> 5291.924 | CA28: =+BL28*2080 -> 58574.88
A29: =+A28+1 -> 26 | B29: Emebet Ashagre | H29: 5653.86 | M29: 1558.65 | O29: 926.92 | Q29: =SUM(C29:P29) -> 8139.43 | S29: 8031.41 | AC29: 1600 | AE29: 2000 | AF29: 3500 | AG29: =SUM(R29:AF29) -> 15131.41 | AH29: 0 | AI29: 0 | AP29: =SUM(AH29:AO29) -> 0 | AS29: 3648.07 | AT29: 875.97 | AV29: 3745.18 | AW29: 1600 | AY29: 1600 | AZ29: =SUM(AQ29:AY29) -> 11469.22 | BD29: 2100 | BK29: =+Q29+AP29+AZ29+BE29+BH29+BI29+BJ29+BG29+AG29+BF29+BA29+BD29+BB29+BC29 -> 36840.06 | BL29: 33.6539 | BM29: =+$BL$29*BM2 -> 2692.312 | BN29: =+$BL$29*BN2 -> 2692.312 | BO29: =+$BL$29*BO2 -> 2692.312 | BP29: =+$BL$29*BP2 -> 2692.312 | BQ29: =+$BL$29*BQ2 -> 2692.312 | BR29: =+$BL$29*BR2 -> 2692.312 | BS29: =+$BL$29*BS2 -> 2692.312 | BT29: =+$BL$29*BT2 -> 2692.312 | ... BW29: =+$BL$29*BW2 -> 1884.6184 | BX29: =SUM(BM29:BW29) -> 28807.738 | BY29: =+BK29-BX29 -> 8032.3216 | CA29: =+BL29*2080 -> 70000.112
A30: 27 | B30: TBH - Marc Aldor | Q30: =SUM(C30:P30) -> 0 | AD30: 28336.18 | AG30: =SUM(R30:AF30) -> 28336.18 | BK30: =+Q30+AP30+AZ30+BE30+BH30+BI30+BJ30+BG30+AG30+BF30+BA30+BD30+BB30+BC30 -> 28336.18 | BY30: =+BK30-BX30 -> 28336.18 | CA30: =+BL30*2080 -> 0
A31: 28 | B31: TBH - Employment Speecialist | N31: 26000 | Q31: =SUM(C31:P31) -> 26000 | AD31: 0 | AG31: =SUM(R31:AF31) -> 0 | AJ31: 0 | AK31: 0 | AP31: =SUM(AH31:AO31) -> 0 | AT31: 0 | AZ31: =SUM(AQ31:AY31) -> 0 | BD31: 0 | BK31: =+Q31+AP31+AZ31+BE31+BH31+BI31+BJ31+BG31+AG31+BF31+BA31+BD31+BB31+BC31 -> 26000 | BL31: 0 | BM31: =+$BL$31*BM2 -> 0 | BN31: =+$BL$31*BN2 -> 0 | BO31: =+$BL$31*BO2 -> 0 | BP31: =+$BL$31*BP2 -> 0 | BQ31: =+$BL$31*BQ2 -> 0 | BR31: =+$BL$31*BR2 -> 0 | BS31: =+$BL$31*BS2 -> 0 | BT31: =+$BL$31*BT2 -> 0 | ... BW31: =+$BL$31*BW2 -> 0 | BX31: =SUM(BM31:BW31) -> 0 | BY31: =+BK31-BX31 -> 26000 | CA31: =+BL31*2080 -> 0
A32: =+A31+1 -> 29 | B32: Esra Bayrakthar | F32: 3192.92 | L32: 178.86 | Q32: =SUM(C32:P32) -> 3371.78 | AG32: =SUM(R32:AF32) -> 0 | AH32: 0 | AI32: 0 | AJ32: 3980.05 | AP32: =SUM(AH32:AO32) -> 3980.05 | AT32: 37176.16 | AZ32: =SUM(AQ32:AY32) -> 37176.16 | BK32: =+Q32+AP32+AZ32+BE32+BH32+BI32+BJ32+BG32+AG32+BF32+BA32+BD32+BB32+BC32 -> 44527.99 | BL32: 40.9583 | BM32: =+$BL$32*BM2 -> 3276.664 | BN32: =+$BL$32*BN2 -> 3276.664 | BO32: =+$BL$32*BO2 -> 3276.664 | BP32: =+$BL$32*BP2 -> 3276.664 | BQ32: =+$BL$32*BQ2 -> 3276.664 | BR32: =+$BL$32*BR2 -> 3276.664 | BS32: =+$BL$32*BS2 -> 3276.664 | BT32: =+$BL$32*BT2 -> 3276.664 | ... BW32: =+$BL$32*BW2 -> 2293.6648 | BX32: =SUM(BM32:BW32) -> 35060.305 | BY32: =+BK32-BX32 -> 9467.6852 | CA32: =+BL32*2080 -> 85193.264
A33: =+A32+1 -> 30 | B33: Evette | Q33: =SUM(C33:P33) -> 0 | S33: 13036 | V33: 1084 | AG33: =SUM(R33:AF33) -> 14120 | AP33: =SUM(AH33:AO33) -> 0 | AZ33: =SUM(AQ33:AY33) -> 0 | BK33: =+Q33+AP33+AZ33+BE33+BH33+BI33+BJ33+BG33+AG33+BF33+BA33+BD33+BB33+BC33 -> 14120 | BL33: 20 | BM33: =+$BL$33*70 -> 1400 | BN33: =+$BL$33*70 -> 1400 | BO33: =+$BL$33*70 -> 1400 | BP33: =+$BL$33*70 -> 1400 | BQ33: =+$BL$33*70 -> 1400 | BR33: =+$BL$33*70 -> 1400 | BS33: =+$BL$33*70 -> 1400 | BT33: =+$BL$33*70 -> 1400 | ... BV33: =+$BL$33*70 -> 1400 | BW33: 0 | BX33: =SUM(BM33:BW33) -> 14000 | BY33: =+BK33-BX33 -> 120 | CA33: =+BL33*2080 -> 41600
A34: =+A33+1 -> 31 | B34: TBH - FatIh Casken | Q34: =SUM(C34:P34) -> 0 | AG34: =SUM(R34:AF34) -> 0 | AK34: 35124.4 | AP34: =SUM(AH34:AO34) -> 35124.4 | AZ34: =SUM(AQ34:AY34) -> 0 | BK34: =+Q34+AP34+AZ34+BE34+BH34+BI34+BJ34+BG34+AG34+BF34+BA34+BD34+BB34+BC34 -> 35124.4 | BL34: 0 | BM34: =+$BL$34*BM2 -> 0 | BN34: =+$BL$34*BN2 -> 0 | BO34: =+$BL$34*BO2 -> 0 | BP34: =+$BL$34*BP2 -> 0 | BQ34: =+$BL$34*BQ2 -> 0 | BR34: =+$BL$34*BR2 -> 0 | BS34: =+$BL$34*BS2 -> 0 | BT34: =+$BL$34*BT2 -> 0 | ... BW34: =+$BL$34*BW2 -> 0 | BX34: =SUM(BM34:BW34) -> 0 | BY34: =+BK34-BX34 -> 35124.4 | CA34: =+BL34*2080 -> 0
A35: =+A34+1 -> 32 | B35: Faye | Q35: =SUM(C35:P35) -> 0 | AG35: =SUM(R35:AF35) -> 0 | AP35: =SUM(AH35:AO35) -> 0 | AU35: 35551.61 | AZ35: =SUM(AQ35:AY35) -> 35551.61 | BK35: =+Q35+AP35+AZ35+BE35+BH35+BI35+BJ35+BG35+AG35+BF35+BA35+BD35+BB35+BC35 -> 35551.61 | BL35: 30.1809 | BM35: =+$BL$35*BM2 -> 2414.472 | BN35: =+$BL$35*BN2 -> 2414.472 | BO35: =+$BL$35*BO2 -> 2414.472 | BP35: =+$BL$35*BP2 -> 2414.472 | BQ35: =+$BL$35*BQ2 -> 2414.472 | BR35: =+$BL$35*BR2 -> 2414.472 | BS35: =+$BL$35*BS2 -> 2414.472 | BT35: =+$BL$35*BT2 -> 2414.472 | ... BW35: =+$BL$35*BW2 -> 1690.1304 | BX35: =SUM(BM35:BW35) -> 25834.85 | BY35: =+BK35-BX35 -> 9716.7596 | CA35: =+BL35*2080 -> 62776.272
A36: =+A35+1 -> 33 | B36: Ferdawok | F36: 15000 | Q36: =SUM(C36:P36) -> 15000 | AG36: =SUM(R36:AF36) -> 0 | AP36: =SUM(AH36:AO36) -> 0 | AZ36: =SUM(AQ36:AY36) -> 0 | BC36: 909.34 | BD36: 4182.99 | BH36: =441.86+6000 -> 6441.86 | BI36: 0 | BK36: =+Q36+AP36+AZ36+BE36+BH36+BI36+BJ36+BG36+AG36+BF36+BA36+BD36+BB36+BC36 -> 26534.19 | BL36: 28.4171 | BM36: =+$BL$36*BM2 -> 2273.368 | BN36: =+$BL$36*BN2 -> 2273.368 | BO36: =+$BL$36*BO2 -> 2273.368 | BP36: =+$BL$36*BP2 -> 2273.368 | BQ36: =+BP36 -> 2273.368 | BR36: =+BQ36 -> 2273.368 | BS36: =+BR36 -> 2273.368 | BT36: =+BS36 -> 2273.368 | BU36: =+BT36 -> 2273.368 | BV36: =+BU36 -> 2273.368 | BW36: =+BV36 -> 2273.368 | BX36: =SUM(BM36:BW36) -> 25007.048 | BY36: =+BK36-BX36 -> 1527.142 | CA36: =+BL36*2080 -> 59107.568
A37: =+A36+1 -> 34 | B37: Firdus | Q37: =SUM(C37:P37) -> 0 | AG37: =SUM(R37:AF37) -> 0 | AP37: =SUM(AH37:AO37) -> 0 | AZ37: =SUM(AQ37:AY37) -> 0 | BE37: =4031+1536+1386.62+2849.53 -> 9803.15 | BK37: =+Q37+AP37+AZ37+BE37+BH37+BI37+BJ37+BG37+AG37+BF37+BA37+BD37+BB37+BC37 -> 9803.15 | BL37: 24 | BM37: =+$BL$37*56 -> 1344 | BN37: =+BM37 -> 1344 | BO37: =+BN37 -> 1344 | BP37: =+BO37 -> 1344 | BQ37: =+BP37 -> 1344 | BR37: =+BQ37 -> 1344 | BS37: =+BR37 -> 1344 | BT37: 395.15 | BU37: 0 | BV37: 0 | BW37: 0 | BX37: =SUM(BM37:BW37) -> 9803.15 | BY37: =+BK37-BX37 -> 0 | CA37: =+BL37*2080 -> 49920
A38: =+A37+1 -> 35 | B38: Florance | Q38: =SUM(C38:P38) -> 0 | AG38: =SUM(R38:AF38) -> 0 | AP38: =SUM(AH38:AO38) -> 0 | AY38: 43861.32 | AZ38: =SUM(AQ38:AY38) -> 43861.32 | BK38: =+Q38+AP38+AZ38+BE38+BH38+BI38+BJ38+BG38+AG38+BF38+BA38+BD38+BB38+BC38 -> 43861.32 | BL38: 27.7771 | BM38: =+$BL$38*BM2 -> 2222.168 | BN38: =+$BL$38*BN2 -> 2222.168 | BO38: =+$BL$38*BO2 -> 2222.168 | BP38: =+$BL$38*BP2 -> 2222.168 | BQ38: =+$BL$38*BQ2 -> 2222.168 | BR38: =+$BL$38*BR2 -> 2222.168 | BS38: =+$BL$38*BS2 -> 2222.168 | BT38: =+$BL$38*BT2 -> 2222.168 | ... BW38: =+$BL$38*BW2 -> 1555.5176 | BX38: =SUM(BM38:BW38) -> 23777.198 | BY38: =+BK38-BX38 -> 20084.122 | CA38: =+BL38*2080 -> 57776.368
A39: 36 | B39: TBH - Mildred | P39: 16195.95 | Q39: =SUM(C39:P39) -> 16195.95 | AG39: =SUM(R39:AF39) -> 0 | BK39: =+Q39+AP39+AZ39+BE39+BH39+BI39+BJ39+BG39+AG39+BF39+BA39+BD39+BB39+BC39 -> 16195.95 | BY39: =+BK39-BX39 -> 16195.95 | CA39: =+BL39*2080 -> 0
A40: 37 | B40: Freshta Atmar | Q40: =SUM(C40:P40) -> 0 | AG40: =SUM(R40:AF40) -> 0 | AP40: =SUM(AH40:AO40) -> 0 | AT40: 0 | AX40: 20605.76 | AZ40: =SUM(AQ40:AY40) -> 20605.76 | BD40: 6250 | BK40: =+Q40+AP40+AZ40+BE40+BH40+BI40+BJ40+BG40+AG40+BF40+BA40+BD40+BB40+BC40 -> 26855.76 | BL40: 24.0385 | BM40: =+$BL$40*BM2 -> 1923.08 | BN40: =+$BL$40*BN2 -> 1923.08 | BO40: =+$BL$40*BO2 -> 1923.08 | BP40: =+$BL$40*BP2 -> 1923.08 | BQ40: =+$BL$40*BQ2 -> 1923.08 | BR40: =+$BL$40*BR2 -> 1923.08 | BS40: =+$BL$40*BS2 -> 1923.08 | BT40: =+$BL$40*BT2 -> 1923.08 | ... BW40: =+$BL$40*BW2 -> 1346.156 | BX40: =SUM(BM40:BW40) -> 20576.956 | BY40: =+BK40-BX40 -> 6278.804 | CA40: =+BL40*2080 -> 50000.08
A41: =+A40+1 -> 38 | B41: Frishta Khalil | Q41: =SUM(C41:P41) -> 0 | AG41: =SUM(R41:AF41) -> 0 | AH41: 25057.65 | AP41: =SUM(AH41:AO41) -> 25057.65 | AZ41: =SUM(AQ41:AY41) -> 0 | BK41: =+Q41+AP41+AZ41+BE41+BH41+BI41+BJ41+BG41+AG41+BF41+BA41+BD41+BB41+BC41 -> 25057.65 | BL41: 24.0385 | BM41: =$BL$41*BM2 -> 1923.08 | BN41: =$BL$41*BN2 -> 1923.08 | BO41: =$BL$41*BO2 -> 1923.08 | BP41: =$BL$41*BP2 -> 1923.08 | BQ41: =$BL$41*BQ2 -> 1923.08 | BR41: =$BL$41*BR2 -> 1923.08 | BS41: =$BL$41*BS2 -> 1923.08 | BT41: =$BL$41*BT2 -> 1923.08 | ... BW41: =$BL$41*BW2 -> 1346.156 | BX41: =SUM(BM41:BW41) -> 20576.956 | BY41: =+BK41-BX41 -> 4480.694 | CA41: =+BL41*2080 -> 50000.08
A42: =+A41+1 -> 39 | B42: Ganna | Q42: =SUM(C42:P42) -> 0 | AD42: 23296.19 | AG42: =SUM(R42:AF42) -> 23296.19 | AO42: 38871.34 | AP42: =SUM(AH42:AO42) -> 38871.34 | AZ42: =SUM(AQ42:AY42) -> 0 | BK42: =+Q42+AP42+AZ42+BE42+BH42+BI42+BJ42+BG42+AG42+BF42+BA42+BD42+BB42+BC42 -> 62167.53 | BL42: 25.601 | BM42: =$BL$42*BM2 -> 2048.08 | BN42: =$BL$42*BN2 -> 2048.08 | BO42: =$BL$42*BO2 -> 2048.08 | BP42: =$BL$42*BP2 -> 2048.08 | BQ42: =$BL$42*BQ2 -> 2048.08 | BR42: =$BL$42*BR2 -> 2048.08 | BS42: =$BL$42*BS2 -> 2048.08 | BT42: =$BL$42*BT2 -> 2048.08 | ... BW42: =$BL$42*BW2 -> 1433.656 | BX42: =SUM(BM42:BW42) -> 21914.456 | BY42: =+BK42-BX42 -> 40253.074 | CA42: =+BL42*2080 -> 53250.08
A43: =+A42+1 -> 40 | B43: Parwana Noori | Q43: =SUM(C43:P43) -> 0 | AG43: =SUM(R43:AF43) -> 0 | AP43: =SUM(AH43:AO43) -> 0 | AT43: =28465.98-11400 -> 17065.98 | AZ43: =SUM(AQ43:AY43) -> 17065.98 | BD43: 3750 | BK43: =+Q43+AP43+AZ43+BE43+BH43+BI43+BJ43+BG43+AG43+BF43+BA43+BD43+BB43+BC43 -> 20815.98 | BL43: 24.0385 | BM43: 0 | BN43: 0 | BO43: =$BL$43*BO2 -> 1923.08 | BP43: =$BL$43*BP2 -> 1923.08 | BQ43: =$BL$43*BQ2 -> 1923.08 | BR43: =$BL$43*BR2 -> 1923.08 | BS43: =$BL$43*BS2 -> 1923.08 | BT43: =$BL$43*BT2 -> 1923.08 | BU43: =$BL$43*BU2 -> 1923.08 | BV43: =$BL$43*BV2 -> 1923.08 | BW43: 0 | BX43: =SUM(BM43:BW43) -> 15384.64 | BY43: =+BK43-BX43 -> 5431.34 | CA43: =+BL43*2080 -> 50000.08
B44: TBH - Gazala Wardak | AT44: 11400 | AZ44: =SUM(AQ44:AY44) -> 11400 | BD44: 3813.23 | BK44: =+Q44+AP44+AZ44+BE44+BH44+BI44+BJ44+BG44+AG44+BF44+BA44+BD44+BB44+BC44 -> 15213.23 | BL44: 0 | BY44: =+BK44-BX44 -> 15213.23 | CA44: =+BL44*2080 -> 0
A45: =+A43+1 -> 41 | B45: Gelila | Q45: =SUM(C45:P45) -> 0 | AG45: =SUM(R45:AF45) -> 0 | AO45: 32615.28 | AP45: =SUM(AH45:AO45) -> 32615.28 | AZ45: =SUM(AQ45:AY45) -> 0 | BK45: =+Q45+AP45+AZ45+BE45+BH45+BI45+BJ45+BG45+AG45+BF45+BA45+BD45+BB45+BC45 -> 32615.28 | BL45: 24.0385 | BM45: =+$BL$45*BM2 -> 1923.08 | BN45: =+$BL$45*BN2 -> 1923.08 | BO45: =+$BL$45*BO2 -> 1923.08 | BP45: =+$BL$45*BP2 -> 1923.08 | BQ45: =+$BL$45*BQ2 -> 1923.08 | BR45: =+$BL$45*BR2 -> 1923.08 | BS45: =+$BL$45*BS2 -> 1923.08 | BT45: =+$BL$45*BT2 -> 1923.08 | ... BW45: =+$BL$45*BW2 -> 1346.156 | BX45: =SUM(BM45:BW45) -> 20576.956 | BY45: =+BK45-BX45 -> 12038.324 | CA45: =+BL45*2080 -> 50000.08
A46: =+A45+1 -> 42 | B46: Hamdard | H46: =11623.91+6500 -> 18123.91 | M46: 4050 | Q46: =SUM(C46:P46) -> 22173.91 | AG46: =SUM(R46:AF46) -> 0 | AP46: =SUM(AH46:AO46) -> 0 | AZ46: =SUM(AQ46:AY46) -> 0 | BB46: 1906.25 | BC46: 500 | BD46: 3851.29 | BK46: =+Q46+AP46+AZ46+BE46+BH46+BI46+BJ46+BG46+AG46+BF46+BA46+BD46+BB46+BC46 -> 28431.45 | BL46: 31.25 | BM46: =+$BL$46*BM2 -> 2500 | BN46: =+$BL$46*BN2 -> 2500 | BO46: =+$BL$46*BO2 -> 2500 | BP46: =+$BL$46*BP2 -> 2500 | BQ46: =+$BL$46*BQ2 -> 2500 | BR46: =+$BL$46*BR2 -> 2500 | BS46: =+$BL$46*BS2 -> 2500 | BT46: =+$BL$46*BT2 -> 2500 | ... BW46: =+$BL$46*BW2 -> 1750 | BX46: =SUM(BM46:BW46) -> 26750 | BY46: =+BK46-BX46 -> 1681.45 | CA46: =+BL46*2080 -> 65000
A47: =+A46+1 -> 43 | B47: Helen Gebru | H47: 0 | I47: 7877.25 | M47: 2550 | N47: 1741.34 | O47: 1700 | Q47: =SUM(C47:P47) -> 13868.59 | AC47: 1066 | AD47: 1741.35 | AE47: 1959.62 | AF47: 3750 | AG47: =SUM(R47:AF47) -> 8516.97 | AH47: 0 | AI47: 0 | AJ47: 15432.7 | AP47: =SUM(AH47:AO47) -> 15432.7 | AX47: 5357.68 | AY47: 1700 | AZ47: =SUM(AQ47:AY47) -> 7057.68 | BA47: 375 | BD47: 2250 | BK47: =+Q47+AP47+AZ47+BE47+BH47+BI47+BJ47+BG47+AG47+BF47+BA47+BD47+BB47+BC47 -> 47500.94 | BL47: 36.05769 | BM47: =+$BL$47*BM2 -> 2884.6152 | BN47: =+$BL$47*BN2 -> 2884.6152 | BO47: =+$BL$47*BO2 -> 2884.6152 | BP47: =+$BL$47*BP2 -> 2884.6152 | BQ47: =+$BL$47*BQ2 -> 2884.6152 | BR47: =+$BL$47*BR2 -> 2884.6152 | BS47: =+$BL$47*BS2 -> 2884.6152 | BT47: =+$BL$47*BT2 -> 2884.6152 | ... BW47: =+$BL$47*BW2 -> 2019.2306 | BX47: =SUM(BM47:BW47) -> 30865.383 | BY47: =+BK47-BX47 -> 16635.557 | CA47: =+BL47*2080 -> 74999.995
A48: =+A47+1 -> 44 | B48: Henok | Q48: =SUM(C48:P48) -> 0 | AG48: =SUM(R48:AF48) -> 0 | AJ48: 25557.65 | AP48: =SUM(AH48:AO48) -> 25557.65 | AZ48: =SUM(AQ48:AY48) -> 0 | BK48: =+Q48+AP48+AZ48+BE48+BH48+BI48+BJ48+BG48+AG48+BF48+BA48+BD48+BB48+BC48 -> 25557.65 | BL48: 24.0385 | BM48: =+$BL$48*BM2 -> 1923.08 | BN48: =+$BL$48*BN2 -> 1923.08 | BO48: =+$BL$48*BO2 -> 1923.08 | BP48: =+$BL$48*BP2 -> 1923.08 | BQ48: =+$BL$48*BQ2 -> 1923.08 | BR48: =+$BL$48*BR2 -> 1923.08 | BS48: =+$BL$48*BS2 -> 1923.08 | BT48: =+$BL$48*BT2 -> 1923.08 | ... BW48: =+$BL$48*BW2 -> 1346.156 | BX48: =SUM(BM48:BW48) -> 20576.956 | BY48: =+BK48-BX48 -> 4980.694 | CA48: =+BL48*2080 -> 50000.08
A49: =+A48+1 -> 45 | B49: Ibraham Diallo | Q49: =SUM(C49:P49) -> 0 | AG49: =SUM(R49:AF49) -> 0 | AN49: 21915 | AP49: =SUM(AH49:AO49) -> 21915 | AZ49: =SUM(AQ49:AY49) -> 0 | BK49: =+Q49+AP49+AZ49+BE49+BH49+BI49+BJ49+BG49+AG49+BF49+BA49+BD49+BB49+BC49 -> 21915 | BL49: 25.601 | BM49: =+$BL$49*BM2 -> 2048.08 | BN49: =+$BL$49*BN2 -> 2048.08 | BO49: =+$BL$49*BO2 -> 2048.08 | BP49: =+$BL$49*BP2 -> 2048.08 | BQ49: =+$BL$49*BQ2 -> 2048.08 | BR49: =+$BL$49*BR2 -> 2048.08 | BS49: =+$BL$49*BS2 -> 2048.08 | BT49: =+$BL$49*BT2 -> 2048.08 | ... BW49: =+$BL$49*BW2 -> 1433.656 | BX49: =SUM(BM49:BW49) -> 21914.456 | BY49: =+BK49-BX49 -> 0.544 | CA49: =+BL49*2080 -> 53250.08
A50: =+A49+1 -> 46 | B50: Indigo | Q50: =SUM(C50:P50) -> 0 | AG50: =SUM(R50:AF50) -> 0 | AH50: 19782.62 | AP50: =SUM(AH50:AO50) -> 19782.62 | AZ50: =SUM(AQ50:AY50) -> 0 | BK50: =+Q50+AP50+AZ50+BE50+BH50+BI50+BJ50+BG50+AG50+BF50+BA50+BD50+BB50+BC50 -> 19782.62 | BL50: 24.0385 | BM50: =+$BL$50*BM2 -> 1923.08 | BN50: =+$BL$50*BN2 -> 1923.08 | BO50: =+$BL$50*BO2 -> 1923.08 | BP50: =+$BL$50*BP2 -> 1923.08 | BQ50: =+$BL$50*BQ2 -> 1923.08 | BR50: =+$BL$50*BR2 -> 1923.08 | BS50: =+$BL$50*BS2 -> 1923.08 | BT50: =+$BL$50*BT2 -> 1923.08 | ... BW50: =+$BL$50*BW2 -> 1346.156 | BX50: =SUM(BM50:BW50) -> 20576.956 | BY50: =+BK50-BX50 -> -794.336 | CA50: =+BL50*2080 -> 50000.08
A51: =+A50+1 -> 47 | B51: Iriana Lessen | Q51: =SUM(C51:P51) -> 0 | V51: 0 | AG51: =SUM(R51:AF51) -> 0 | AJ51: =25024.79+1000+4362.14+0.29 -> 30387.22 | AP51: =SUM(AH51:AO51) -> 30387.22 | AZ51: =SUM(AQ51:AY51) -> 0 | BK51: =+Q51+AP51+AZ51+BE51+BH51+BI51+BJ51+BG51+AG51+BF51+BA51+BD51+BB51+BC51 -> 30387.22 | BL51: 30.1809 | BM51: =+$BL$51*BM2 -> 2414.472 | BN51: =+$BL$51*BN2 -> 2414.472 | BO51: =+$BL$51*BO2 -> 2414.472 | BP51: =+$BL$51*BP2 -> 2414.472 | BQ51: =+$BL$51*BQ2 -> 2414.472 | BR51: =+$BL$51*BR2 -> 2414.472 | BS51: =+$BL$51*BS2 -> 2414.472 | BT51: =+$BL$51*BT2 -> 2414.472 | ... BW51: =+$BL$51*BW2 -> 1690.1304 | BX51: =SUM(BM51:BW51) -> 25834.85 | BY51: =+BK51-BX51 -> 4552.3696 | CA51: =+BL51*2080 -> 62776.272
A52: =+A51+1 -> 48 | B52: Iryna Gaiduk | G52: 1523.12 | H52: 5844.58 | O52: 5335.2 | Q52: =SUM(C52:P52) -> 12702.9 | AG52: =SUM(R52:AF52) -> 0 | AH52: 0 | AI52: 0 | AP52: =SUM(AH52:AO52) -> 0 | AW52: 28122.88 | AX52: 1133.4 | AY52: 1560 | AZ52: =SUM(AQ52:AY52) -> 30816.28 | BK52: =+Q52+AP52+AZ52+BE52+BH52+BI52+BJ52+BG52+AG52+BF52+BA52+BD52+BB52+BC52 -> 43519.18 | BL52: 30.5547 | BM52: =+$BL$52*BM2 -> 2444.376 | BN52: =+$BL$52*BN2 -> 2444.376 | BO52: =+$BL$52*BO2 -> 2444.376 | BP52: =+$BL$52*BP2 -> 2444.376 | BQ52: =+$BL$52*BQ2 -> 2444.376 | BR52: =+$BL$52*BR2 -> 2444.376 | BS52: =+$BL$52*BS2 -> 2444.376 | BT52: =+$BL$52*BT2 -> 2444.376 | ... BW52: =+$BL$52*BW2 -> 1711.0632 | BX52: =SUM(BM52:BW52) -> 26154.823 | BY52: =+BK52-BX52 -> 17364.357 | CA52: =+BL52*2080 -> 63553.776
A53: =+A52+1 -> 49 | B53: Jamal Noori | Q53: =SUM(C53:P53) -> 0 | AG53: =SUM(R53:AF53) -> 0 | AP53: =SUM(AH53:AO53) -> 0 | AX53: 21869.24 | AZ53: =SUM(AQ53:AY53) -> 21869.24 | BC53: 1126.44 | BD53: 23429.95 | BK53: =+Q53+AP53+AZ53+BE53+BH53+BI53+BJ53+BG53+AG53+BF53+BA53+BD53+BB53+BC53 -> 46425.63 | BL53: 28.161 | BM53: =+$BL$53*BM2 -> 2252.88 | BN53: =+$BL$53*BN2 -> 2252.88 | BO53: =+$BL$53*BO2 -> 2252.88 | BP53: =+$BL$53*BP2 -> 2252.88 | BQ53: =+$BL$53*BQ2 -> 2252.88 | BR53: =+$BL$53*BR2 -> 2252.88 | BS53: =+$BL$53*BS2 -> 2252.88 | BT53: =+$BL$53*BT2 -> 2252.88 | ... BW53: =+$BL$53*BW2 -> 1577.016 | BX53: =SUM(BM53:BW53) -> 24105.816 | BY53: =+BK53-BX53 -> 22319.814 | CA53: =+BL53*2080 -> 58574.88
A54: =+A53+1 -> 50 | B54: Jean | Q54: =SUM(C54:P54) -> 0 | AG54: =SUM(R54:AF54) -> 0 | AP54: =SUM(AH54:AO54) -> 0 | AR54: 28000.88 | AZ54: =SUM(AQ54:AY54) -> 28000.88 | BK54: =+Q54+AP54+AZ54+BE54+BH54+BI54+BJ54+BG54+AG54+BF54+BA54+BD54+BB54+BC54 -> 28000.88 | BL54: 27.777 | BM54: =+$BL$54*BM2 -> 2222.16 | BN54: =+$BL$54*BN2 -> 2222.16 | BO54: =+$BL$54*BO2 -> 2222.16 | BP54: =+$BL$54*BP2 -> 2222.16 | BQ54: =+$BL$54*BQ2 -> 2222.16 | BR54: =+$BL$54*BR2 -> 2222.16 | BS54: =+$BL$54*BS2 -> 2222.16 | BT54: =+$BL$54*BT2 -> 2222.16 | ... BW54: =+$BL$54*BW2 -> 1555.512 | BX54: =SUM(BM54:BW54) -> 23777.112 | BY54: =+BK54-BX54 -> 4223.768 | CA54: =+BL54*2080 -> 57776.16
A55: =+A54+1 -> 51 | B55: Jehanzeb Louis | H55: 2923.07 | O55: 1315.38 | Q55: =SUM(C55:P55) -> 4238.45 | AG55: =SUM(R55:AF55) -> 0 | AH55: 0 | AI55: 0 | AP55: =SUM(AH55:AO55) -> 0 | AQ55: 780 | AR55: 850 | AS55: 4730.79 | AT55: 26884.61 | AV55: 73.06 | AW55: 1700 | AX55: 6800 | AY55: 1700 | AZ55: =SUM(AQ55:AY55) -> 43518.46 | BD55: 2000 | BE55: 0 | BG55: =4891.08-291.04 -> 4600.04 | BK55: =+Q55+AP55+AZ55+BE55+BH55+BI55+BJ55+BG55+AG55+BF55+BA55+BD55+BB55+BC55 -> 54356.95 | BL55: 38.4615 | BM55: =+$BL$55*BM2 -> 3076.92 | BN55: =+$BL$55*BN2 -> 3076.92 | BO55: =+$BL$55*BO2 -> 3076.92 | BP55: =+$BL$55*BP2 -> 3076.92 | BQ55: =+$BL$55*BQ2 -> 3076.92 | BR55: =+$BL$55*BR2 -> 3076.92 | BS55: =+$BL$55*BS2 -> 3076.92 | BT55: =+$BL$55*BT2 -> 3076.92 | ... BW55: =+$BL$55*BW2 -> 2153.844 | BX55: =SUM(BM55:BW55) -> 32923.044 | BY55: =+BK55-BX55 -> 21433.906 | CA55: =+BL55*2080 -> 79999.92
A56: =+A55+1 -> 52 | B56: Jeremy Schimmel | Q56: =SUM(C56:P56) -> 0 | AG56: =SUM(R56:AF56) -> 0 | AK56: 18001.17 | AP56: =SUM(AH56:AO56) -> 18001.17 | AZ56: =SUM(AQ56:AY56) -> 0 | BA56: 17923 | BB56: 896.16 | BK56: =+Q56+AP56+AZ56+BE56+BH56+BI56+BJ56+BG56+AG56+BF56+BA56+BD56+BB56+BC56 -> 36820.33 | BL56: 28.0049 | BM56: =+$BL$56*BM2 -> 2240.392 | BN56: =+$BL$56*BN2 -> 2240.392 | BO56: =+$BL$56*BO2 -> 2240.392 | BP56: =+$BL$56*BP2 -> 2240.392 | BQ56: =+$BL$56*BQ2 -> 2240.392 | BR56: =+$BL$56*BR2 -> 2240.392 | BS56: =+$BL$56*BS2 -> 2240.392 | BT56: =+$BL$56*BT2 -> 2240.392 | ... BW56: =+$BL$56*BW2 -> 1568.2744 | BX56: =SUM(BM56:BW56) -> 23972.194 | BY56: =+BK56-BX56 -> 12848.136 | CA56: =+BL56*2080 -> 58250.192
A57: =+A56+1 -> 53 | B57: Kamela Azizi | Q57: =SUM(C57:P57) -> 0 | AG57: =SUM(R57:AF57) -> 0 | AK57: 45162.03 | AP57: =SUM(AH57:AO57) -> 45162.03 | AZ57: =SUM(AQ57:AY57) -> 0 | BK57: =+Q57+AP57+AZ57+BE57+BH57+BI57+BJ57+BG57+AG57+BF57+BA57+BD57+BB57+BC57 -> 45162.03 | BL57: 28.161 | BM57: =+$BL$57*BM2 -> 2252.88 | BN57: =+$BL$57*BN2 -> 2252.88 | BO57: =+$BL$57*BO2 -> 2252.88 | BP57: =+$BL$57*BP2 -> 2252.88 | BQ57: =+$BL$57*BQ2 -> 2252.88 | BR57: =+$BL$57*BR2 -> 2252.88 | BS57: =+$BL$57*BS2 -> 2252.88 | BT57: =+$BL$57*BT2 -> 2252.88 | ... BW57: =+$BL$57*BW2 -> 1577.016 | BX57: =SUM(BM57:BW57) -> 24105.816 | BY57: =+BK57-BX57 -> 21056.214 | CA57: =+BL57*2080 -> 58574.88
A58: =+A57+1 -> 54 | B58: Konjit | Q58: =SUM(C58:P58) -> 0 | AG58: =SUM(R58:AF58) -> 0 | AP58: =SUM(AH58:AO58) -> 0 | AZ58: =SUM(AQ58:AY58) -> 0 | BF58: 16379.55 | BH58: =13251.55-1778.26 -> 11473.29 | BK58: =+Q58+AP58+AZ58+BE58+BH58+BI58+BJ58+BG58+AG58+BF58+BA58+BD58+BB58+BC58 -> 27852.84 | BL58: 31.2588 | BM58: =+$BL$58*BM2 -> 2500.704 | BN58: =+$BL$58*BN2 -> 2500.704 | BO58: =+$BL$58*BO2 -> 2500.704 | BP58: =+$BL$58*BP2 -> 2500.704 | BQ58: =+$BL$58*BQ2 -> 2500.704 | BR58: =+$BL$58*BR2 -> 2500.704 | BS58: =+$BL$58*BS2 -> 2500.704 | BT58: =+$BL$58*BT2 -> 2500.704 | BU58: =+$BL$58*BU2 -> 2500.704 | BV58: =+BU58 -> 2500.704 | BW58: =+BV58 -> 2500.704 | BX58: =SUM(BM58:BW58) -> 27507.744 | BY58: =+BK58-BX58 -> 345.096 | CA58: =+BL58*2080 -> 65018.304
A59: =+A58+1 -> 55 | B59: Laryssa Romenko | E59: 2516.68 | H59: 8055.61 | N59: 3600 | O59: 14000.22 | Q59: =SUM(C59:P59) -> 28172.51 | AG59: =SUM(R59:AF59) -> 0 | AH59: 0 | AI59: 0 | AP59: =SUM(AH59:AO59) -> 0 | AW59: 3422.59 | AX59: 6240 | AY59: 1200 | AZ59: =SUM(AQ59:AY59) -> 10862.59 | BK59: =+Q59+AP59+AZ59+BE59+BH59+BI59+BJ59+BG59+AG59+BF59+BA59+BD59+BB59+BC59 -> 39035.1 | BL59: 27.7771 | BM59: =+$BL$59*BM2 -> 2222.168 | BN59: =+$BL$59*BN2 -> 2222.168 | BO59: =+$BL$59*BO2 -> 2222.168 | BP59: =+$BL$59*BP2 -> 2222.168 | BQ59: =+$BL$59*BQ2 -> 2222.168 | BR59: =+$BL$59*BR2 -> 2222.168 | BS59: =+$BL$59*BS2 -> 2222.168 | BT59: =+$BL$59*BT2 -> 2222.168 | ... BW59: =+$BL$59*BW2 -> 1555.5176 | BX59: =SUM(BM59:BW59) -> 23777.198 | BY59: =+BK59-BX59 -> 15257.902 | CA59: =+BL59*2080 -> 57776.368
A60: =+A59+1 -> 56 | B60: Lema | Q60: =SUM(C60:P60) -> 0 | AG60: =SUM(R60:AF60) -> 0 | AP60: =SUM(AH60:AO60) -> 0 | AZ60: =SUM(AQ60:AY60) -> 0 | BI60: 14307.63 | BJ60: 3557.69 | BK60: =+Q60+AP60+AZ60+BE60+BH60+BI60+BJ60+BG60+AG60+BF60+BA60+BD60+BB60+BC60 -> 17865.32 | BL60: 24.0385 | BM60: =+$BL$60*BM2 -> 1923.08 | BN60: =+$BL$60*BN2 -> 1923.08 | BO60: =+$BL$60*BO2 -> 1923.08 | BP60: =+$BL$60*BP2 -> 1923.08 | BQ60: =+$BL$60*BQ2 -> 1923.08 | BR60: =+$BL$60*BR2 -> 1923.08 | BS60: =+$BL$60*BS2 -> 1923.08 | BT60: =+$BL$60*BT2 -> 1923.08 | ... BW60: =+$BL$60*BW2 -> 1346.156 | BX60: =SUM(BM60:BW60) -> 20576.956 | BY60: =+BK60-BX60 -> -2711.636 | CA60: =+BL60*2080 -> 50000.08
A61: =+A60+1 -> 57 | B61: Leyu | Q61: =SUM(C61:P61) -> 0 | AG61: =SUM(R61:AF61) -> 0 | AN61: 20577 | AP61: =SUM(AH61:AO61) -> 20577 | AZ61: =SUM(AQ61:AY61) -> 0 | BK61: =+Q61+AP61+AZ61+BE61+BH61+BI61+BJ61+BG61+AG61+BF61+BA61+BD61+BB61+BC61 -> 20577 | BL61: 24.0385 | BM61: =+$BL$61*BM2 -> 1923.08 | BN61: =+$BL$61*BN2 -> 1923.08 | BO61: =+$BL$61*BO2 -> 1923.08 | BP61: =+$BL$61*BP2 -> 1923.08 | BQ61: =+$BL$61*BQ2 -> 1923.08 | BR61: =+$BL$61*BR2 -> 1923.08 | BS61: =+$BL$61*BS2 -> 1923.08 | BT61: =+$BL$61*BT2 -> 1923.08 | ... BW61: =+$BL$61*BW2 -> 1346.156 | BX61: =SUM(BM61:BW61) -> 20576.956 | BY61: =+BK61-BX61 -> 0.044 | CA61: =+BL61*2080 -> 50000.08
A62: =+A61+1 -> 58 | B62: Manizha Nuzhat | F62: 2815.45 | H62: 6500 | N62: 2212.04 | O62: 1434.8 | Q62: =SUM(C62:P62) -> 12962.29 | AD62: 6069.66 | AE62: 4434.8 | AF62: 2688.81 | AG62: =SUM(R62:AF62) -> 13193.27 | AH62: 0 | AI62: 0 | AP62: =SUM(AH62:AO62) -> 0 | AV62: 1163.89 | AW62: 945.92 | AX62: =2225.41+2599.1 -> 4824.51 | AY62: 1434.8 | AZ62: =SUM(AQ62:AY62) -> 8369.12 | BK62: =+Q62+AP62+AZ62+BE62+BH62+BI62+BJ62+BG62+AG62+BF62+BA62+BD62+BB62+BC62 -> 34524.68 | BL62: 30.5547 | BM62: =+$BL$62*BM2 -> 2444.376 | BN62: =+$BL$62*BN2 -> 2444.376 | BO62: =+$BL$62*BO2 -> 2444.376 | BP62: =+$BL$62*BP2 -> 2444.376 | BQ62: =+$BL$62*BQ2 -> 2444.376 | BR62: =+$BL$62*BR2 -> 2444.376 | BS62: =+$BL$62*BS2 -> 2444.376 | BT62: =+$BL$62*BT2 -> 2444.376 | ... BW62: =+$BL$62*BW2 -> 1711.0632 | BX62: =SUM(BM62:BW62) -> 26154.823 | BY62: =+BK62-BX62 -> 8369.8568 | CA62: =+BL62*2080 -> 63553.776
A63: 59 | B63: Maramjan Sadaqat | Q63: =SUM(C63:P63) -> 0 | V63: 16024.98 | AG63: =SUM(R63:AF63) -> 16024.98 | AJ63: 25538.45 | AK63: 0 | AP63: =SUM(AH63:AO63) -> 25538.45 | AZ63: =SUM(AQ63:AY63) -> 0 | BK63: =+Q63+AP63+AZ63+BE63+BH63+BI63+BJ63+BG63+AG63+BF63+BA63+BD63+BB63+BC63 -> 41563.43 | BL63: 24.0385 | BM63: =+$BL$63*BM2 -> 1923.08 | BN63: =+$BL$63*BN2 -> 1923.08 | BO63: =+$BL$63*BO2 -> 1923.08 | BP63: =+$BL$63*BP2 -> 1923.08 | BQ63: =+$BL$63*BQ2 -> 1923.08 | BR63: =+$BL$63*BR2 -> 1923.08 | BS63: =+$BL$63*BS2 -> 1923.08 | BT63: =+$BL$63*BT2 -> 1923.08 | ... BW63: =+$BL$63*BW2 -> 1346.156 | BX63: =SUM(BM63:BW63) -> 20576.956 | BY63: =+BK63-BX63 -> 20986.474 | CA63: =+BL63*2080 -> 50000.08
A64: =+A63+1 -> 60 | B64: Maryam | Q64: =SUM(C64:P64) -> 0 | AG64: =SUM(R64:AF64) -> 0 | AL64: 28486.61 | AP64: =SUM(AH64:AO64) -> 28486.61 | AZ64: =SUM(AQ64:AY64) -> 0 | BK64: =+Q64+AP64+AZ64+BE64+BH64+BI64+BJ64+BG64+AG64+BF64+BA64+BD64+BB64+BC64 -> 28486.61 | BL64: 24.0385 | BM64: =+$BL$64*BM2 -> 1923.08 | BN64: =+$BL$64*BN2 -> 1923.08 | BO64: =+$BL$64*BO2 -> 1923.08 | BP64: =+$BL$64*BP2 -> 1923.08 | BQ64: =+$BL$64*BQ2 -> 1923.08 | BR64: =+$BL$64*BR2 -> 1923.08 | BS64: =+$BL$64*BS2 -> 1923.08 | BT64: =+$BL$64*BT2 -> 1923.08 | ... BW64: =+$BL$64*BW2 -> 1346.156 | BX64: =SUM(BM64:BW64) -> 20576.956 | BY64: =+BK64-BX64 -> 7909.654 | CA64: =+BL64*2080 -> 50000.08
A65: =+A64+1 -> 61 | B65: Albab Azeze | Q65: =SUM(C65:P65) -> 0 | Z65: =3550-4.43 -> 3545.57 | AG65: =SUM(R65:AF65) -> 3545.57 | AJ65: 0 | AK65: 45098.07 | AP65: =SUM(AH65:AO65) -> 45098.07 | AZ65: =SUM(AQ65:AY65) -> 0 | BK65: =+Q65+AP65+AZ65+BE65+BH65+BI65+BJ65+BG65+AG65+BF65+BA65+BD65+BB65+BC65 -> 48643.64 | BL65: 24.0385 | BM65: =+$BL$65*BM2 -> 1923.08 | BN65: =+$BL$65*BN2 -> 1923.08 | BO65: =+$BL$65*BO2 -> 1923.08 | BP65: =+$BL$65*BP2 -> 1923.08 | BQ65: =+$BL$65*BQ2 -> 1923.08 | BR65: =+$BL$65*BR2 -> 1923.08 | BS65: =+$BL$65*BS2 -> 1923.08 | BT65: =+$BL$65*BT2 -> 1923.08 | ... BW65: =+$BL$65*BW2 -> 1346.156 | BX65: =SUM(BM65:BW65) -> 20576.956 | BY65: =+BK65-BX65 -> 28066.684 | CA65: =+BL65*2080 -> 50000.08
A66: =+A65+1 -> 62 | B66: Megdad | Q66: =SUM(C66:P66) -> 0 | AG66: =SUM(R66:AF66) -> 0 | AK66: 25730.94 | AP66: =SUM(AH66:AO66) -> 25730.94 | AZ66: =SUM(AQ66:AY66) -> 0 | BK66: =+Q66+AP66+AZ66+BE66+BH66+BI66+BJ66+BG66+AG66+BF66+BA66+BD66+BB66+BC66 -> 25730.94 | BL66: 27.777 | BM66: =+$BL$66*BM2 -> 2222.16 | BN66: =+$BL$66*BN2 -> 2222.16 | BO66: =+$BL$66*BO2 -> 2222.16 | BP66: =+$BL$66*BP2 -> 2222.16 | BQ66: =+$BL$66*BQ2 -> 2222.16 | BR66: =+$BL$66*BR2 -> 2222.16 | BS66: =+$BL$66*BS2 -> 2222.16 | BT66: =+$BL$66*BT2 -> 2222.16 | ... BW66: =+$BL$66*BW2 -> 1555.512 | BX66: =SUM(BM66:BW66) -> 23777.112 | BY66: =+BK66-BX66 -> 1953.828 | CA66: =+BL66*2080 -> 57776.16
A67: 63 | B67: Munsif Noor Ul Haq | Q67: =SUM(C67:P67) -> 0 | R67: 24068.23 | AC67: 2143.34 | AG67: =SUM(R67:AF67) -> 26211.57 | AP67: =SUM(AH67:AO67) -> 0 | AZ67: =SUM(AQ67:AY67) -> 0 | BK67: =+Q67+AP67+AZ67+BE67+BH67+BI67+BJ67+BG67+AG67+BF67+BA67+BD67+BB67+BC67 -> 26211.57 | BL67: 24.0385 | BM67: =+$BL$67*BM2 -> 1923.08 | BN67: =+$BL$67*BN2 -> 1923.08 | BO67: =+$BL$67*BO2 -> 1923.08 | BP67: =+$BL$67*BP2 -> 1923.08 | BQ67: =+$BL$67*BQ2 -> 1923.08 | BR67: =+$BL$67*BR2 -> 1923.08 | BS67: =+$BL$67*BS2 -> 1923.08 | BT67: =+$BL$67*BT2 -> 1923.08 | ... BW67: =+$BL$67*BW2 -> 1346.156 | BX67: =SUM(BM67:BW67) -> 20576.956 | BY67: =+BK67-BX67 -> 5634.614 | CA67: =+BL67*2080 -> 50000.08
A68: =+A67+1 -> 64 | B68: TBH - Myrah Osmani | Q68: =SUM(C68:P68) -> 0 | AG68: =SUM(R68:AF68) -> 0 | AP68: =SUM(AH68:AO68) -> 0 | AR68: 732 | AT68: 38301 | AZ68: =SUM(AQ68:AY68) -> 39033 | BC68: 499.99 | BD68: 5199.85 | BK68: =+Q68+AP68+AZ68+BE68+BH68+BI68+BJ68+BG68+AG68+BF68+BA68+BD68+BB68+BC68 -> 44732.84 | BL68: 33.3324 | BM68: =+$BL$68*BM2 -> 2666.592 | BN68: =+$BL$68*BN2 -> 2666.592 | BO68: =+$BL$68*BO2 -> 2666.592 | BP68: =+$BL$68*BP2 -> 2666.592 | BQ68: =+$BL$68*BQ2 -> 2666.592 | BR68: =+$BL$68*BR2 -> 2666.592 | BS68: =+$BL$68*BS2 -> 2666.592 | BT68: =+$BL$68*BT2 -> 2666.592 | ... BW68: =+$BL$68*BW2 -> 1866.6144 | BX68: =SUM(BM68:BW68) -> 28532.534 | BY68: =+BK68-BX68 -> 16200.306 | CA68: =+BL68*2080 -> 69331.392
A69: =+A68+1 -> 65 | B69: Najia | Q69: =SUM(C69:P69) -> 0 | AG69: =SUM(R69:AF69) -> 0 | AP69: =SUM(AH69:AO69) -> 0 | AQ69: =19509.59+300 -> 19809.59 | AS69: 6500 | AZ69: =SUM(AQ69:AY69) -> 26309.59 | BE69: 0 | BK69: =+Q69+AP69+AZ69+BE69+BH69+BI69+BJ69+BG69+AG69+BF69+BA69+BD69+BB69+BC69 -> 26309.59 | BL69: 30.7212 | BM69: =+$BL$69*BM2 -> 2457.696 | BN69: =+$BL$69*BN2 -> 2457.696 | BO69: =+$BL$69*BO2 -> 2457.696 | BP69: =+$BL$69*BP2 -> 2457.696 | BQ69: =+$BL$69*BQ2 -> 2457.696 | BR69: =+$BL$69*BR2 -> 2457.696 | BS69: =+$BL$69*BS2 -> 2457.696 | BT69: =+$BL$69*BT2 -> 2457.696 | ... BW69: =+$BL$69*BW2 -> 1720.3872 | BX69: =SUM(BM69:BW69) -> 26297.347 | BY69: =+BK69-BX69 -> 12.2428 | CA69: =+BL69*2080 -> 63900.096
A70: =+A69+1 -> 66 | B70: Nassrullah Mohibi | Q70: =SUM(C70:P70) -> 0 | AG70: =SUM(R70:AF70) -> 0 | AI70: 26686.63 | AP70: =SUM(AH70:AO70) -> 26686.63 | AZ70: =SUM(AQ70:AY70) -> 0 | BK70: =+Q70+AP70+AZ70+BE70+BH70+BI70+BJ70+BG70+AG70+BF70+BA70+BD70+BB70+BC70 -> 26686.63 | BL70: 25.601 | BM70: =+$BL$70*BM2 -> 2048.08 | BN70: =+$BL$70*BN2 -> 2048.08 | BO70: =+$BL$70*BO2 -> 2048.08 | BP70: =+$BL$70*BP2 -> 2048.08 | BQ70: =+$BL$70*BQ2 -> 2048.08 | BR70: =+$BL$70*BR2 -> 2048.08 | BS70: =+$BL$70*BS2 -> 2048.08 | BT70: =+$BL$70*BT2 -> 2048.08 | ... BW70: =+$BL$70*BW2 -> 1433.656 | BX70: =SUM(BM70:BW70) -> 21914.456 | BY70: =+BK70-BX70 -> 4772.174 | CA70: =+BL70*2080 -> 53250.08
A71: =+A70+1 -> 67 | B71: TBH - Rahila Azimi | Q71: =SUM(C71:P71) -> 0 | AC71: 28785.76 | AG71: =SUM(R71:AF71) -> 28785.76 | AP71: =SUM(AH71:AO71) -> 0 | BK71: =+Q71+AP71+AZ71+BE71+BH71+BI71+BJ71+BG71+AG71+BF71+BA71+BD71+BB71+BC71 -> 28785.76 | BL71: 0 | BM71: 0 | BN71: 0 | BO71: 0 | BP71: 0 | BQ71: 0 | BR71: 0 | BS71: 0 | BT71: 0 | BU71: 0 | BV71: 0 | BW71: 0 | BX71: =SUM(BM71:BW71) -> 0 | BY71: =+BK71-BX71 -> 28785.76 | CA71: =+BL71*2080 -> 0
A72: =+A71+1 -> 68 | B72: Razia Mahrami | Q72: =SUM(C72:P72) -> 0 | AG72: =SUM(R72:AF72) -> 0 | AK72: 33184.74 | AP72: =SUM(AH72:AO72) -> 33184.74 | AZ72: =SUM(AQ72:AY72) -> 0 | BK72: =+Q72+AP72+AZ72+BE72+BH72+BI72+BJ72+BG72+AG72+BF72+BA72+BD72+BB72+BC72 -> 33184.74 | BL72: 33.2813 | BM72: =+$BL$72*BM2 -> 2662.504 | BN72: =+$BL$72*BN2 -> 2662.504 | BO72: =+$BL$72*BO2 -> 2662.504 | BP72: =+$BL$72*BP2 -> 2662.504 | BQ72: =+$BL$72*BQ2 -> 2662.504 | BR72: =+$BL$72*BR2 -> 2662.504 | BS72: =+$BL$72*BS2 -> 2662.504 | BT72: =+$BL$72*BT2 -> 2662.504 | ... BW72: =+$BL$72*BW2 -> 1863.7528 | BX72: =SUM(BM72:BW72) -> 28488.793 | BY72: =+BK72-BX72 -> 4695.9472 | CA72: =+BL72*2080 -> 69225.104
A73: =+A72+1 -> 69 | B73: Ruby Diaz | Q73: =SUM(C73:P73) -> 0 | AG73: =SUM(R73:AF73) -> 0 | AK73: 21730.77 | AP73: =SUM(AH73:AO73) -> 21730.77 | AZ73: =SUM(AQ73:AY73) -> 0 | BA73: 6500 | BB73: 769.24 | BK73: =+Q73+AP73+AZ73+BE73+BH73+BI73+BJ73+BG73+AG73+BF73+BA73+BD73+BB73+BC73 -> 29000.01 | BL73: 24.0385 | BM73: =+$BL$73*BM2 -> 1923.08 | BN73: =+$BL$73*BN2 -> 1923.08 | BO73: =+$BL$73*BO2 -> 1923.08 | BP73: =+$BL$73*BP2 -> 1923.08 | BQ73: =+$BL$73*BQ2 -> 1923.08 | BR73: =+$BL$73*BR2 -> 1923.08 | BS73: =+$BL$73*BS2 -> 1923.08 | BT73: =+$BL$73*BT2 -> 1923.08 | ... BW73: =+$BL$73*BW2 -> 1346.156 | BX73: =SUM(BM73:BW73) -> 20576.956 | BY73: =+BK73-BX73 -> 8423.054 | CA73: =+BL73*2080 -> 50000.08
A74: =+A73+1 -> 70 | B74: Sana Amini | Q74: =SUM(C74:P74) -> 0 | U74: 153.37 | V74: 7238.37 | AA74: 3388.83 | AD74: 3759.46 | AE74: 6786.94 | AF74: 5000 | AG74: =SUM(R74:AF74) -> 26326.97 | AJ74: 8076.92 | AM74: 30795.61 | AP74: =SUM(AH74:AO74) -> 38872.53 | AZ74: =SUM(AQ74:AY74) -> 0 | BK74: =+Q74+AP74+AZ74+BE74+BH74+BI74+BJ74+BG74+AG74+BF74+BA74+BD74+BB74+BC74 -> 65199.5 | BL74: 24.0385 | BM74: =+$BL$74*BM2 -> 1923.08 | BN74: =+$BL$74*BN2 -> 1923.08 | BO74: =+$BL$74*BO2 -> 1923.08 | BP74: =+$BL$74*BP2 -> 1923.08 | BQ74: =+$BL$74*BQ2 -> 1923.08 | BR74: =+$BL$74*BR2 -> 1923.08 | BS74: =+$BL$74*BS2 -> 1923.08 | BT74: =+$BL$74*BT2 -> 1923.08 | ... BW74: =+$BL$74*BW2 -> 1346.156 | BX74: =SUM(BM74:BW74) -> 20576.956 | BY74: =+BK74-BX74 -> 44622.544 | CA74: =+BL74*2080 -> 50000.08
A75: =+A74+1 -> 71 | B75: Sarah Zullo | N75: 5400 | O75: 2700 | Q75: =SUM(C75:P75) -> 8100 | AC75: 1062.42 | AD75: 5400 | AE75: 5700 | AF75: 5218.01 | AG75: =SUM(R75:AF75) -> 17380.43 | AH75: 0 | AI75: 0 | AJ75: 750 | AK75: 3000 | AL75: 1350 | AM75: =3192.38-2301.15 -> 891.23 | AO75: =3592.42-23.79 -> 3568.63 | AP75: =SUM(AH75:AO75) -> 9559.86 | AQ75: =1350-590.91 -> 759.09 | AR75: 1350 | AS75: =5737.2 -> 5737.2 | AT75: 3027.85 | AU75: =4050-677.86 -> 3372.14 | AV75: 3019.67 | AW75: =2700-679.8 -> 2020.2 | AX75: 8791.08 | AY75: =2700-350.05 -> 2349.95 | AZ75: =SUM(AQ75:AY75) -> 30427.18 | BA75: 521.8 | BD75: 2609.01 | BI75: =3045.52-476.64 -> 2568.88 | BJ75: 0 | BK75: =+Q75+AP75+AZ75+BE75+BH75+BI75+BJ75+BG75+AG75+BF75+BA75+BD75+BB75+BC75 -> 71167.16 | BL75: 50.1732 | BM75: =+$BL$75*BM2 -> 4013.856 | BN75: =+$BL$75*BN2 -> 4013.856 | BO75: =+$BL$75*BO2 -> 4013.856 | BP75: =+$BL$75*BP2 -> 4013.856 | BQ75: =+$BL$75*BQ2 -> 4013.856 | BR75: =+$BL$75*BR2 -> 4013.856 | BS75: =+$BL$75*BS2 -> 4013.856 | BT75: =+$BL$75*BT2 -> 4013.856 | ... BW75: =+$BL$75*BW2 -> 2809.6992 | BX75: =SUM(BM75:BW75) -> 42948.259 | BY75: =+BK75-BX75 -> 28218.901 | CA75: =+BL75*2080 -> 104360.26
A76: =+A75+1 -> 72 | B76: Shakil Tabassum | M76: 3177.26 | N76: 230.55 | O76: 2118.17 | Q76: =SUM(C76:P76) -> 5525.98 | AC76: 0 | AD76: 778.12 | AE76: 812.68 | AF76: 4564.88 | AG76: =SUM(R76:AF76) -> 6155.68 | AH76: 0 | AI76: 0 | AK76: 3215.64 | AL76: 1059 | AM76: 1469.4 | AO76: 572.22 | AP76: =SUM(AH76:AO76) -> 6316.26 | AQ76: 136.89 | AR76: 136.89 | AS76: 6852.5 | AT76: 6074.97 | AU76: 2716.16 | AV76: 6643.88 | AW76: 2118.17 | AX76: 8472.69 | AY76: 734.88 | AZ76: =SUM(AQ76:AY76) -> 33887.03 | BA76: 479.54 | BD76: 2397.71 | BI76: 146.83 | BK76: =+Q76+AP76+AZ76+BE76+BH76+BI76+BJ76+BG76+AG76+BF76+BA76+BD76+BB76+BC76 -> 54909.03 | BL76: 46.1099 | BM76: =+$BL$76*BM2 -> 3688.792 | BN76: =+$BL$76*BN2 -> 3688.792 | BO76: =+$BL$76*BO2 -> 3688.792 | BP76: =+$BL$76*BP2 -> 3688.792 | BQ76: =+$BL$76*BQ2 -> 3688.792 | BR76: =+$BL$76*BR2 -> 3688.792 | BS76: =+$BL$76*BS2 -> 3688.792 | BT76: =+$BL$76*BT2 -> 3688.792 | ... BW76: =+$BL$76*BW2 -> 2582.1544 | BX76: =SUM(BM76:BW76) -> 39470.074 | BY76: =+BK76-BX76 -> 15438.956 | CA76: =+BL76*2080 -> 95908.592
A77: =+A76+1 -> 73 | B77: Slenka Flores | Q77: =SUM(C77:P77) -> 0 | AG77: =SUM(R77:AF77) -> 0 | AI77: 25057.63 | AP77: =SUM(AH77:AO77) -> 25057.63 | AZ77: =SUM(AQ77:AY77) -> 0 | BK77: =+Q77+AP77+AZ77+BE77+BH77+BI77+BJ77+BG77+AG77+BF77+BA77+BD77+BB77+BC77 -> 25057.63 | BL77: 24.0385 | BM77: =+$BL$77*BM2 -> 1923.08 | BN77: =+$BL$77*BN2 -> 1923.08 | BO77: =+$BL$77*BO2 -> 1923.08 | BP77: =+$BL$77*BP2 -> 1923.08 | BQ77: =+$BL$77*BQ2 -> 1923.08 | BR77: =+$BL$77*BR2 -> 1923.08 | BS77: =+$BL$77*BS2 -> 1923.08 | BT77: =+$BL$77*BT2 -> 1923.08 | ... BW77: =+$BL$77*BW2 -> 1346.156 | BX77: =SUM(BM77:BW77) -> 20576.956 | BY77: =+BK77-BX77 -> 4480.674 | CA77: =+BL77*2080 -> 50000.08
A78: =+A77+1 -> 74 | B78: Spencer | Q78: =SUM(C78:P78) -> 0 | W78: =49.36+748.96 -> 798.32 | X78: 1916.55 | AA78: 16.08 | AB78: 1778.44 | AD78: 18781.87 | AE78: 68.82 | AG78: =SUM(R78:AF78) -> 23360.08 | AM78: 17995.45 | AO78: 1800 | AP78: =SUM(AH78:AO78) -> 19795.45 | AZ78: =SUM(AQ78:AY78) -> 0 | BK78: =+Q78+AP78+AZ78+BE78+BH78+BI78+BJ78+BG78+AG78+BF78+BA78+BD78+BB78+BC78 -> 43155.53 | BL78: 32.6923 | BM78: =+$BL$78*BM2 -> 2615.384 | BN78: =+$BL$78*BN2 -> 2615.384 | BO78: =+$BL$78*BO2 -> 2615.384 | BP78: =+$BL$78*BP2 -> 2615.384 | BQ78: =+$BL$78*BQ2 -> 2615.384 | BR78: =+$BL$78*BR2 -> 2615.384 | BS78: =+$BL$78*BS2 -> 2615.384 | BT78: =+$BL$78*BT2 -> 2615.384 | ... BW78: =+$BL$78*BW2 -> 1830.7688 | BX78: =SUM(BM78:BW78) -> 27984.609 | BY78: =+BK78-BX78 -> 15170.921 | CA78: =+BL78*2080 -> 67999.984
A79: =+A78+1 -> 75 | B79: Tahera Azizi | F79: 6176.34 | L79: 18572.96 | M79: 3166.21 | Q79: =SUM(C79:P79) -> 27915.51 | AG79: =SUM(R79:AF79) -> 0 | AH79: 0 | AI79: 0 | AP79: =SUM(AH79:AO79) -> 0 | AZ79: =SUM(AQ79:AY79) -> 0 | BK79: =+Q79+AP79+AZ79+BE79+BH79+BI79+BJ79+BG79+AG79+BF79+BA79+BD79+BB79+BC79 -> 27915.51 | BL79: 28.0048 | BM79: =+$BL$79*BM2 -> 2240.384 | BN79: =+$BL$79*BN2 -> 2240.384 | BO79: =+$BL$79*BO2 -> 2240.384 | BP79: =+$BL$79*BP2 -> 2240.384 | BQ79: =+$BL$79*BQ2 -> 2240.384 | BR79: =+$BL$79*BR2 -> 2240.384 | BS79: =+$BL$79*BS2 -> 2240.384 | BT79: =+$BL$79*BT2 -> 2240.384 | ... BW79: =+$BL$79*BW2 -> 1568.2688 | BX79: =SUM(BM79:BW79) -> 23972.109 | BY79: =+BK79-BX79 -> 3943.4012 | CA79: =+BL79*2080 -> 58249.984
A80: =+A79+1 -> 76 | B80: Taylor | Q80: =SUM(C80:P80) -> 0 | AG80: =SUM(R80:AF80) -> 0 | AP80: =SUM(AH80:AO80) -> 0 | AY80: 32557.66 | AZ80: =SUM(AQ80:AY80) -> 32557.66 | BK80: =+Q80+AP80+AZ80+BE80+BH80+BI80+BJ80+BG80+AG80+BF80+BA80+BD80+BB80+BC80 -> 32557.66 | BL80: 24.0385 | BM80: =+$BL$80*BM2 -> 1923.08 | BN80: =+$BL$80*BN2 -> 1923.08 | BO80: =+$BL$80*BO2 -> 1923.08 | BP80: =+$BL$80*BP2 -> 1923.08 | BQ80: =+$BL$80*BQ2 -> 1923.08 | BR80: =+$BL$80*BR2 -> 1923.08 | BS80: =+$BL$80*BS2 -> 1923.08 | BT80: =+$BL$80*BT2 -> 1923.08 | ... BW80: =+$BL$80*BW2 -> 1346.156 | BX80: =SUM(BM80:BW80) -> 20576.956 | BY80: =+BK80-BX80 -> 11980.704 | CA80: =+BL80*2080 -> 50000.08
A81: 77 | B81: TBH | Q81: =SUM(C81:P81) -> 0 | V81: 23728.97 | AG81: =SUM(R81:AF81) -> 23728.97 | BK81: =+Q81+AP81+AZ81+BE81+BH81+BI81+BJ81+BG81+AG81+BF81+BA81+BD81+BB81+BC81 -> 23728.97 | BY81: =+BK81-BX81 -> 23728.97 | CA81: =+BL81*2080 -> 0
A82: 78 | B82: TBH - Afiba Beke | M82: 28108.14 | Q82: =SUM(C82:P82) -> 28108.14 | AG82: =SUM(R82:AF82) -> 0 | AP82: =SUM(AH82:AO82) -> 0 | BK82: =+Q82+AP82+AZ82+BE82+BH82+BI82+BJ82+BG82+AG82+BF82+BA82+BD82+BB82+BC82 -> 28108.14 | BY82: =+BK82-BX82 -> 28108.14 | CA82: =+BL82*2080 -> 0
A83: 79 | B83: TBH - Victoria Ramassini | Q83: =SUM(C83:P83) -> 0 | V83: 30352.59 | AE83: 11400 | AG83: =SUM(R83:AF83) -> 41752.59 | AI83: 0 | AJ83: 4307.71 | AP83: =SUM(AH83:AO83) -> 4307.71 | AZ83: =SUM(AQ83:AY83) -> 0 | BK83: =+Q83+AP83+AZ83+BE83+BH83+BI83+BJ83+BG83+AG83+BF83+BA83+BD83+BB83+BC83 -> 46060.3 | BL83: 0 | BM83: =+$BL$83*BM2 -> 0 | BN83: =+$BL$83*BN2 -> 0 | BO83: =+$BL$83*BO2 -> 0 | BP83: =+$BL$83*BP2 -> 0 | BQ83: =+$BL$83*BQ2 -> 0 | BR83: =+$BL$83*BR2 -> 0 | BS83: =+$BL$83*BS2 -> 0 | BT83: =+$BL$83*BT2 -> 0 | ... BW83: =+$BL$83*BW2 -> 0 | BX83: =SUM(BM83:BW83) -> 0 | BY83: =+BK83-BX83 -> 46060.3 | CA83: =+BL83*2080 -> 0
A84: =+A83+1 -> 80 | B84: TBH - Victoria Neigim | Q84: =SUM(C84:P84) -> 0 | AG84: =SUM(R84:AF84) -> 0 | AP84: =SUM(AH84:AO84) -> 0 | AS84: =47000.34-330.75 -> 46669.59 | AZ84: =SUM(AQ84:AY84) -> 46669.59 | BK84: =+Q84+AP84+AZ84+BE84+BH84+BI84+BJ84+BG84+AG84+BF84+BA84+BD84+BB84+BC84 -> 46669.59 | BL84: 0 | BM84: =+$BL$84*BM2 -> 0 | BN84: =+$BL$84*BN2 -> 0 | BO84: =+$BL$84*BO2 -> 0 | BP84: =+$BL$84*BP2 -> 0 | BQ84: =+$BL$84*BQ2 -> 0 | BR84: =+$BL$84*BR2 -> 0 | BS84: =+$BL$84*BS2 -> 0 | BT84: =+$BL$84*BT2 -> 0 | ... BW84: =+$BL$84*BW2 -> 0 | BX84: =SUM(BM84:BW84) -> 0 | BY84: =+BK84-BX84 -> 46669.59 | CA84: =+BL84*2080 -> 0
A85: =+A84+1 -> 81 | B85: Viktoria Sutanovska | H85: 6349.24 | J85: 3300 | N85: 10004.67 | O85: 3332.19 | Q85: =SUM(C85:P85) -> 22986.1 | AG85: =SUM(R85:AF85) -> 0 | AH85: 0 | AI85: 0 | AP85: =SUM(AH85:AO85) -> 0 | AW85: 23575.14 | AX85: 31.78 | AZ85: =SUM(AQ85:AY85) -> 23606.92 | BK85: =+Q85+AP85+AZ85+BE85+BH85+BI85+BJ85+BG85+AG85+BF85+BA85+BD85+BB85+BC85 -> 46593.02 | BL85: 33.2813 | BM85: =+$BL$85*BM2 -> 2662.504 | BN85: =+$BL$85*BN2 -> 2662.504 | BO85: =+$BL$85*BO2 -> 2662.504 | BP85: =+$BL$85*BP2 -> 2662.504 | BQ85: =+$BL$85*BQ2 -> 2662.504 | BR85: =+$BL$85*BR2 -> 2662.504 | BS85: =+$BL$85*BS2 -> 2662.504 | BT85: =+$BL$85*BT2 -> 2662.504 | ... BW85: =+$BL$85*BW2 -> 1863.7528 | BX85: =SUM(BM85:BW85) -> 28488.793 | BY85: =+BK85-BX85 -> 18104.227 | CA85: =+BL85*2080 -> 69225.104 | CB85: =+CA85*BL85 -> 2303901.5
A86: =+A85+1 -> 82 | B86: William Wade | Q86: =SUM(C86:P86) -> 0 | AG86: =SUM(R86:AF86) -> 0 | AL86: 26686.65 | AP86: =SUM(AH86:AO86) -> 26686.65 | AZ86: =SUM(AQ86:AY86) -> 0 | BK86: =+Q86+AP86+AZ86+BE86+BH86+BI86+BJ86+BG86+AG86+BF86+BA86+BD86+BB86+BC86 -> 26686.65 | BL86: 25.601 | BM86: =+$BL$86*BM2 -> 2048.08 | BN86: =+$BL$86*BN2 -> 2048.08 | BO86: =+$BL$86*BO2 -> 2048.08 | BP86: =+$BL$86*BP2 -> 2048.08 | BQ86: =+$BL$86*BQ2 -> 2048.08 | BR86: =+$BL$86*BR2 -> 2048.08 | BS86: =+$BL$86*BS2 -> 2048.08 | BT86: =+$BL$86*BT2 -> 2048.08 | ... BW86: =+$BL$86*BW2 -> 1433.656 | BX86: =SUM(BM86:BW86) -> 21914.456 | BY86: =+BK86-BX86 -> 4772.194 | CA86: =+BL86*2080 -> 53250.08
A87: =+A86+1 -> 83 | B87: Yama | Q87: =SUM(C87:P87) -> 0 | AG87: =SUM(R87:AF87) -> 0 | AP87: =SUM(AH87:AO87) -> 0 | AT87: 34800.93 | AZ87: =SUM(AQ87:AY87) -> 34800.93 | BK87: =+Q87+AP87+AZ87+BE87+BH87+BI87+BJ87+BG87+AG87+BF87+BA87+BD87+BB87+BC87 -> 34800.93 | BL87: 30.5547 | BM87: =+$BL$87*BM2 -> 2444.376 | BN87: =+$BL$87*BN2 -> 2444.376 | BO87: =+$BL$87*BO2 -> 2444.376 | BP87: =+$BL$87*BP2 -> 2444.376 | BQ87: =+$BL$87*BQ2 -> 2444.376 | BR87: =+$BL$87*BR2 -> 2444.376 | BS87: =+$BL$87*BS2 -> 2444.376 | BT87: =+$BL$87*BT2 -> 2444.376 | ... BW87: =+$BL$87*BW2 -> 1711.0632 | BX87: =SUM(BM87:BW87) -> 26154.823 | BY87: =+BK87-BX87 -> 8646.1068 | CA87: =+BL87*2080 -> 63553.776
C88: =SUM(C4:C87) -> 0 | D88: =SUM(D4:D87) -> 731.25 | E88: =SUM(E4:E87) -> 2516.68 | F88: =SUM(F4:F87) -> 40126.88 | G88: =SUM(G4:G87) -> 3986.33 | H88: =SUM(H4:H87) -> 70221.89 | I88: =SUM(I4:I87) -> 9566.34 | J88: =SUM(J4:J87) -> 13286.27 | ... BJ88: =SUM(BJ4:BJ87) -> 15475.02 | BK88: =+BJ88+BI88+BH88+BG88+BF88+BE88+AZ88+AP88+AG88+Q88+BA88+BB88+BC88+BD88 -> 2742318.8 | BY88: =SUM(BY4:BY87) -> 965758.42
Q89: =+Q88 -> 373130.03 | AG89: =+AG88 -> 423500.07 | AH89: 48483.4 | AI89: =25057.63+668.02+26686.63 -> 52412.28 | AJ89: 125315.79 | AK89: 357966.41 | AL89: =1350+1059+800+731+26686.63+26686.65+28486.61 -> 85799.89 | AM89: 80549.43 | AN89: 42492 | AO89: 81129.74 | AQ89: =1350+136.89-290.91+780+700+156.31+19509.59 -> 22341.88 | AR89: =1350+136.89+850+700+732+28000.88 -> 31769.77 | AS89: =5737.2+6952.5+3648.07+47000.34+33624.85+13753.82+6500-430.75+4730.79 -> 121516.82 | AT89: =3027.85+6074.97+875.97+26682.65+38301+34800.93+28465.98+15253.83+29538.41+26255.11+37176.16+29843.76+26884.61 -> 303181.23 | AU89: =4050+2716.16-393.28+35551.61-284.58 -> 41639.91 | AV89: 38232.56 | AW89: 65242.4 | AX89: 87357.39 | AY89: 90098.61 | BA89: 46752.48 | BB89: 4758.37 | BC89: 5646.35 | BD89: 82209.03 | BE89: 9803.15 | BF89: 16379.55 | BG89: 17573.05 | BH89: 51222.5 | BI89: 20339.67 | BJ89: 15475.02
AI90: =+AI89-AI88 -> 0 | AJ90: =+AJ89-AJ88 -> 0 | AK90: =+AK89-AK88 -> 0 | AL90: =+AL89-AL88 -> 0 | AM90: =+AM89-AM88 -> 0 | AN90: =+AN89-AN88 -> 0 | AO90: =+AO89-AO88 -> 0 | AP90: =+AP89-AP88 -> -874148.93 | ... BJ90: =+BJ89-BJ88 -> 0
BE91: Done | BF91: Done | BG91: Done | BH91: done | BI91: done
BG93: `

Sheet FY26
AC2: MORA | AM2: ONA | AV2: MG | AX2: R&P
C3: Hourly Rate | D3: Annual Income | E3: Budget Total | F3: Variance | G3: PC ICM 5208-30 | H3: ASA III 5147-30 | I3: ASA IV 5176-30 | J3: PC UHP 5129-30 | K3: PC UHP V 5211-30 | L3: PC REA III 5209-30 | M3: PC Add. 5227-30 | N3: FY 26 ICM 5240 30 | O3: Total PC VA | P3: PC ICM 5208-33 | Q3: ASA II 5124-33 | R3: ASA III 5147-33 | S3: PC ASA IV 5176-33 | T3: PC UHP II 5145-33 | U3: PC UHP III 5166-33 | V3: PC UHP IV 5175-33 | W3: PC UHP V 5211-33 | X3: PC REA III 5209-33 | Y3: PC Additional 5227-33 | Z3: FY 26 ICM 5240-33 | AA3: Total PC MD | AB3: 2032 RYMP | AC3: 5051 SOR | AD3: 5052 ECMP | AE3: 5059 RSS | AF3: RTCA FY 26 5247 | AG3: RTCA FY 25 5212 | AH3: 5236-CMF #1 Oct-Dec | AI3: 5248 CMF #2 Jan - June | AJ3: 5196 ARSS | AK3: MORA | AL3: 5061 | AM3: 5062 | AN3: 5117 | AO3: 5118 | AP3: 5119 | AQ3: 5151 | AR3: 5214 | AS3: 5215 | AT3: 5216 | AU3: ONA | AV3: MG 5222-33 | AW3: MG 5222-30 | AX3: RP PIR 5245-30 | AY3: PC Initial Resettlement 5245-33 | AZ3: R&P 5213-30 | BA3: R&P 52130-33 | BB3: Total R&P | BC3: AFHS 2103-30 | BD3: Food Securtity Arlington 1060-30 | BE3: VFHY 3002-30 | BF3: DV #1 2025-30 | BG3: DV #2 2126-30 | BH3: NOFO 4007-30 | BI3: VOCA 2060-30 | BJ3: TVAP 2094-30
A4: 1 | B4: Abeer Omer | C4: 24.0385 | D4: =+C4*2080 -> 50000.08 | E4: =+O4+AA4+AK4+AU4+AV4+AW4+BC4+BE4+BF4+BG4+BH4+BI4+BJ4+BB4+BD4 -> 60418.505 | F4: =+E4-D4 -> 10418.425 | N4: 0 | O4: =SUM(G4:N4) -> 0 | Z4: 0 | AA4: =SUM(P4:Z4) -> 0 | AB4: 0 | AC4: 0 | AD4: 0 | AE4: 0 | AF4: 0 | AH4: 0 | AJ4: 0 | AK4: =SUM(AB4:AJ4) -> 0 | AL4: 0 | AM4: 0 | AN4: 0 | AO4: 0 | AP4: 0 | AQ4: 0 | AR4: 0 | AS4: 0 | AT4: 0 | AU4: =SUM(AL4:AT4) -> 0 | AX4: 0 | AY4: 0 | BB4: =SUM(AX4:BA4) -> 0 | BF4: 2500 | BG4: =+'[1]P 2- Salary'!$L$10 -> 48814.275 | BI4: 9104.23 | BL4: =+D4*5% -> 2500.004 | BM4: =+BL4+D4 -> 52500.084
A5: =+A4+1 -> 2 | B5: Aemal Sanjeeda | C5: 26.4423 | D5: =+C5*2080 -> 54999.984 | E5: =+O5+AA5+AK5+AU5+AV5+AW5+BC5+BE5+BF5+BG5+BH5+BI5+BJ5+BB5+BD5 -> 57749 | F5: =+E5-D5 -> 2749.016 | N5: 0 | O5: =SUM(G5:N5) -> 0 | Z5: 0 | AA5: =SUM(P5:Z5) -> 0 | AB5: 0 | AC5: 0 | AD5: 0 | AE5: 0 | AF5: 0 | AH5: 0 | AJ5: 0 | AK5: =SUM(AB5:AJ5) -> 0 | AO5: =+'[2]P 2-Salary '!$J$24 -> 57749 | AU5: =SUM(AL5:AT5) -> 57749 | AX5: 0 | AY5: 0 | BB5: =SUM(AX5:BA5) -> 0 | BL5: =+D5*5% -> 2749.9992 | BM5: =+BL5+D5 -> 57749.983
A6: =+A5+1 -> 3 | B6: Ahmed Seyar Auobi | C6: 24.0385 | D6: =+C6*2080 -> 50000.08 | E6: =+O6+AA6+AK6+AU6+AV6+AW6+BC6+BE6+BF6+BG6+BH6+BI6+BJ6+BB6+BD6 -> 52500 | F6: =+E6-D6 -> 2499.92 | G6: 13125 | N6: 39375 | O6: =SUM(G6:N6) -> 52500 | Z6: 0 | AA6: =SUM(P6:Z6) -> 0 | AB6: 0 | AC6: 0 | AD6: 0 | AE6: 0 | AF6: 0 | AH6: 0 | AJ6: 0 | AK6: =SUM(AB6:AJ6) -> 0 | AU6: =SUM(AL6:AT6) -> 0 | AX6: 0 | AY6: 0 | BB6: =SUM(AX6:BA6) -> 0 | BL6: =+D6*5% -> 2500.004 | BM6: =+BL6+D6 -> 52500.084
A7: =+A6+1 -> 4 | B7: Ajmal Amiri | C7: 25.601 | D7: =+C7*2080 -> 53250.08 | E7: =+O7+AA7+AK7+AU7+AV7+AW7+BC7+BE7+BF7+BG7+BH7+BI7+BJ7+BB7+BD7 -> 74363.16 | F7: =+E7-D7 -> 21113.08 | K7: 7268.56 | L7: 11182.4 | N7: 0 | O7: =SUM(G7:N7) -> 18450.96 | Z7: 0 | AA7: =SUM(P7:Z7) -> 0 | AK7: =SUM(AB7:AJ7) -> 0 | AR7: =+'[4]P 2-Salary '!$J$18 -> 11182.6 | AS7: =+'[5]P 2-Salary '!$J$25 -> 16773.6 | AT7: =+'[6]P 2-Salary '!$J$19 -> 27956 | AU7: =SUM(AL7:AT7) -> 55912.2 | AX7: 0 | AY7: 0 | BB7: =SUM(AX7:BA7) -> 0 | BL7: =+D7*5% -> 2662.504 | BM7: =+BL7+D7 -> 55912.584
A8: =+A7+1 -> 5 | B8: Ajmal Khurram | C8: 24.0385 | D8: =+C8*2080 -> 50000.08 | E8: =+O8+AA8+AK8+AU8+AV8+AW8+BC8+BE8+BF8+BG8+BH8+BI8+BJ8+BB8+BD8 -> 55913 | F8: =+E8-D8 -> 5912.92 | N8: 0 | O8: =SUM(G8:N8) -> 0 | Z8: 0 | AA8: =SUM(P8:Z8) -> 0 | AE8: 55913 | AK8: =SUM(AB8:AJ8) -> 55913 | AU8: =SUM(AL8:AT8) -> 0 | AX8: 0 | AY8: 0 | BB8: =SUM(AX8:BA8) -> 0 | BL8: =+D8*5% -> 2500.004 | BM8: =+BL8+D8 -> 52500.084
A9: =+A8+1 -> 6 | B9: Akilu Debalkew | C9: 24.0385 | D9: =+C9*2080 -> 50000.08 | E9: =+O9+AA9+AK9+AU9+AV9+AW9+BC9+BE9+BF9+BG9+BH9+BI9+BJ9+BB9+BD9 -> 61982.7 | F9: =+E9-D9 -> 11982.62 | G9: 5250 | H9: 1050 | I9: 2100 | J9: 4200 | K9: 1575 | M9: 2625 | N9: 7875 | O9: =SUM(G9:N9) -> 24675 | Z9: 0 | AA9: =SUM(P9:Z9) -> 0 | AG9: 0 | AI9: 0 | AK9: =SUM(AB9:AJ9) -> 0 | AO9: 0 | AU9: =SUM(AL9:AT9) -> 0 | AV9: 0 | AW9: 24000 | AX9: 6000 | AY9: 0 | AZ9: 7307.7 | BB9: =SUM(AX9:BA9) -> 13307.7 | BL9: =+D9*5% -> 2500.004 | BM9: =+BL9+D9 -> 52500.084
A10: =+A9+1 -> 7 | B10: Albab Azeze | C10: 24.0385 | D10: =+C10*2080 -> 50000.08 | E10: =+O10+AA10+AK10+AU10+AV10+AW10+BC10+BE10+BF10+BG10+BH10+BI10+BJ10+BB10+BD10 -> 58157 | F10: =+E10-D10 -> 8156.92 | N10: 0 | O10: =SUM(G10:N10) -> 0 | Z10: 0 | AA10: =SUM(P10:Z10) -> 0 | AE10: 10000 | AF10: 10000 | AG10: =50257-30000+17900 -> 38157 | AK10: =SUM(AB10:AJ10) -> 58157 | AO10: 0 | AU10: =SUM(AL10:AT10) -> 0 | AX10: 0 | AY10: 0 | BB10: =SUM(AX10:BA10) -> 0 | BL10: =+D10*5% -> 2500.004 | BM10: =+BL10+D10 -> 52500.084
A11: =+A10+1 -> 8 | B11: Anna Kurzer | C11: 33.2813 | D11: =+C11*2080 -> 69225.104 | E11: =+O11+AA11+AK11+AU11+AV11+AW11+BC11+BE11+BF11+BG11+BH11+BI11+BJ11+BB11+BD11 -> 70850.7 | F11: =+E11-D11 -> 1625.596 | N11: 0 | O11: =SUM(G11:N11) -> 0 | Z11: 0 | AA11: =SUM(P11:Z11) -> 0 | AF11: 29074 | AG11: =35000+13570-20000-15000-900 -> 12670 | AH11: 5325.01 | AI11: 0 | AJ11: 14280 | AK11: =SUM(AB11:AJ11) -> 61349.01 | AU11: =SUM(AL11:AT11) -> 0 | AV11: 9501.69 | AX11: 0 | AY11: 0 | BB11: =SUM(AX11:BA11) -> 0 | BL11: =+D11*5% -> 3461.2552 | BM11: =+BL11+D11 -> 72686.359
A12: =+A11+1 -> 9 | B12: Atakhleti Alemseged | C12: 32.7064 | D12: =+C12*2080 -> 68029.312 | E12: =+O12+AA12+AK12+AU12+AV12+AW12+BC12+BE12+BF12+BG12+BH12+BI12+BJ12+BB12+BD12 -> 71101.37 | F12: =+E12-D12 -> 3072.058 | I12: 3503.5 | N12: 0 | O12: =SUM(G12:N12) -> 3503.5 | R12: 6306.3 | Z12: 0 | AA12: =SUM(P12:Z12) -> 6306.3 | AD12: 42597 | AH12: 0 | AK12: =SUM(AB12:AJ12) -> 42597 | AU12: =SUM(AL12:AT12) -> 0 | AX12: 0 | AY12: 0 | AZ12: 5219.53 | BB12: =SUM(AX12:BA12) -> 5219.53 | BH12: =26557.58-13082.54 -> 13475.04 | BL12: =+D12*5% -> 3401.4656 | BM12: =+BL12+D12 -> 71430.778
A13: =+A12+1 -> 10 | B13: Barbara Callen | C13: 31.25 | D13: =+C13*2080 -> 65000 | E13: =+O13+AA13+AK13+AU13+AV13+AW13+BC13+BE13+BF13+BG13+BH13+BI13+BJ13+BB13+BD13 -> 93163.75 | F13: =+E13-D13 -> 28163.75 | G13: 2730 | H13: 1365 | J13: 3412.5 | K13: 2047.5 | L13: 3412.5 | M13: 4095 | N13: 2730 | O13: =SUM(G13:N13) -> 19792.5 | P13: 2730 | Q13: 1365 | T13: 2047.5 | U13: 1365 | X13: 2047.5 | Z13: 2047.5 | AA13: =SUM(P13:Z13) -> 11602.5 | AD13: 6825 | AE13: 6825 | AH13: 5625 | AI13: 3250 | AJ13: 6825 | AK13: =SUM(AB13:AJ13) -> 29350 | AN13: =+'[7]P 2-Salary '!$J$24 -> 6825 | AO13: =+'[2]P 2-Salary '!$J$30 -> 6825 | AR13: =+'[4]P 2-Salary '!$J$24 -> 3412.5 | AT13: =+'[6]P 2-Salary '!$J$23 -> 6825 | AU13: =SUM(AL13:AT13) -> 23887.5 | AV13: 0 | AW13: 4550 | AX13: 0 | AY13: 0 | AZ13: 2031.25 | BA13: 0 | BB13: =SUM(AX13:BA13) -> 2031.25 | BI13: 1950 | BL13: =+D13*5% -> 3250 | BM13: =+BL13+D13 -> 68250
A14: =+A13+1 -> 11 | B14: Baryalai Rawan | C14: 32.6923 | D14: =+C14*2080 -> 67999.984 | E14: =+O14+AA14+AK14+AU14+AV14+AW14+BC14+BE14+BF14+BG14+BH14+BI14+BJ14+BB14+BD14 -> 74222 | F14: =+E14-D14 -> 6222.016 | N14: 0 | O14: =SUM(G14:N14) -> 0 | P14: 5712 | Z14: 7140 | AA14: =SUM(P14:Z14) -> 12852 | AB14: 7140 | AC14: 24990 | AD14: 24990 | AH14: 4250 | AK14: =SUM(AB14:AJ14) -> 61370 | AU14: =SUM(AL14:AT14) -> 0 | AX14: 0 | AY14: 0 | BB14: =SUM(AX14:BA14) -> 0 | BL14: =+D14*5% -> 3399.9992 | BM14: =+BL14+D14 -> 71399.983
A15: =+A14+1 -> 12 | B15: Bethelem Alemahyehu | C15: 24.0385 | D15: =+C15*2080 -> 50000.08 | E15: =+O15+AA15+AK15+AU15+AV15+AW15+BC15+BE15+BF15+BG15+BH15+BI15+BJ15+BB15+BD15 -> 52500 | F15: =+E15-D15 -> 2499.92 | N15: 0 | O15: =SUM(G15:N15) -> 0 | Z15: 0 | AA15: =SUM(P15:Z15) -> 0 | AD15: 0 | AE15: 52500 | AK15: =SUM(AB15:AJ15) -> 52500 | AU15: =SUM(AL15:AT15) -> 0 | AX15: 0 | AY15: 0 | BB15: =SUM(AX15:BA15) -> 0 | BL15: =+D15*5% -> 2500.004 | BM15: =+BL15+D15 -> 52500.084
A16: =+A15+1 -> 13 | B16: Bob Elston | C16: 31.25 | D16: =+C16*2080 -> 65000 | E16: =+O16+AA16+AK16+AU16+AV16+AW16+BC16+BE16+BF16+BG16+BH16+BI16+BJ16+BB16+BD16 -> 81485 | F16: =+E16-D16 -> 16485 | G16: 3412.5 | H16: 1365 | J16: 4095 | K16: 2047.5 | L16: 3412.5 | N16: =+'[3]PC Admin & Client (Regular)'!$E$24 -> 2047.5 | O16: =SUM(G16:N16) -> 16380 | P16: 2730 | Q16: 1365 | T16: 2047.5 | U16: 1365 | X16: 2047.5 | Z16: 0 | AA16: =SUM(P16:Z16) -> 9555 | AD16: 6825 | AE16: 6825 | AH16: 4375 | AI16: 3250 | AJ16: 6825 | AK16: =SUM(AB16:AJ16) -> 28100 | AN16: =+'[7]P 2-Salary '!$J$25 -> 6825 | AO16: =+'[2]P 2-Salary '!$J$31 -> 6825 | AR16: =+'[4]P 2-Salary '!$J$25 -> 3412.5 | AT16: =+'[6]P 2-Salary '!$J$25 -> 6825 | AU16: =SUM(AL16:AT16) -> 23887.5 | AV16: 2625 | AX16: 0 | AY16: 0 | AZ16: 937.5 | BB16: =SUM(AX16:BA16) -> 937.5 | BL16: =+D16*5% -> 3250 | BM16: =+BL16+D16 -> 68250
A17: =+A16+1 -> 14 | B17: Dagim McKonnen | C17: 30.5547 | D17: =+C17*2080 -> 63553.776 | E17: =+O17+AA17+AK17+AU17+AV17+AW17+BC17+BE17+BF17+BG17+BH17+BI17+BJ17+BB17+BD17 -> 70398.57 | F17: =+E17-D17 -> 6844.794 | N17: 0 | O17: =SUM(G17:N17) -> 0 | Z17: 0 | AA17: =SUM(P17:Z17) -> 0 | AE17: 66732 | AH17: 3666.57 | AK17: =SUM(AB17:AJ17) -> 70398.57 | AU17: =SUM(AL17:AT17) -> 0 | AX17: 0 | AY17: 0 | BB17: =SUM(AX17:BA17) -> 0 | BL17: =+D17*5% -> 3177.6888 | BM17: =+BL17+D17 -> 66731.465
A18: =+A17+1 -> 15 | B18: Razia Mahrami | C18: 36.5385 | D18: =+C18*2080 -> 76000.08 | E18: =+O18+AA18+AK18+AU18+AV18+AW18+BC18+BE18+BF18+BG18+BH18+BI18+BJ18+BB18+BD18 -> 132948.35 | F18: =+E18-D18 -> 56948.27 | N18: 0 | O18: =SUM(G18:N18) -> 0 | P18: 2907.44 | Q18: 1453.72 | T18: 5814.88 | U18: 5814.88 | X18: 7268.6 | Y18: 3634.3 | Z18: 0 | AA18: =SUM(P18:Z18) -> 26893.82 | AB18: 15960 | AC18: 15960 | AD18: 11970 | AE18: 15960 | AF18: 3192 | AG18: 750 | AH18: 8151.53 | AI18: 15960 | AJ18: 15960 | AK18: =SUM(AB18:AJ18) -> 103863.53 | AU18: =SUM(AL18:AT18) -> 0 | AV18: 0 | AX18: 0 | AY18: 2191 | BB18: =SUM(AX18:BA18) -> 2191 | BL18: =+D18*5% -> 3800.004 | BM18: =+BL18+D18 -> 79800.084
A19: =+A18+1 -> 16 | B19: Earnest Overton | C19: 24.0385 | D19: =+C19*2080 -> 50000.08 | E19: =+O19+AA19+AK19+AU19+AV19+AW19+BC19+BE19+BF19+BG19+BH19+BI19+BJ19+BB19+BD19 -> 52500 | F19: =+E19-D19 -> 2499.92 | N19: 0 | O19: =SUM(G19:N19) -> 0 | Z19: 0 | AA19: =SUM(P19:Z19) -> 0 | AK19: =SUM(AB19:AJ19) -> 0 | AO19: =+'[2]P 2-Salary '!$J$27 -> 52500 | AU19: =SUM(AL19:AT19) -> 52500 | AX19: 0 | AY19: 0 | BB19: =SUM(AX19:BA19) -> 0 | BL19: =+D19*5% -> 2500.004 | BM19: =+BL19+D19 -> 52500.084
A20: =+A19+1 -> 17 | B20: Eftihia Ionnidou | C20: 32.2571 | D20: =+C20*2080 -> 67094.768 | E20: =+O20+AA20+AK20+AU20+AV20+AW20+BC20+BE20+BF20+BG20+BH20+BI20+BJ20+BB20+BD20 -> 70449 | F20: =+E20-D20 -> 3354.232 | N20: 0 | O20: =SUM(G20:N20) -> 0 | Z20: 0 | AA20: =SUM(P20:Z20) -> 0 | AK20: =SUM(AB20:AJ20) -> 0 | AN20: =+'[7]P 2-Salary '!$J$17 -> 70449 | AU20: =SUM(AL20:AT20) -> 70449 | AX20: 0 | AY20: 0 | BB20: =SUM(AX20:BA20) -> 0 | BL20: =+D20*5% -> 3354.7384 | BM20: =+BL20+D20 -> 70449.506
A21: =+A20+1 -> 18 | B21: Egosia Ajeih | C21: 25.601 | D21: =+C21*2080 -> 53250.08 | E21: =+O21+AA21+AK21+AU21+AV21+AW21+BC21+BE21+BF21+BG21+BH21+BI21+BJ21+BB21+BD21 -> 56527.42 | F21: =+E21-D21 -> 3277.34 | N21: 0 | O21: =SUM(G21:N21) -> 0 | Z21: 0 | AA21: =SUM(P21:Z21) -> 0 | AE21: 55913 | AH21: 614.42 | AK21: =SUM(AB21:AJ21) -> 56527.42 | AU21: =SUM(AL21:AT21) -> 0 | AX21: 0 | AY21: 0 | BB21: =SUM(AX21:BA21) -> 0 | BL21: =+D21*5% -> 2662.504 | BM21: =+BL21+D21 -> 55912.584
A22: =+A21+1 -> 19 | B22: Elizaabeth Buara Kamara | C22: 28.161 | D22: =+C22*2080 -> 58574.88 | E22: =+O22+AA22+AK22+AU22+AV22+AW22+BC22+BE22+BF22+BG22+BH22+BI22+BJ22+BB22+BD22 -> 62937.39 | F22: =+E22-D22 -> 4362.51 | N22: 0 | O22: =SUM(G22:N22) -> 0 | Z22: 0 | AA22: =SUM(P22:Z22) -> 0 | AH22: 9687.39 | AI22: 53250 | AK22: =SUM(AB22:AJ22) -> 62937.39 | AU22: =SUM(AL22:AT22) -> 0 | AX22: 0 | AY22: 0 | BB22: =SUM(AX22:BA22) -> 0 | BL22: =+D22*5% -> 2928.744 | BM22: =+BL22+D22 -> 61503.624
A23: =+A22+1 -> 20 | B23: Emebet Ashagre | C23: 33.6539 | D23: =+C23*2080 -> 70000.112 | E23: =+O23+AA23+AK23+AU23+AV23+AW23+BC23+BE23+BF23+BG23+BH23+BI23+BJ23+BB23+BD23 -> 109704.24 | F23: =+E23-D23 -> 39704.132 | G23: 2940 | H23: 1470 | J23: 4410 | K23: 2205 | L23: 3675 | N23: =+'[3]PC Admin & Client (Regular)'!$E$18 -> 2205.0036 | O23: =SUM(G23:N23) -> 16905.004 | P23: 2940 | Q23: 1470 | T23: 2205 | U23: 1470 | W23: 1470 | X23: 2205 | Y23: 2205 | Z23: 0 | AA23: =SUM(P23:Z23) -> 13965 | AB23: 3675 | AD23: 7350 | AE23: 7350 | AF23: 1470 | AH23: 4711.54 | AI23: 3500 | AJ23: 7350 | AK23: =SUM(AB23:AJ23) -> 35406.54 | AL23: =+'[8]P 2-Salary '!$J$19 -> 1470 | AM23: =+'[9]P 2-Salary '!$J$18 -> 2205 | AN23: =+'[7]P 2-Salary '!$J$16 -> 3675 | AO23: =+'[2]P 2-Salary '!$J$16 -> 7350 | AP23: =+'[10]P 2-Salary '!$J$16 -> 2940 | AQ23: =+'[11]P 2-Salary '!$J$16 -> 2940 | AR23: =+'[4]P 2-Salary '!$J$23 -> 3675 | AS23: =+'[5]P 2-Salary '!$J$21 -> 2940 | AT23: =+'[6]P 2-Salary '!$J$22 -> 5880 | AU23: =SUM(AL23:AT23) -> 33075 | AW23: =4900-1600 -> 3300 | AX23: 1800 | AY23: 1470 | AZ23: 1682.7 | BA23: 0 | BB23: =SUM(AX23:BA23) -> 4952.7 | BI23: 2100 | BL23: =+D23*5% -> 3500.0056 | BM23: =+BL23+D23 -> 73500.118
A24: =+A23+1 -> 21 | B24: Esra Bayrakthar | C24: 40.9583 | D24: =+C24*2080 -> 85193.264 | E24: =+O24+AA24+AK24+AU24+AV24+AW24+BC24+BE24+BF24+BG24+BH24+BI24+BJ24+BB24+BD24 -> 99961.19 | F24: =+E24-D24 -> 14767.926 | N24: 0 | O24: =SUM(G24:N24) -> 0 | Q24: 8050.68 | Z24: 0 | AA24: =SUM(P24:Z24) -> 8050.68 | AD24: 0 | AE24: 0 | AH24: 2457.51 | AK24: =SUM(AB24:AJ24) -> 2457.51 | AO24: =+'[2]P 2-Salary '!$J$28 -> 89453 | AU24: =SUM(AL24:AT24) -> 89453 | AX24: 0 | AY24: 0 | BB24: =SUM(AX24:BA24) -> 0 | BL24: =+D24*5% -> 4259.6632 | BM24: =+BL24+D24 -> 89452.927
A25: =+A24+1 -> 22 | B25: Evette Phillips | C25: 20 | D25: =+C25*2040 -> 40800 | E25: =+O25+AA25+AK25+AU25+AV25+AW25+BC25+BE25+BF25+BG25+BH25+BI25+BJ25+BB25+BD25 -> 28111 | F25: =+E25-D25 -> -12689 | N25: 0 | O25: =SUM(G25:N25) -> 0 | Z25: 11466 | AA25: =SUM(P25:Z25) -> 11466 | AH25: 6020 | AI25: 10625 | AK25: =SUM(AB25:AJ25) -> 16645 | AU25: =SUM(AL25:AT25) -> 0 | AX25: 0 | AY25: 0 | BB25: =SUM(AX25:BA25) -> 0 | BC25: 0 | BL25: =+D25*5% -> 2040 | BM25: =+BL25+D25 -> 42840
A26: =+A25+1 -> 23 | B26: Faye Biggs | C26: 30.1809 | D26: =+C26*2080 -> 62776.272 | E26: =+O26+AA26+AK26+AU26+AV26+AW26+BC26+BE26+BF26+BG26+BH26+BI26+BJ26+BB26+BD26 -> 65915 | F26: =+E26-D26 -> 3138.728 | N26: 0 | O26: =SUM(G26:N26) -> 0 | Z26: 0 | AA26: =SUM(P26:Z26) -> 0 | AK26: =SUM(AB26:AJ26) -> 0 | AP26: =+'[10]P 2-Salary '!$J$20 -> 52732 | AQ26: =+'[11]P 2-Salary '!$J$22 -> 13183 | AU26: =SUM(AL26:AT26) -> 65915 | AX26: 0 | AY26: 0 | BB26: =SUM(AX26:BA26) -> 0 | BL26: =+D26*5% -> 3138.8136 | BM26: =+BL26+D26 -> 65915.086
A27: =+A26+1 -> 24 | B27: Ferdawok Woyesa | C27: 28.4171 | D27: =+C27*2080 -> 59107.568 | E27: =+O27+AA27+AK27+AU27+AV27+AW27+BC27+BE27+BF27+BG27+BH27+BI27+BJ27+BB27+BD27 -> 68498.85 | F27: =+E27-D27 -> 9391.282 | N27: 0 | O27: =SUM(G27:N27) -> 0 | Z27: 0 | AA27: =SUM(P27:Z27) -> 0 | AK27: =SUM(AB27:AJ27) -> 0 | AO27: 0 | AU27: =SUM(AL27:AT27) -> 0 | AW27: 0 | AX27: 0 | AY27: 0 | BB27: =SUM(AX27:BA27) -> 0 | BG27: 23834.2 | BI27: 44664.65 | BL27: =+D27*5% -> 2955.3784 | BM27: =+BL27+D27 -> 62062.946
A28: =+A27+1 -> 25 | B28: Firdus Yusuf | C28: 24 | D28: =+C28*56*26 -> 34944 | E28: =+O28+AA28+AK28+AU28+AV28+AW28+BC28+BE28+BF28+BG28+BH28+BI28+BJ28+BB28+BD28 -> 18431.78 | F28: =+E28-D28 -> -16512.22 | N28: 0 | O28: =SUM(G28:N28) -> 0 | Z28: 0 | AA28: =SUM(P28:Z28) -> 0 | AK28: =SUM(AB28:AJ28) -> 0 | AU28: =SUM(AL28:AT28) -> 0 | AX28: 0 | AY28: 0 | BB28: =SUM(AX28:BA28) -> 0 | BC28: 18431.78 | BL28: =+D28*5% -> 1747.2 | BM28: =+BL28+D28 -> 36691.2
A29: =+A28+1 -> 26 | B29: Florance Ahmadi | C29: 27.7771 | D29: =+C29*2080 -> 57776.368 | E29: =+O29+AA29+AK29+AU29+AV29+AW29+BC29+BE29+BF29+BG29+BH29+BI29+BJ29+BB29+BD29 -> 60665 | F29: =+E29-D29 -> 2888.632 | N29: 0 | O29: =SUM(G29:N29) -> 0 | Z29: 0 | AA29: =SUM(P29:Z29) -> 0 | AI29: 0 | AK29: =SUM(AB29:AJ29) -> 0 | AN29: =+'[7]P 2-Salary '!$J$18 -> 60665 | AU29: =SUM(AL29:AT29) -> 60665 | AX29: 0 | AY29: 0 | BB29: =SUM(AX29:BA29) -> 0 | BL29: =+D29*5% -> 2888.8184 | BM29: =+BL29+D29 -> 60665.186
A30: =+A29+1 -> 27 | B30: Freshta Atmar | C30: 24.0385 | D30: =+C30*2080 -> 50000.08 | E30: =+O30+AA30+AK30+AU30+AV30+AW30+BC30+BE30+BF30+BG30+BH30+BI30+BJ30+BB30+BD30 -> 59286.89 | F30: =+E30-D30 -> 9286.81 | N30: 0 | O30: =SUM(G30:N30) -> 0 | Z30: 0 | AA30: =SUM(P30:Z30) -> 0 | AK30: =SUM(AB30:AJ30) -> 0 | AS30: =+'[5]P 2-Salary '!$J$24 -> 26250 | AU30: =SUM(AL30:AT30) -> 26250 | AW30: 30036.89 | AX30: 0 | AY30: 0 | AZ30: 3000 | BA30: 0 | BB30: =SUM(AX30:BA30) -> 3000 | BL30: =+D30*5% -> 2500.004 | BM30: =+BL30+D30 -> 52500.084
A31: =+A30+1 -> 28 | B31: Maternity Frishta Khalil | C31: 24.0385 | D31: =+C31*2080 -> 50000.08 | E31: =+O31+AA31+AK31+AU31+AV31+AW31+BC31+BE31+BF31+BG31+BH31+BI31+BJ31+BB31+BD31 -> 49203 | F31: =+E31-D31 -> -797.08 | N31: 0 | O31: =SUM(G31:N31) -> 0 | Z31: 0 | AA31: =SUM(P31:Z31) -> 0 | AB31: 0 | AE31: 49203 | AK31: =SUM(AB31:AJ31) -> 49203 | AU31: =SUM(AL31:AT31) -> 0 | AX31: 0 | AY31: 0 | BB31: =SUM(AX31:BA31) -> 0 | BL31: =+D31*5% -> 2500.004 | BM31: =+BL31+D31 -> 52500.084
A32: =+A31+1 -> 29 | B32: TBH - Ganna Poskara | C32: 25.601 | D32: =+C32*2080 -> 53250.08 | E32: =+O32+AA32+AK32+AU32+AV32+AW32+BC32+BE32+BF32+BG32+BH32+BI32+BJ32+BB32+BD32 -> 54000 | F32: =+E32-D32 -> 749.92 | N32: 0 | O32: =SUM(G32:N32) -> 0 | Z32: 0 | AA32: =SUM(P32:Z32) -> 0 | AB32: 0 | AC32: 0 | AD32: 0 | AE32: 0 | AF32: 0 | AG32: 0 | AH32: 0 | AJ32: =52500+1500 -> 54000 | AK32: =SUM(AB32:AJ32) -> 54000 | AU32: =SUM(AL32:AT32) -> 0 | AX32: 0 | AY32: 0 | BB32: =SUM(AX32:BA32) -> 0 | BL32: =+D32*5% -> 2662.504 | BM32: =+BL32+D32 -> 55912.584
A33: =+A32+1 -> 30 | B33: TBH - Gelila Woodimagen | C33: 24.0385 | D33: =+C33*2080 -> 50000.08 | E33: =+O33+AA33+AK33+AU33+AV33+AW33+BC33+BE33+BF33+BG33+BH33+BI33+BJ33+BB33+BD33 -> 51000 | F33: =+E33-D33 -> 999.92 | N33: 0 | O33: =SUM(G33:N33) -> 0 | Z33: 0 | AA33: =SUM(P33:Z33) -> 0 | AB33: 0 | AC33: 0 | AD33: 0 | AE33: 0 | AF33: 0 | AH33: 0 | AJ33: =52500-1500 -> 51000 | AK33: =SUM(AB33:AJ33) -> 51000 | AU33: =SUM(AL33:AT33) -> 0 | AX33: 0 | AY33: 0 | BA33: 0 | BB33: =SUM(AX33:BA33) -> 0 | BL33: =+D33*5% -> 2500.004 | BM33: =+BL33+D33 -> 52500.084
A34: =+A33+1 -> 31 | B34: Hamdard Hashmatullah | C34: 31.25 | D34: =+C34*2080 -> 65000 | E34: =+O34+AA34+AK34+AU34+AV34+AW34+BC34+BE34+BF34+BG34+BH34+BI34+BJ34+BB34+BD34 -> 63158.75 | F34: =+E34-D34 -> -1841.25 | H34: 6825 | O34: =SUM(G34:N34) -> 6825 | Z34: 0 | AA34: =SUM(P34:Z34) -> 0 | AB34: 0 | AC34: 0 | AD34: 0 | AE34: 0 | AF34: 0 | AH34: 0 | AI34: 0 | AJ34: 0 | AK34: =SUM(AB34:AJ34) -> 0 | AU34: =SUM(AL34:AT34) -> 0 | AW34: 7386.25 | AX34: 15697.5 | AY34: 0 | AZ34: 33250 | BA34: 0 | BB34: =SUM(AX34:BA34) -> 48947.5 | BL34: =+D34*5% -> 3250 | BM34: =+BL34+D34 -> 68250
A35: =+A34+1 -> 32 | B35: Helen Gebru | C35: 36.05769 | D35: =+C35*2080 -> 74999.995 | E35: =+O35+AA35+AK35+AU35+AV35+AW35+BC35+BE35+BF35+BG35+BH35+BI35+BJ35+BB35+BD35 -> 134724.99 | F35: =+E35-D35 -> 59724.995 | G35: 3150 | H35: 1575 | J35: 4725 | K35: 2362.5 | L35: 3937.5 | N35: 3150 | O35: =SUM(G35:N35) -> 18900 | P35: 3150 | Q35: 1575 | T35: 2362.5 | U35: 1575 | W35: 1575 | X35: 2362.5 | Y35: 2362.5 | Z35: 2362.5 | AA35: =SUM(P35:Z35) -> 17325 | AB35: 3938 | AC35: 0 | AD35: 15750 | AE35: 11813 | AF35: 1575 | AH35: 6634.58 | AI35: 3750 | AJ35: 7875 | AK35: =SUM(AB35:AJ35) -> 51335.58 | AL35: =+'[8]P 2-Salary '!$J$20-1000 -> 575 | AM35: =+'[9]P 2-Salary '!$J$19 -> 2362.5 | AN35: =+'[7]P 2-Salary '!$J$21 -> 3937.5 | AO35: =+'[2]P 2-Salary '!$J$17 -> 7875 | AP35: =+'[10]P 2-Salary '!$J$17 -> 3150 | AQ35: =+'[11]P 2-Salary '!$J$17 -> 3150 | AR35: =+'[4]P 2-Salary '!$J$22 -> 3937.5 | AS35: =+'[5]P 2-Salary '!$J$20 -> 3150 | AT35: =+'[6]P 2-Salary '!$J$21 -> 6300 | AU35: =SUM(AL35:AT35) -> 34437.5 | AV35: 0 | AW35: 5250 | AX35: 1575 | AY35: 1575 | AZ35: 4326.91 | BA35: 0 | BB35: =SUM(AX35:BA35) -> 7476.91 | BL35: =+D35*5% -> 3749.9998 | BM35: =+BL35+D35 -> 78749.995
A36: =+A35+1 -> 33 | B36: Henok Shishige | C36: 24.0385 | D36: =+C36*2080 -> 50000.08 | E36: =+O36+AA36+AK36+AU36+AV36+AW36+BC36+BE36+BF36+BG36+BH36+BI36+BJ36+BB36+BD36 -> 52500 | F36: =+E36-D36 -> 2499.92 | N36: 0 | O36: =SUM(G36:N36) -> 0 | Z36: 0 | AA36: =SUM(P36:Z36) -> 0 | AB36: 0 | AC36: 0 | AD36: 52500 | AE36: 0 | AF36: 0 | AH36: 0 | AJ36: 0 | AK36: =SUM(AB36:AJ36) -> 52500 | AU36: =SUM(AL36:AT36) -> 0 | AX36: 0 | AY36: 0 | BB36: =SUM(AX36:BA36) -> 0 | BC36: 0 | BL36: =+D36*5% -> 2500.004 | BM36: =+BL36+D36 -> 52500.084
A37: =+A36+1 -> 34 | B37: Ibraham Diallo | C37: 25.601 | D37: =+C37*2080 -> 53250.08 | E37: =+O37+AA37+AK37+AU37+AV37+AW37+BC37+BE37+BF37+BG37+BH37+BI37+BJ37+BB37+BD37 -> 56778.09 | F37: =+E37-D37 -> 3528.01 | N37: 0 | O37: =SUM(G37:N37) -> 0 | Z37: 0 | AA37: =SUM(P37:Z37) -> 0 | AB37: 0 | AC37: 2796 | AD37: 10650 | AE37: 10650 | AF37: 26250 | AG37: 4000 | AH37: 2432.09 | AJ37: 0 | AK37: =SUM(AB37:AJ37) -> 56778.09 | AU37: =SUM(AL37:AT37) -> 0 | AX37: 0 | AY37: 0 | BB37: =SUM(AX37:BA37) -> 0 | BL37: =+D37*5% -> 2662.504 | BM37: =+BL37+D37 -> 55912.584
A38: =+A37+1 -> 35 | B38: Iriana Lessen | C38: 31.25 | D38: =+C38*2080 -> 65000 | E38: =+O38+AA38+AK38+AU38+AV38+AW38+BC38+BE38+BF38+BG38+BH38+BI38+BJ38+BB38+BD38 -> 95315 | F38: =+E38-D38 -> 30315 | N38: 0 | O38: =SUM(G38:N38) -> 0 | Q38: 7875 | T38: 8400 | V38: 2625 | W38: 5250 | X38: 5250 | Z38: 0 | AA38: =SUM(P38:Z38) -> 29400 | AB38: 0 | AC38: 0 | AD38: 65915 | AE38: 0 | AF38: 0 | AH38: 0 | AI38: 0 | AJ38: 0 | AK38: =SUM(AB38:AJ38) -> 65915 | AU38: =SUM(AL38:AT38) -> 0 | AX38: 0 | AY38: 0 | BB38: =SUM(AX38:BA38) -> 0 | BL38: =+D38*5% -> 3250 | BM38: =+BL38+D38 -> 68250
A39: =+A38+1 -> 36 | B39: Iryna Gaiduk | C39: 30.5547 | D39: =+C39*2080 -> 63553.776 | E39: =+O39+AA39+AK39+AU39+AV39+AW39+BC39+BE39+BF39+BG39+BH39+BI39+BJ39+BB39+BD39 -> 87417.61 | F39: =+E39-D39 -> 23863.834 | J39: 6673.1 | K39: 5338.48 | L39: 5338.48 | N39: 0 | O39: =SUM(G39:N39) -> 17350.06 | Z39: 0 | AA39: =SUM(P39:Z39) -> 0 | AB39: 0 | AC39: 0 | AD39: 0 | AE39: 0 | AF39: 0 | AH39: 0 | AJ39: 0 | AK39: =SUM(AB39:AJ39) -> 0 | AR39: =+'[4]P 2-Salary '!$J$19 -> 23355.85 | AS39: =+'[5]P 2-Salary '!$J$18 -> 20019.3 | AT39: =+'[6]P 2-Salary '!$J$17 -> 26692.4 | AU39: =SUM(AL39:AT39) -> 70067.55 | AX39: 0 | AY39: 0 | BB39: =SUM(AX39:BA39) -> 0 | BE39: 0 | BH39: 0 | BL39: =+D39*5% -> 3177.6888 | BM39: =+BL39+D39 -> 66731.465
A40: =+A39+1 -> 37 | B40: Isabelle Veron | C40: 24.0385 | D40: =+C40*2080 -> 50000.08 | E40: =+O40+AA40+AK40+AU40+AV40+AW40+BC40+BE40+BF40+BG40+BH40+BI40+BJ40+BB40+BD40 -> 52500 | F40: =+E40-D40 -> 2499.92 | N40: 0 | O40: =SUM(G40:N40) -> 0 | Z40: 0 | AA40: =SUM(P40:Z40) -> 0 | AB40: 52500 | AH40: 0 | AK40: =SUM(AB40:AJ40) -> 52500 | AX40: 0 | AY40: 0 | BB40: =SUM(AX40:BA40) -> 0 | BL40: =+D40*5% -> 2500.004 | BM40: =+BL40+D40 -> 52500.084
A41: =+A40+1 -> 38 | B41: Jamal Noori | C41: 28.161 | D41: =+C41*2080 -> 58574.88 | E41: =+O41+AA41+AK41+AU41+AV41+AW41+BC41+BE41+BF41+BG41+BH41+BI41+BJ41+BB41+BD41 -> 66049.23 | F41: =+E41-D41 -> 7474.35 | N41: 0 | O41: =SUM(G41:N41) -> 0 | Z41: 0 | AA41: =SUM(P41:Z41) -> 0 | AB41: 0 | AC41: 0 | AD41: 0 | AE41: 0 | AF41: 0 | AH41: 0 | AI41: 0 | AJ41: 0 | AK41: =SUM(AB41:AJ41) -> 0 | AS41: =+'[5]P 2-Salary '!$J$23+5000 -> 35751.5 | AU41: =SUM(AL41:AT41) -> 35751.5 | AW41: =17482.34+5500+1215.39+1600 -> 25797.73 | AX41: 0 | AY41: 0 | AZ41: 4500 | BA41: 0 | BB41: =SUM(AX41:BA41) -> 4500 | BL41: =+D41*5% -> 2928.744 | BM41: =+BL41+D41 -> 61503.624
A42: =+A41+1 -> 39 | B42: Jean Cyprien | C42: 27.777 | D42: =+C42*2080 -> 57776.16 | E42: =+O42+AA42+AK42+AU42+AV42+AW42+BC42+BE42+BF42+BG42+BH42+BI42+BJ42+BB42+BD42 -> 60665 | F42: =+E42-D42 -> 2888.84 | N42: 0 | O42: =SUM(G42:N42) -> 0 | Z42: 0 | AA42: =SUM(P42:Z42) -> 0 | AB42: 0 | AC42: 0 | AD42: 0 | AE42: 0 | AF42: 0 | AH42: 0 | AJ42: 0 | AK42: =SUM(AB42:AJ42) -> 0 | AM42: =+'[9]P 2-Salary '!$J$17 -> 60665 | AU42: =SUM(AL42:AT42) -> 60665 | AX42: 0 | AY42: 0 | BB42: =SUM(AX42:BA42) -> 0 | BI42: 0 | BL42: =+D42*5% -> 2888.808 | BM42: =+BL42+D42 -> 60664.968
A43: =+A42+1 -> 40 | B43: Jehanzeb Louis | C43: 38.4615 | D43: =+C43*2080 -> 79999.92 | E43: =+O43+AA43+AK43+AU43+AV43+AW43+BC43+BE43+BF43+BG43+BH43+BI43+BJ43+BB43+BD43 -> 108494.61 | F43: =+E43-D43 -> 28494.69 | G43: 4200 | J43: 8400 | K43: 1680 | L43: 4200 | N43: 0 | O43: =SUM(G43:N43) -> 18480 | Z43: 0 | AA43: =SUM(P43:Z43) -> 0 | AB43: 0 | AC43: 0 | AD43: 0 | AE43: 0 | AF43: 0 | AH43: 0 | AJ43: 0 | AK43: =SUM(AB43:AJ43) -> 0 | AL43: =+'[8]P 2-Salary '!$J$18 -> 1680 | AM43: =+'[9]P 2-Salary '!$J$16 -> 4200 | AN43: =+'[7]P 2-Salary '!$J$20 -> 12600 | AO43: =+'[2]P 2-Salary '!$J$19 -> 21000 | AP43: =+'[10]P 2-Salary '!$J$21 -> 8400 | AQ43: =+'[11]P 2-Salary '!$J$21 -> 12600 | AR43: =+'[4]P 2-Salary '!$J$16 -> 8400 | AS43: =+'[5]P 2-Salary '!$J$16 -> 8400 | AT43: =+'[6]P 2-Salary '!$J$16 -> 8400 | AU43: =SUM(AL43:AT43) -> 85680 | AW43: 0 | AX43: 1950 | AY43: 0 | AZ43: 1923.07 | BA43: 0 | BB43: =SUM(AX43:BA43) -> 3873.07 | BC43: 0 | BF43: 461.54 | BG43: 0 | BL43: =+D43*5% -> 3999.996 | BM43: =+BL43+D43 -> 83999.916
A44: =+A43+1 -> 41 | B44: Jenna McGillcuddy | C44: 24.0385 | D44: =+C44*2080 -> 50000.08 | E44: =+O44+AA44+AK44+AU44+AV44+AW44+BC44+BE44+BF44+BG44+BH44+BI44+BJ44+BB44+BD44 -> 119500 | F44: =+E44-D44 -> 69499.92 | N44: 0 | O44: =SUM(G44:N44) -> 0 | P44: 7350 | S44: 14700 | Z44: 30450 | AA44: =SUM(P44:Z44) -> 52500 | AB44: 0 | AC44: 25000 | AD44: 0 | AE44: 0 | AF44: 0 | AH44: 0 | AI44: 0 | AJ44: 0 | AK44: =SUM(AB44:AJ44) -> 25000 | AU44: =SUM(AL44:AT44) -> 0 | AX44: 0 | AY44: 42000 | BB44: =SUM(AX44:BA44) -> 42000 | BI44: 0 | BL44: =+D44*5% -> 2500.004 | BM44: =+BL44+D44 -> 52500.084
A45: =+A44+1 -> 42 | B45: Kamela Azizi | C45: 28.161 | D45: =+C45*2080 -> 58574.88 | E45: =+O45+AA45+AK45+AU45+AV45+AW45+BC45+BE45+BF45+BG45+BH45+BI45+BJ45+BB45+BD45 -> 62056.91 | F45: =+E45-D45 -> 3482.03 | N45: 0 | O45: =SUM(G45:N45) -> 0 | Z45: 0 | AA45: =SUM(P45:Z45) -> 0 | AB45: 0 | AC45: 0 | AD45: 0 | AE45: 0 | AF45: 0 | AH45: 6054.61 | AI45: 0 | AJ45: 0 | AK45: =SUM(AB45:AJ45) -> 6054.61 | AU45: =SUM(AL45:AT45) -> 0 | AX45: 0 | AY45: 52500 | AZ45: 0 | BA45: 3502.3 | BB45: =SUM(AX45:BA45) -> 56002.3 | BL45: =+D45*5% -> 2928.744 | BM45: =+BL45+D45 -> 61503.624
A46: =+A45+1 -> 43 | B46: Konjit Edward | C46: 31.2588 | D46: =+C46*2080 -> 65018.304 | E46: =+O46+AA46+AK46+AU46+AV46+AW46+BC46+BE46+BF46+BG46+BH46+BI46+BJ46+BB46+BD46 -> 54122.82 | F46: =+E46-D46 -> -10895.484 | H46: 13393.8 | N46: 0 | O46: =SUM(G46:N46) -> 13393.8 | Z46: 0 | AA46: =SUM(P46:Z46) -> 0 | AB46: 0 | AC46: 0 | AD46: 0 | AE46: 0 | AF46: 0 | AH46: 0 | AJ46: 0 | AK46: =SUM(AB46:AJ46) -> 0 | AU46: =SUM(AL46:AT46) -> 0 | AX46: 0 | AY46: 0 | AZ46: 11970 | BA46: 0 | BB46: =SUM(AX46:BA46) -> 11970 | BE46: 24132.72 | BH46: =8752.46-4126.16 -> 4626.3 | BL46: =+D46*5% -> 3250.9152 | BM46: =+BL46+D46 -> 68269.219
A47: =+A46+1 -> 44 | B47: Laryssa Romenko | C47: 27.7771 | D47: =+C47*2080 -> 57776.368 | E47: =+O47+AA47+AK47+AU47+AV47+AW47+BC47+BE47+BF47+BG47+BH47+BI47+BJ47+BB47+BD47 -> 80684.45 | F47: =+E47-D47 -> 22908.082 | J47: 6066.5 | K47: 4853.2 | L47: 6066.5 | N47: 0 | O47: =SUM(G47:N47) -> 16986.2 | Z47: 0 | AA47: =SUM(P47:Z47) -> 0 | AB47: 0 | AC47: 0 | AD47: 0 | AE47: 0 | AF47: 0 | AH47: 0 | AJ47: 0 | AK47: =SUM(AB47:AJ47) -> 0 | AR47: =+'[4]P 2-Salary '!$J$17 -> 48532 | AS47: =+'[5]P 2-Salary '!$J$17 -> 9099.75 | AT47: =+'[6]P 2-Salary '!$J$18 -> 6066.5 | AU47: =SUM(AL47:AT47) -> 63698.25 | AX47: 0 | AY47: 0 | BB47: =SUM(AX47:BA47) -> 0 | BL47: =+D47*5% -> 2888.8184 | BM47: =+BL47+D47 -> 60665.186
A48: =+A47+1 -> 45 | B48: Manizha Nuzhat | C48: =68000/2080 -> 32.692308 | D48: =+C48*2080 -> 68000 | E48: =+O48+AA48+AK48+AU48+AV48+AW48+BC48+BE48+BF48+BG48+BH48+BI48+BJ48+BB48+BD48 -> 108888.2 | F48: =+E48-D48 -> 40888.2 | G48: 3570 | H48: 1428 | J48: 4284 | K48: 2142 | L48: 3570 | N48: =+'[3]PC Admin & Client (Regular)'!$E$19 -> 2142 | O48: =SUM(G48:N48) -> 17136 | P48: 2856 | Q48: 1428 | T48: 2142 | U48: 1428 | W48: 1428 | X48: 2142 | Y48: 2142 | Z48: 2142 | AA48: =SUM(P48:Z48) -> 15708 | AB48: 0 | AC48: 4004 | AD48: 6673 | AE48: 10010 | AF48: 2142 | AH48: 5361.54 | AI48: 3250 | AJ48: 6673 | AK48: =SUM(AB48:AJ48) -> 38113.54 | AL48: =+'[8]P 2-Salary '!$J$21 -> 1428 | AM48: =+'[9]P 2-Salary '!$J$20 -> 2142 | AN48: =+'[7]P 2-Salary '!$J$22 -> 3570 | AO48: =+'[2]P 2-Salary '!$J$18 -> 7140 | AP48: =+'[10]P 2-Salary '!$J$18 -> 2856 | AQ48: =+'[11]P 2-Salary '!$J$18 -> 2856 | AR48: =+'[4]P 2-Salary '!$J$20 -> 3587 | AS48: =+'[5]P 2-Salary '!$J$19 -> 2856 | AT48: =+'[6]P 2-Salary '!$J$20 -> 5739.2 | AU48: =SUM(AL48:AT48) -> 32174.2 | AX48: 2040 | AY48: 1428 | AZ48: 2288.46 | BB48: =SUM(AX48:BA48) -> 5756.46 | BL48: =+D48*5% -> 3400 | BM48: =+BL48+D48 -> 71400
A49: =+A48+1 -> 46 | B49: Mariam Noorzad | C49: 24.0385 | D49: =+C49*2080 -> 50000.08 | E49: =+O49+AA49+AK49+AU49+AV49+AW49+BC49+BE49+BF49+BG49+BH49+BI49+BJ49+BB49+BD49 -> 52500 | F49: =+E49-D49 -> 2499.92 | N49: 0 | O49: =SUM(G49:N49) -> 0 | Z49: 0 | AA49: =SUM(P49:Z49) -> 0 | AB49: 0 | AC49: 0 | AD49: 0 | AE49: 52500 | AF49: 0 | AH49: 0 | AJ49: 0 | AK49: =SUM(AB49:AJ49) -> 52500 | AU49: =SUM(AL49:AT49) -> 0 | AX49: 0 | AY49: 0 | BB49: =SUM(AX49:BA49) -> 0 | BL49: =+D49*5% -> 2500.004 | BM49: =+BL49+D49 -> 52500.084
A50: =+A49+1 -> 47 | B50: Megdad Mehmoodi | C50: 27.777 | D50: =+C50*2080 -> 57776.16 | E50: =+O50+AA50+AK50+AU50+AV50+AW50+BC50+BE50+BF50+BG50+BH50+BI50+BJ50+BB50+BD50 -> 60665 | F50: =+E50-D50 -> 2888.84 | N50: 0 | O50: =SUM(G50:N50) -> 0 | Z50: 0 | AA50: =SUM(P50:Z50) -> 0 | AB50: 0 | AC50: 0 | AD50: 0 | AE50: 60665 | AF50: 0 | AH50: 0 | AJ50: 0 | AK50: =SUM(AB50:AJ50) -> 60665 | AU50: =SUM(AL50:AT50) -> 0 | AX50: 0 | AY50: 0 | BB50: =SUM(AX50:BA50) -> 0 | BL50: =+D50*5% -> 2888.808 | BM50: =+BL50+D50 -> 60664.968
A51: =+A50+1 -> 48 | B51: Miramjan Sadaqat | C51: =57000/2080 -> 27.403846 | D51: =+C51*2080 -> 57000 | E51: =+O51+AA51+AK51+AU51+AV51+AW51+BC51+BE51+BF51+BG51+BH51+BI51+BJ51+BB51+BD51 -> 74812.5 | F51: =+E51-D51 -> 17812.5 | N51: 0 | O51: =SUM(G51:N51) -> 0 | T51: 14962.5 | Z51: 0 | AA51: =SUM(P51:Z51) -> 14962.5 | AB51: 0 | AC51: 0 | AD51: 59850 | AE51: 0 | AF51: 0 | AH51: 0 | AJ51: 0 | AK51: =SUM(AB51:AJ51) -> 59850 | AU51: =SUM(AL51:AT51) -> 0 | AW51: 0 | AX51: 0 | AY51: 0 | BB51: =SUM(AX51:BA51) -> 0 | BL51: =+D51*5% -> 2850 | BM51: =+BL51+D51 -> 59850
A52: =+A51+1 -> 49 | B52: Mohammad Akbar Akbar | C52: 24.0385 | D52: =+C52*904 -> 21730.804 | E52: =+O52+AA52+AK52+AU52+AV52+AW52+BC52+BE52+BF52+BG52+BH52+BI52+BJ52+BB52+BD52 -> 23846.19 | F52: =+E52-D52 -> 2115.386 | N52: 0 | O52: =SUM(G52:N52) -> 0 | Z52: 0 | AA52: =SUM(P52:Z52) -> 0 | AK52: =SUM(AB52:AJ52) -> 0 | AX52: 0 | AY52: 0 | AZ52: 23846.19 | BB52: =SUM(AX52:BA52) -> 23846.19 | BL52: =+D52*5% -> 1086.5402 | BM52: =+BL52+D52 -> 22817.344
A53: =+A52+1 -> 50 | B53: Mohammad Baig | C53: =65000/2080 -> 31.25 | D53: =+C53*2080 -> 65000 | E53: =+O53+AA53+AK53+AU53+AV53+AW53+BC53+BE53+BF53+BG53+BH53+BI53+BJ53+BB53+BD53 -> 68354.57 | F53: =+E53-D53 -> 3354.57 | N53: 0 | O53: =SUM(G53:N53) -> 0 | Z53: 0 | AA53: =SUM(P53:Z53) -> 0 | AK53: =SUM(AB53:AJ53) -> 0 | AM53: =+'[9]P 2-Salary '!$J$21+600 -> 7425 | AN53: 0 | AO53: =+'[2]P 2-Salary '!$J$20 -> 54600 | AU53: =SUM(AL53:AT53) -> 62025 | AW53: 6329.57 | AX53: 0 | AY53: 0 | BA53: 0 | BB53: =SUM(AX53:BA53) -> 0 | BC53: 0 | BL53: =+D53*5% -> 3250 | BM53: =+BL53+D53 -> 68250
A54: =+A53+1 -> 51 | B54: Morgan Swindall | C54: =55000/2080 -> 26.442308 | D54: =+C54*2080 -> 55000 | E54: =+O54+AA54+AK54+AU54+AV54+AW54+BC54+BE54+BF54+BG54+BH54+BI54+BJ54+BB54+BD54 -> 62730.78 | F54: =+E54-D54 -> 7730.78 | N54: 0 | O54: =SUM(G54:N54) -> 0 | Z54: 0 | AA54: =SUM(P54:Z54) -> 0 | AK54: =SUM(AB54:AJ54) -> 0 | AO54: =+'[2]P 2-Salary '!$J$22 -> 57750 | AU54: =SUM(AL54:AT54) -> 57750 | AW54: 4980.78 | AX54: 0 | AY54: 0 | BA54: 0 | BB54: =SUM(AX54:BA54) -> 0 | BL54: =+D54*5% -> 2750 | BM54: =+BL54+D54 -> 57750
A55: =+A54+1 -> 52 | B55: Munsif Noor Ul Haq | C55: 24.0385 | D55: =+C55*2080 -> 50000.08 | E55: =+O55+AA55+AK55+AU55+AV55+AW55+BC55+BE55+BF55+BG55+BH55+BI55+BJ55+BB55+BD55 -> 52500 | F55: =+E55-D55 -> 2499.92 | N55: 0 | O55: =SUM(G55:N55) -> 0 | P55: 21000 | Z55: 31500 | AA55: =SUM(P55:Z55) -> 52500 | AB55: 0 | AC55: 0 | AD55: 0 | AE55: 0 | AF55: 0 | AH55: 0 | AJ55: 0 | AK55: =SUM(AB55:AJ55) -> 0 | AU55: =SUM(AL55:AT55) -> 0 | AX55: 0 | AY55: 0 | BB55: =SUM(AX55:BA55) -> 0 | BI55: 0 | BL55: =+D55*5% -> 2500.004 | BM55: =+BL55+D55 -> 52500.084
A56: =+A55+1 -> 53 | B56: Najia Hashimzada | C56: 30.7212 | D56: =+C56*2080 -> 63900.096 | E56: =+O56+AA56+AK56+AU56+AV56+AW56+BC56+BE56+BF56+BG56+BH56+BI56+BJ56+BB56+BD56 -> 67319.98 | F56: =+E56-D56 -> 3419.884 | N56: 0 | O56: =SUM(G56:N56) -> 0 | Z56: 0 | AA56: =SUM(P56:Z56) -> 0 | AB56: 0 | AC56: 0 | AD56: 0 | AE56: 0 | AF56: 0 | AH56: 0 | AJ56: 0 | AK56: =SUM(AB56:AJ56) -> 0 | AL56: =+'[8]P 2-Salary '!$J$17+3000+1000 -> 66398.35 | AU56: =SUM(AL56:AT56) -> 66398.35 | AX56: 0 | AY56: 0 | BB56: =SUM(AX56:BA56) -> 0 | BC56: 921.63 | BL56: =+D56*5% -> 3195.0048 | BM56: =+BL56+D56 -> 67095.101
A57: =+A56+1 -> 54 | B57: Nassrullah Mohibi | C57: 25.601 | D57: =+C57*2080 -> 53250.08 | E57: =+O57+AA57+AK57+AU57+AV57+AW57+BC57+BE57+BF57+BG57+BH57+BI57+BJ57+BB57+BD57 -> 55913 | F57: =+E57-D57 -> 2662.92 | N57: 0 | O57: =SUM(G57:N57) -> 0 | Z57: 0 | AA57: =SUM(P57:Z57) -> 0 | AB57: 0 | AC57: 0 | AD57: 55913 | AE57: 0 | AF57: 0 | AH57: 0 | AJ57: 0 | AK57: =SUM(AB57:AJ57) -> 55913 | AU57: =SUM(AL57:AT57) -> 0 | AX57: 0 | AY57: 0 | BB57: =SUM(AX57:BA57) -> 0 | BL57: =+D57*5% -> 2662.504 | BM57: =+BL57+D57 -> 55912.584
A58: =+A57+1 -> 55 | B58: Parwana Noori | C58: 24.0385 | D58: =+C58*2080 -> 50000.08 | E58: =+O58+AA58+AK58+AU58+AV58+AW58+BC58+BE58+BF58+BG58+BH58+BI58+BJ58+BB58+BD58 -> 55788.47 | F58: =+E58-D58 -> 5788.39 | N58: 0 | O58: =SUM(G58:N58) -> 0 | Z58: 0 | AA58: =SUM(P58:Z58) -> 0 | AB58: 0 | AC58: 0 | AD58: 0 | AE58: 0 | AF58: 0 | AH58: 0 | AJ58: 0 | AK58: =SUM(AB58:AJ58) -> 0 | AO58: =+'[2]P 2-Salary '!$J$29 -> 52500 | AU58: =SUM(AL58:AT58) -> 52500 | AW58: 3288.47 | AX58: 0 | AY58: 0 | BA58: 0 | BB58: =SUM(AX58:BA58) -> 0 | BL58: =+D58*5% -> 2500.004 | BM58: =+BL58+D58 -> 52500.084
A59: =+A58+1 -> 56 | B59: Ramaswami Swaminathan Abirami | C59: 25.601 | D59: =+C59*2080 -> 53250.08 | E59: =+O59+AA59+AK59+AU59+AV59+AW59+BC59+BE59+BF59+BG59+BH59+BI59+BJ59+BB59+BD59 -> 55912.58 | F59: =+E59-D59 -> 2662.5 | N59: 0 | O59: =SUM(G59:N59) -> 0 | Z59: 0 | AA59: =SUM(P59:Z59) -> 0 | AB59: 0 | AC59: 0 | AD59: 0 | AE59: 0 | AF59: 0 | AH59: 0 | AJ59: 0 | AK59: =SUM(AB59:AJ59) -> 0 | AN59: =+'[7]P 2-Salary '!$J$19 -> 27956.29 | AO59: =+'[2]P 2-Salary '!$J$23 -> 27956.29 | AU59: =SUM(AL59:AT59) -> 55912.58 | AX59: 0 | AY59: 0 | BB59: =SUM(AX59:BA59) -> 0 | BL59: =+D59*5% -> 2662.504 | BM59: =+BL59+D59 -> 55912.584
A60: =+A59+1 -> 57 | B60: TBH - Razia Mahrami | C60: 33.2813 | D60: =+C60*2080 -> 69225.104 | E60: =+O60+AA60+AK60+AU60+AV60+AW60+BC60+BE60+BF60+BG60+BH60+BI60+BJ60+BB60+BD60 -> 72666 | F60: =+E60-D60 -> 3440.896 | N60: 0 | O60: =SUM(G60:N60) -> 0 | Z60: 0 | AA60: =SUM(P60:Z60) -> 0 | AB60: 0 | AC60: 0 | AD60: 0 | AE60: 72666 | AF60: 0 | AH60: 0 | AJ60: 0 | AK60: =SUM(AB60:AJ60) -> 72666 | AU60: =SUM(AL60:AT60) -> 0 | AX60: 0 | AY60: 0 | BB60: =SUM(AX60:BA60) -> 0 | BL60: =+D60*5% -> 3461.2552 | BM60: =+BL60+D60 -> 72686.359
A61: =+A60+1 -> 58 | B61: Ruby Diaz | C61: 24.0385 | D61: =+C61*2080 -> 50000.08 | E61: =+O61+AA61+AK61+AU61+AV61+AW61+BC61+BE61+BF61+BG61+BH61+BI61+BJ61+BB61+BD61 -> 52523.06 | F61: =+E61-D61 -> 2522.98 | N61: 0 | O61: =SUM(G61:N61) -> 0 | Z61: 0 | AA61: =SUM(P61:Z61) -> 0 | AC61: 0 | AD61: 0 | AE61: 0 | AF61: =5750+1100 -> 6850 | AG61: 0 | AH61: 0 | AJ61: 0 | AK61: =SUM(AB61:AJ61) -> 6850 | AU61: =SUM(AL61:AT61) -> 0 | AV61: 45673.06 | AX61: 0 | AY61: 0 | BB61: =SUM(AX61:BA61) -> 0 | BL61: =+D61*5% -> 2500.004 | BM61: =+BL61+D61 -> 52500.084
A62: =+A61+1 -> 59 | B62: Sana Amini | C62: 24.0385 | D62: =+C62*2080 -> 50000.08 | E62: =+O62+AA62+AK62+AU62+AV62+AW62+BC62+BE62+BF62+BG62+BH62+BI62+BJ62+BB62+BD62 -> 52500 | F62: =+E62-D62 -> 2499.92 | N62: 0 | O62: =SUM(G62:N62) -> 0 | Z62: 0 | AA62: =SUM(P62:Z62) -> 0 | AB62: 52500 | AC62: 0 | AD62: 0 | AE62: 0 | AF62: 0 | AH62: 0 | AJ62: 0 | AK62: =SUM(AB62:AJ62) -> 52500 | AU62: =SUM(AL62:AT62) -> 0 | AX62: 0 | AY62: 0 | BB62: =SUM(AX62:BA62) -> 0 | BL62: =+D62*5% -> 2500.004 | BM62: =+BL62+D62 -> 52500.084
A63: =+A62+1 -> 60 | B63: TBH - Albab | C63: 24.0385 | D63: 22500 | E63: =+O63+AA63+AK63+AU63+AV63+AW63+BC63+BE63+BF63+BG63+BH63+BI63+BJ63+BB63+BD63 -> 42500 | F63: =+E63-D63 -> 20000 | N63: 0 | O63: =SUM(G63:N63) -> 0 | Z63: 0 | AA63: =SUM(P63:Z63) -> 0 | AB63: 0 | AC63: 0 | AD63: 0 | AE63: =22500+20000 -> 42500 | AF63: 0 | AG63: 0 | AH63: 0 | AJ63: 0 | AK63: =SUM(AB63:AJ63) -> 42500 | AU63: =SUM(AL63:AT63) -> 0 | AX63: 0 | AY63: 0 | BB63: =SUM(AX63:BA63) -> 0 | BC63: 0 | BL63: =+D63*5% -> 1125 | BM63: =+BL63+D63 -> 23625
A64: =+A63+1 -> 61 | B64: Sarah Zullo | C64: 50.1732 | D64: =+C64*2080 -> 104360.26 | E64: =+O64+AA64+AK64+AU64+AV64+AW64+BC64+BE64+BF64+BG64+BH64+BI64+BJ64+BB64+BD64 -> 168567.61 | F64: =+E64-D64 -> 64207.354 | G64: 4383.12 | H64: 2191.56 | J64: 6574.68 | K64: 3287.34 | L64: 5478.9 | N64: 3287.34 | O64: =SUM(G64:N64) -> 25202.94 | P64: 4383.12 | Q64: 2191.56 | T64: 3287.34 | U64: 2191.56 | W64: 2191.56 | X64: 3287.34 | Y64: 3287.35 | Z64: 3287.34 | AA64: =SUM(P64:Z64) -> 24107.17 | AB64: 5479 | AC64: 6575 | AD64: 10958 | AE64: 10958 | AF64: =2192-1100 -> 1092 | AH64: 8027.72 | AI64: 6750 | AJ64: 10958 | AK64: =SUM(AB64:AJ64) -> 60797.72 | AL64: =+'[8]P 2-Salary '!$J$14-1500 -> 691.58 | AM64: =+'[9]P 2-Salary '!$J$14-600 -> 2687.37 | AN64: =+'[7]P 2-Salary '!$J$14 -> 5478.95 | AO64: =+'[2]P 2-Salary '!$J$14 -> 10957.8 | AP64: =+'[10]P 2-Salary '!$J$14 -> 4383.12 | AQ64: =+'[11]P 2-Salary '!$J$14 -> 5400 | AR64: =+'[4]P 2-Salary '!$J$14 -> 5478.9 | AS64: =+'[5]P 2-Salary '!$J$14-2500 -> 1883.12 | AT64: =+'[6]P 2-Salary '!$J$14-1500 -> 7266.24 | AU64: =SUM(AL64:AT64) -> 44227.08 | AV64: 0 | AW64: 2805.22 | AX64: 2191.58 | AY64: 2191.58 | AZ64: 3913.51 | BA64: 0 | BB64: =SUM(AX64:BA64) -> 8296.67 | BI64: 3130.81 | BL64: =+D64*5% -> 5218.0128 | BM64: =+BL64+D64 -> 109578.27
A65: =+A64+1 -> 62 | B65: Shakil Tabassum | C65: 46.1099 | D65: =+C65*2080 -> 95908.592 | E65: =+O65+AA65+AK65+AU65+AV65+AW65+BC65+BE65+BF65+BG65+BH65+BI65+BJ65+BB65+BD65 -> 153366.22 | F65: =+E65-D65 -> 57457.624 | G65: 4028.16 | H65: 2014.08 | J65: 6042.24 | K65: 3021.12 | L65: 5035.2 | N65: 3021.12 | O65: =SUM(G65:N65) -> 23161.92 | P65: 4028.16 | Q65: 2014.08 | U65: 2014.08 | W65: 2014.08 | X65: 3021.12 | Y65: 3021.12 | Z65: 3021.12 | AA65: =SUM(P65:Z65) -> 19133.76 | AB65: 5035 | AC65: 6041 | AD65: 10070 | AE65: 10070 | AF65: 2014 | AH65: 7930.89 | AI65: 5295 | AJ65: 10070 | AK65: =SUM(AB65:AJ65) -> 56525.89 | AL65: =+'[8]P 2-Salary '!$J$15-1500 -> 514.08 | AM65: =+'[9]P 2-Salary '!$J$15 -> 3021.12 | AN65: =+'[7]P 2-Salary '!$J$15 -> 5035.2 | AO65: =+'[2]P 2-Salary '!$J$15 -> 10070.4 | AP65: =+'[10]P 2-Salary '!$J$15-100 -> 3928.16 | AQ65: =+'[11]P 2-Salary '!$J$15 -> 4236.3456 | AR65: =+'[4]P 2-Salary '!$J$15 -> 5035.2 | AS65: =+'[5]P 2-Salary '!$J$15-2500 -> 1528.16 | AT65: =+'[6]P 2-Salary '!$J$15 -> 8056.32 | AU65: =SUM(AL65:AT65) -> 41424.986 | AV65: 0 | AW65: 1879.9 | AX65: 2014.08 | AY65: 2014.08 | AZ65: 4334.34 | BA65: 0 | BB65: =SUM(AX65:BA65) -> 8362.5 | BI65: 2877.26 | BL65: =+D65*5% -> 4795.4296 | BM65: =+BL65+D65 -> 100704.02
A66: =+A65+1 -> 63 | B66: Slenka Luna Flores | C66: 24.0385 | D66: =+C66*2080 -> 50000.08 | E66: =+O66+AA66+AK66+AU66+AV66+AW66+BC66+BE66+BF66+BG66+BH66+BI66+BJ66+BB66+BD66 -> 52500 | F66: =+E66-D66 -> 2499.92 | N66: 0 | O66: =SUM(G66:N66) -> 0 | Z66: 0 | AA66: =SUM(P66:Z66) -> 0 | AB66: 0 | AC66: 52500 | AD66: 0 | AE66: 0 | AF66: 0 | AH66: 0 | AJ66: 0 | AK66: =SUM(AB66:AJ66) -> 52500 | AU66: =SUM(AL66:AT66) -> 0 | AX66: 0 | AY66: 0 | BB66: =SUM(AX66:BA66) -> 0 | BL66: =+D66*5% -> 2500.004 | BM66: =+BL66+D66 -> 52500.084
A67: =+A66+1 -> 64 | B67: Tahera Azizi | C67: 28.0048 | D67: =+C67*2080 -> 58249.984 | E67: =+O67+AA67+AK67+AU67+AV67+AW67+BC67+BE67+BF67+BG67+BH67+BI67+BJ67+BB67+BD67 -> 110674.96 | F67: =+E67-D67 -> 52424.976 | G67: 21406.87 | H67: 24464.99 | I67: 6116.25 | N67: 9174.37 | O67: =SUM(G67:N67) -> 61162.48 | Z67: 0 | AA67: =SUM(P67:Z67) -> 0 | AC67: 0 | AD67: 0 | AE67: 0 | AF67: 0 | AH67: 0 | AJ67: 0 | AK67: =SUM(AB67:AJ67) -> 0 | AO67: 0 | AU67: =SUM(AL67:AT67) -> 0 | AX67: 49512.48 | AY67: 0 | BB67: =SUM(AX67:BA67) -> 49512.48 | BL67: =+D67*5% -> 2912.4992 | BM67: =+BL67+D67 -> 61162.483
A68: =+A67+1 -> 65 | B68: Taylor Woody | C68: 24.0385 | D68: =+C68*2080 -> 50000.08 | E68: =+O68+AA68+AK68+AU68+AV68+AW68+BC68+BE68+BF68+BG68+BH68+BI68+BJ68+BB68+BD68 -> 52550 | F68: =+E68-D68 -> 2549.92 | N68: 0 | O68: =SUM(G68:N68) -> 0 | Z68: 0 | AA68: =SUM(P68:Z68) -> 0 | AC68: 0 | AD68: 0 | AE68: 0 | AF68: 0 | AH68: 0 | AJ68: 0 | AK68: =SUM(AB68:AJ68) -> 0 | AP68: =+'[10]P 2-Salary '!$J$22+100 -> 10550 | AQ68: =+'[11]P 2-Salary '!$J$20 -> 42000 | AU68: =SUM(AL68:AT68) -> 52550 | AX68: 0 | AY68: 0 | BB68: =SUM(AX68:BA68) -> 0 | BL68: =+D68*5% -> 2500.004 | BM68: =+BL68+D68 -> 52500.084
A69: =+A68+1 -> 66 | B69: Tilahun Zewadi | C69: 28.8462 | D69: =+C69*2080 -> 60000.096 | E69: =+O69+AA69+AK69+AU69+AV69+AW69+BC69+BE69+BF69+BG69+BH69+BI69+BJ69+BB69+BD69 -> 87423.11 | F69: =+E69-D69 -> 27423.014 | N69: 0 | O69: =SUM(G69:N69) -> 0 | Q69: 18900 | R69: 12600 | Z69: 0 | AA69: =SUM(P69:Z69) -> 31500 | AD69: 30000 | AH69: 9923.11 | AI69: 16000 | AK69: =SUM(AB69:AJ69) -> 55923.11 | AU69: =SUM(AL69:AT69) -> 0 | AX69: 0 | AY69: 0 | BB69: =SUM(AX69:BA69) -> 0
A70: =+A69+1 -> 67 | B70: Viktoria Sutanovska | C70: 33.2813 | D70: =+C70*2080 -> 69225.104 | E70: =+O70+AA70+AK70+AU70+AV70+AW70+BC70+BE70+BF70+BG70+BH70+BI70+BJ70+BB70+BD70 -> 96886.38 | F70: =+E70-D70 -> 27661.276 | J70: 7268.6 | L70: 10902.9 | N70: 5814.88 | O70: =SUM(G70:N70) -> 23986.38 | Z70: 0 | AA70: =SUM(P70:Z70) -> 0 | AB70: 0 | AC70: 0 | AD70: 0 | AE70: 0 | AF70: 0 | AH70: 0 | AJ70: 0 | AK70: =SUM(AB70:AJ70) -> 0 | AR70: =+'[4]P 2-Salary '!$J$21 -> 21420 | AS70: =+'[5]P 2-Salary '!$J$22 -> 24990 | AT70: =+'[6]P 2-Salary '!$J$24+1500 -> 26490 | AU70: =SUM(AL70:AT70) -> 72900 | AX70: 0 | AY70: 0 | BB70: =SUM(AX70:BA70) -> 0
A71: =+A70+1 -> 68 | B71: Wade William | C71: 25.601 | D71: =+C71*2080 -> 53250.08 | E71: =+O71+AA71+AK71+AU71+AV71+AW71+BC71+BE71+BF71+BG71+BH71+BI71+BJ71+BB71+BD71 -> 56527.42 | F71: =+E71-D71 -> 3277.34 | N71: 0 | O71: =SUM(G71:N71) -> 0 | Z71: 0 | AA71: =SUM(P71:Z71) -> 0 | AB71: 0 | AC71: 0 | AD71: 0 | AE71: 55913 | AF71: 0 | AH71: 614.42 | AJ71: 0 | AK71: =SUM(AB71:AJ71) -> 56527.42 | AU71: =SUM(AL71:AT71) -> 0 | AX71: 0 | AY71: 0 | BB71: =SUM(AX71:BA71) -> 0
A72: =+A71+1 -> 69 | B72: Yama Ahmadi | C72: 30.5547 | D72: =+C72*2080 -> 63553.776 | E72: =+O72+AA72+AK72+AU72+AV72+AW72+BC72+BE72+BF72+BG72+BH72+BI72+BJ72+BB72+BD72 -> 71400 | F72: =+E72-D72 -> 7846.224 | N72: 0 | O72: =SUM(G72:N72) -> 0 | Z72: 0 | AA72: =SUM(P72:Z72) -> 0 | AB72: 0 | AC72: 0 | AD72: 0 | AE72: 0 | AF72: 0 | AH72: 0 | AJ72: 0 | AK72: =SUM(AB72:AJ72) -> 0 | AO72: =+'[2]P 2-Salary '!$J$21 -> 71400 | AU72: =SUM(AL72:AT72) -> 71400 | AX72: 0 | AY72: 0 | BB72: =SUM(AX72:BA72) -> 0
A73: =+A72+1 -> 70 | B73: Ziai Shafiullah | C73: =65000/2080 -> 31.25 | D73: =+C73*904 -> 28250 | E73: =+O73+AA73+AK73+AU73+AV73+AW73+BC73+BE73+BF73+BG73+BH73+BI73+BJ73+BB73+BD73 -> 38250 | F73: =+E73-D73 -> 10000 | N73: 0 | O73: =SUM(G73:N73) -> 0 | Z73: 0 | AA73: =SUM(P73:Z73) -> 0 | AK73: =SUM(AB73:AJ73) -> 0 | AU73: =SUM(AL73:AT73) -> 0 | AX73: 0 | AY73: 0 | AZ73: 38250 | BB73: =SUM(AX73:BA73) -> 38250
A74: =+A73+1 -> 71 | B74: TBH - Annie Phillips | C74: 32.6923 | D74: =+C74*(2080-160-160) -> 57538.448 | E74: =+O74+AA74+AK74+AU74+AV74+AW74+BC74+BE74+BF74+BG74+BH74+BI74+BJ74+BB74+BD74 -> 99450 | F74: =+E74-D74 -> 41911.552 | H74: 7150 | I74: 6500 | J74: 6500 | K74: 6500 | L74: 9100 | M74: 9750 | N74: 0 | O74: =SUM(G74:N74) -> 45500 | Z74: 0 | AA74: =SUM(P74:Z74) -> 0 | AK74: =SUM(AB74:AJ74) -> 0 | AL74: =+'[8]P 2-Salary '!$J$16 -> 7140 | AN74: =+'[7]P 2-Salary '!$J$23 -> 17850 | AP74: =+'[10]P 2-Salary '!$J$19 -> 14280 | AQ74: =+'[11]P 2-Salary '!$J$19 -> 14680 | AU74: =SUM(AL74:AT74) -> 53950 | AX74: 0 | AY74: 0 | BB74: =SUM(AX74:BA74) -> 0 | BD74: 0 | BL74: =+D74*5% -> 2876.9224 | BM74: =+BL74+D74 -> 60415.37
A75: 72 | B75: TBH - Case Manager | C75: 24.0385 | D75: 50000 | E75: =+O75+AA75+AK75+AU75+AV75+AW75+BC75+BE75+BF75+BG75+BH75+BI75+BJ75+BB75+BD75 -> 50000 | F75: =+E75-D75 -> 0 | N75: 0 | O75: =SUM(G75:N75) -> 0 | Z75: 0 | AA75: =SUM(P75:Z75) -> 0 | AK75: =SUM(AB75:AJ75) -> 0 | AU75: =SUM(AL75:AT75) -> 0 | AX75: 50000 | AY75: 0 | BB75: =SUM(AX75:BA75) -> 50000
A76: 73 | B76: TBH - Outreach Coordinator | C76: 24.0385 | D76: =+C76*1040 -> 25000.04 | E76: =+O76+AA76+AK76+AU76+AV76+AW76+BC76+BE76+BF76+BG76+BH76+BI76+BJ76+BB76+BD76 -> 38125 | F76: =+E76-D76 -> 13124.96 | N76: 0 | O76: =SUM(G76:N76) -> 0 | Z76: 0 | AA76: =SUM(P76:Z76) -> 0 | AK76: =SUM(AB76:AJ76) -> 0 | AU76: =SUM(AL76:AT76) -> 0 | AX76: 25000 | AY76: 13125 | BB76: =SUM(AX76:BA76) -> 38125
A77: 74 | B77: TBH - Donation Assistant | C77: 24.0385 | D77: =+C77*1040 -> 25000.04 | E77: =+O77+AA77+AK77+AU77+AV77+AW77+BC77+BE77+BF77+BG77+BH77+BI77+BJ77+BB77+BD77 -> 38125 | F77: =+E77-D77 -> 13124.96 | N77: 0 | O77: =SUM(G77:N77) -> 0 | Z77: 0 | AA77: =SUM(P77:Z77) -> 0 | AK77: =SUM(AB77:AJ77) -> 0 | AX77: 25000 | AY77: 13125 | BB77: =SUM(AX77:BA77) -> 38125
A78: 75 | B78: TBH - Case Manager | C78: =52500/2080 -> 25.240385 | D78: =+C78*2080 -> 52500 | E78: =+O78+AA78+AK78+AU78+AV78+AW78+BC78+BE78+BF78+BG78+BH78+BI78+BJ78+BB78+BD78 -> 27500 | F78: =+E78-D78 -> -25000 | N78: 0 | O78: =SUM(G78:N78) -> 0 | Z78: 0 | AA78: =SUM(P78:Z78) -> 0 | AC78: 27500 | AK78: =SUM(AB78:AJ78) -> 27500 | AU78: =SUM(AL78:AT78) -> 0 | AX78: 0 | AY78: 0 | BB78: =SUM(AX78:BA78) -> 0 | BL78: =+D78*5% -> 2625 | BM78: =+BL78+D78 -> 55125
A79: 76 | B79: TBH - Case Manager | C79: =+D79/2080 -> 25.240385 | D79: 52500 | E79: =+O79+AA79+AK79+AU79+AV79+AW79+BC79+BE79+BF79+BG79+BH79+BI79+BJ79+BB79+BD79 -> 52500 | F79: =+E79-D79 -> 0 | N79: 0 | O79: =SUM(G79:N79) -> 0 | Z79: 0 | AA79: =SUM(P79:Z79) -> 0 | AF79: 52500 | AG79: 0 | AH79: 0 | AI79: 0 | AK79: =SUM(AB79:AJ79) -> 52500 | AU79: =SUM(AL79:AT79) -> 0 | AX79: 0 | AY79: 0 | BB79: =SUM(AX79:BA79) -> 0 | BL79: =+D79*5% -> 2625 | BM79: =+BL79+D79 -> 55125
A80: =+A79+1 -> 77 | B80: TBH - Case Manager | C80: =+D80/2080 -> 25.240385 | D80: 52500 | E80: =+O80+AA80+AK80+AU80+AV80+AW80+BC80+BE80+BF80+BG80+BH80+BI80+BJ80+BB80+BD80 -> 52500 | F80: =+E80-D80 -> 0 | N80: 0 | O80: =SUM(G80:N80) -> 0 | Z80: 0 | AA80: =SUM(P80:Z80) -> 0 | AD80: =+'[12]G-2 Budget'!$E$20 -> 52500 | AK80: =SUM(AB80:AJ80) -> 52500 | AU80: =SUM(AL80:AT80) -> 0 | AX80: 0 | AY80: 0 | BB80: =SUM(AX80:BA80) -> 0 | BL80: =+D80*5% -> 2625 | BM80: =+BL80+D80 -> 55125
A81: =+#REF!+1 -> #REF! | B81: TBH - Case Manager | C81: =+D81/2080 -> 25.240385 | D81: 52500 | E81: =+O81+AA81+AK81+AU81+AV81+AW81+BC81+BE81+BF81+BG81+BH81+BI81+BJ81+BB81+BD81 -> 52500 | F81: =+E81-D81 -> 0 | N81: 0 | O81: =SUM(G81:N81) -> 0 | Z81: 0 | AA81: =SUM(P81:Z81) -> 0 | AE81: 52500 | AK81: =SUM(AB81:AJ81) -> 52500 | AU81: =SUM(AL81:AT81) -> 0 | AX81: 0 | AY81: 0 | BB81: =SUM(AX81:BA81) -> 0 | BL81: =+D81*5% -> 2625 | BM81: =+BL81+D81 -> 55125
B82: Mariela Peneranda | C82: 24.0385 | D82: =+C82*800 -> 19230.8 | E82: =+O82+AA82+AK82+AU82+AV82+AW82+BC82+BE82+BF82+BG82+BH82+BI82+BJ82+BB82+BD82 -> 24269.29 | F82: =+E82-D82 -> 5038.49 | N82: 0 | O82: =SUM(G82:N82) -> 0 | Z82: 0 | AA82: =SUM(P82:Z82) -> 0 | AK82: =SUM(AB82:AJ82) -> 0 | AX82: 0 | AY82: 0 | AZ82: 18269.29 | BA82: 0 | BB82: =SUM(AX82:BA82) -> 18269.29 | BD82: 6000 | BL82: =+D82*5% -> 961.54 | BM82: =+BL82+D82 -> 20192.34
B83: TBH - Case Manager | E83: =+O83+AA83+AK83+AU83+AV83+AW83+BC83+BE83+BF83+BG83+BH83+BI83+BJ83+BB83+BD83 -> 41475 | F83: =+E83-D83 -> 41475 | L83: 13125 | M83: 15225 | N83: 13125 | O83: =SUM(G83:N83) -> 41475 | AA83: =SUM(P83:Z83) -> 0 | AK83: =SUM(AB83:AJ83) -> 0 | BB83: =SUM(AX83:BA83) -> 0
B84: TBH - Case Manager | E84: =+O84+AA84+AK84+AU84+AV84+AW84+BC84+BE84+BF84+BG84+BH84+BI84+BJ84+BB84+BD84 -> 26375 | F84: =+E84-D84 -> 26375 | H84: 26375 | O84: =SUM(G84:N84) -> 26375 | AA84: =SUM(P84:Z84) -> 0 | AK84: =SUM(AB84:AJ84) -> 0 | BB84: =SUM(AX84:BA84) -> 0
B85: TBH - PM (Spencer) | E85: =+O85+AA85+AK85+AU85+AV85+AW85+BC85+BE85+BF85+BG85+BH85+BI85+BJ85+BB85+BD85 -> 63700 | F85: =+E85-D85 -> 63700 | O85: =SUM(G85:N85) -> 0 | Q85: 4550 | R85: 5850 | W85: 16250 | X85: 20800 | Y85: 16250 | AA85: =SUM(P85:Z85) -> 63700 | AK85: =SUM(AB85:AJ85) -> 0 | BB85: =SUM(AX85:BA85) -> 0
B86: TBH - Case Manager | E86: =+O86+AA86+AK86+AU86+AV86+AW86+BC86+BE86+BF86+BG86+BH86+BI86+BJ86+BB86+BD86 -> 50000 | F86: =+E86-D86 -> 50000 | O86: =SUM(G86:N86) -> 0 | T86: 50000 | AA86: =SUM(P86:Z86) -> 50000 | AK86: =SUM(AB86:AJ86) -> 0 | BB86: =SUM(AX86:BA86) -> 0
B87: TBH - Case Manager | E87: =+O87+AA87+AK87+AU87+AV87+AW87+BC87+BE87+BF87+BG87+BH87+BI87+BJ87+BB87+BD87 -> 1300 | F87: =+E87-D87 -> 1300 | O87: =SUM(G87:N87) -> 0 | T87: 1300 | AA87: =SUM(P87:Z87) -> 1300 | AI87: 0 | AK87: =SUM(AB87:AJ87) -> 0 | BB87: =SUM(AX87:BA87) -> 0
B88: TBH - Case Manager | E88: =+O88+AA88+AK88+AU88+AV88+AW88+BC88+BE88+BF88+BG88+BH88+BI88+BJ88+BB88+BD88 -> 0 | F88: =+E88-D88 -> 0 | O88: =SUM(G88:N88) -> 0 | AA88: =SUM(P88:Z88) -> 0 | AI88: 0 | AK88: =SUM(AB88:AJ88) -> 0 | BB88: =SUM(AX88:BA88) -> 0
A89: =+A81+1 -> #REF! | B89: =+B81 -> TBH - Case Manager | C89: =+D89/2080 -> 25.240385 | D89: 52500 | E89: =+O89+AA89+AK89+AU89+AV89+AW89+BC89+BE89+BF89+BG89+BH89+BI89+BJ89+BB89+BD89 -> 52500 | F89: =+E89-D89 -> 0 | N89: 0 | O89: =SUM(G89:N89) -> 0 | Z89: 0 | AA89: =SUM(P89:Z89) -> 0 | AE89: 52500 | AK89: =SUM(AB89:AJ89) -> 52500 | AU89: =SUM(AL89:AT89) -> 0 | AX89: 0 | AY89: 0 | BB89: =SUM(AX89:BA89) -> 0
A90: =+A89+1 -> #REF! | B90: Brishna Katawazai - Christina | C90: 25.601 | D90: =+C90*2080 -> 53250.08 | E90: =+O90+AA90+AK90+AU90+AV90+AW90+BC90+BE90+BF90+BG90+BH90+BI90+BJ90+BB90+BD90 -> 55912 | F90: =+E90-D90 -> 2661.92 | N90: 0 | O90: =SUM(G90:N90) -> 0 | Z90: 0 | AA90: =SUM(P90:Z90) -> 0 | AK90: =SUM(AB90:AJ90) -> 0 | AO90: =+'[2]P 2-Salary '!$J$25 -> 55912 | AU90: =SUM(AL90:AT90) -> 55912 | AX90: 0 | AY90: 0 | BB90: =SUM(AX90:BA90) -> 0
A91: =+#REF!+1 -> #REF! | B91: TBH - Ferdawok | C91: 24.0385 | D91: =+C91*2080 -> 50000.08 | E91: =+O91+AA91+AK91+AU91+AV91+AW91+BC91+BE91+BF91+BG91+BH91+BI91+BJ91+BB91+BD91 -> 62062 | F91: =+E91-D91 -> 12061.92 | N91: 0 | O91: =SUM(G91:N91) -> 0 | Z91: 0 | AA91: =SUM(P91:Z91) -> 0 | AB91: 0 | AC91: 0 | AD91: 0 | AE91: 0 | AF91: 0 | AH91: 0 | AJ91: 0 | AK91: =SUM(AB91:AJ91) -> 0 | AO91: 62062 | AU91: =SUM(AL91:AT91) -> 62062 | AX91: 0 | AY91: 0 | BB91: =SUM(AX91:BA91) -> 0 | BI91: 0
A92: 84 | B92: TBH- Case Manager | C92: =+D92/2080 -> 25.240385 | D92: 52500 | E92: =+O92+AA92+AK92+AU92+AV92+AW92+BC92+BE92+BF92+BG92+BH92+BI92+BJ92+BB92+BD92 -> 52500 | F92: =+E92-D92 -> 0 | N92: 0 | O92: =SUM(G92:N92) -> 0 | Z92: 0 | AA92: =SUM(P92:Z92) -> 0 | AD92: =+'[12]G-2 Budget'!$E$27 -> 52500 | AK92: =SUM(AB92:AJ92) -> 52500 | AU92: =SUM(AL92:AT92) -> 0 | AX92: 0 | AY92: 0 | BB92: =SUM(AX92:BA92) -> 0
A93: =+A92+1 -> 85 | B93: TBH Job Developer VA | C93: =+D93/2080 -> 26.442308 | D93: 55000 | E93: =+O93+AA93+AK93+AU93+AV93+AW93+BC93+BE93+BF93+BG93+BH93+BI93+BJ93+BB93+BD93 -> 55000 | F93: =+E93-D93 -> 0 | N93: 0 | O93: =SUM(G93:N93) -> 0 | Z93: 0 | AA93: =SUM(P93:Z93) -> 0 | AK93: =SUM(AB93:AJ93) -> 0 | AO93: =+'[2]P 2-Salary '!$J$32 -> 55000 | AU93: =SUM(AL93:AT93) -> 55000 | AW93: 0 | AX93: 0 | AY93: 0 | BA93: 0 | BB93: =SUM(AX93:BA93) -> 0 | BL93: =+D93*5% -> 2750 | BM93: =+BL93+D93 -> 57750
D94: =SUM(D4:D93) -> 4694801.4 | E94: =SUM(E4:E93) -> 5812270.6 | F94: =SUM(F4:F93) -> 1117469.3 | G94: =SUM(G4:G93) -> 68195.65 | H94: =SUM(H4:H93) -> 90667.43 | I94: =SUM(I4:I93) -> 18219.75 | J94: =SUM(J4:J93) -> 72651.62 | K94: =SUM(K4:K93) -> 44328.2 | ... BJ94: =SUM(BJ4:BJ93) -> 0
B95: Fringe | AC95: 52788 | AD95: 59697 | AE95: 189105 | AF95: 277954 | AG95: 54673 | AI95: 0 | AK95: 66366 | AL95: =SUM(AC95:AK95) -> 700583 | AM95: 28842.82 | AN95: 30579.58 | AO95: 81176.97 | AP95: 235113.11 | AQ95: 37262.16 | AR95: 36477.37 | AS95: 51055.89 | AT95: 48308.77 | AU95: 47092.89 | AV95: =SUM(AM95:AU95) -> 595909.56
B96: Interpreter | AC96: 1500 | AD96: 2000 | AE96: 5000 | AF96: 4500 | AG96: 0 | AI96: 0 | AK96: 1500 | AL96: =SUM(AC96:AK96) -> 14500 | AM96: 1000 | AN96: 500 | AO96: 4500 | AP96: 0 | AQ96: 2300 | AR96: 1500 | AT96: 1500 | AV96: =SUM(AM96:AU96) -> 11300
B97: Telephone | AC97: 900 | AD97: 840 | AE97: 2520 | AF97: 4620 | AG97: 1200 | AI97: 0 | AK97: 1200 | AL97: =SUM(AC97:AK97) -> 11280 | AM97: 1000 | AN97: 1500 | AO97: 0 | AP97: 0 | AQ97: 1000 | AR97: 1000 | AS97: 1500 | AT97: 1500 | AU97: 2000 | AV97: =SUM(AM97:AU97) -> 9500
B98: Travel | AC98: 3060 | AD98: 1504 | AE98: 3360 | AF98: 2100 | AG98: 1789 | AI98: 0 | AK98: 840 | AL98: =SUM(AC98:AK98) -> 12653 | AM98: 1000 | AN98: 500 | AO98: 500 | AP98: 2500 | AQ98: 1000 | AR98: 500 | AS98: 2000 | AT98: 2000 | AU98: 3000 | AV98: =SUM(AM98:AU98) -> 13000
B99: Printing | AC99: 0 | AD99: 480 | AE99: 900 | AF99: 900 | AG99: 0 | AI99: 0 | AK99: 600 | AL99: =SUM(AC99:AK99) -> 2880 | AM99: 0 | AN99: 0 | AO99: 0 | AP99: 0 | AQ99: 0 | AR99: 0 | AS99: 0 | AT99: 0 | AU99: 0 | AV99: =SUM(AM99:AU99) -> 0
B100: Direct | AC100: 0 | AD100: 0 | AE100: 317000 | AF100: 151000 | AG100: 429600 | AI100: 0 | AK100: 172500 | AL100: =SUM(AC100:AK100) -> 1070100 | AM100: 18500 | AN100: 20000 | AO100: 127500 | AP100: 2423000 | AQ100: 10500 | AR100: 18000 | AS100: 47000 | AT100: 43500 | AU100: 41500 | AV100: =SUM(AM100:AU100) -> 2749500
B101: Rent | AC101: 10221 | AD101: 11400 | AE101: 30806 | AF101: 47610 | AG101: 8400 | AI101: 0 | AK101: 13048 | AL101: =SUM(AC101:AK101) -> 121485 | AM101: 0 | AN101: 0 | AO101: 0 | AP101: 0 | AQ101: 0 | AR101: 0 | AS101: 0 | AT101: 0 | AU101: 0 | AV101: =SUM(AM101:AU101) -> 0
...

Sheet Open Positions
E9: =+F9 -> PC Resettlement | F9: PC Resettlement | G9: PC ICM | H9: RSS | I9: ARSS | J9: 5051 | K9: RTCA | L9: ECMP | M9: RHEO | N9: ASA RHEO | O9: ASA RSS | P9: ASA VRSAP | Q9: ASA MYVA
E10: 5245-30 | F10: 5245-33 | G10: 5240-30 | H10: 5059 | I10: 5196 | J10: SOR | K10: New | L10: 5052 | M10: 5061 | N10: 5117 | O10: 5118 | P10: 5119 | Q10: 5151 | R10: Total
C11: 1 | D11: Maternity Frishta Khalil | E11: 0 | F11: 0 | G11: 0 | H11: =+'FY26'!AE31 -> 49203 | I11: 0 | J11: 0 | K11: 0 | L11: 0 | M11: 0 | N11: 0 | O11: 0 | P11: 0 | Q11: 0 | R11: =SUM(E11:Q11) -> 49203
C12: 2 | D12: =+'FY26'!B32 -> TBH - Ganna Poskara | E12: 0 | F12: 0 | G12: 0 | H12: 0 | I12: =+'FY26'!AJ32 -> 54000 | J12: 0 | K12: 0 | L12: 0 | M12: 0 | N12: 0 | O12: 0 | P12: 0 | Q12: 0 | R12: =SUM(E12:Q12) -> 54000
C13: 3 | D13: =+'FY26'!B33 -> TBH - Gelila Woodimagen | E13: 0 | F13: 0 | G13: 0 | H13: 0 | I13: =+'FY26'!AJ33 -> 51000 | J13: 0 | K13: 0 | L13: 0 | M13: 0 | N13: 0 | O13: 0 | P13: 0 | Q13: 0 | R13: =SUM(E13:Q13) -> 51000
C14: 4 | D14: =+'FY26'!B60 -> TBH - Razia Mahrami | E14: 0 | F14: 0 | G14: 0 | H14: =+'FY26'!AE60 -> 72666 | I14: 0 | J14: 0 | K14: 0 | L14: 0 | M14: 0 | N14: 0 | O14: 0 | P14: 0 | Q14: 0 | R14: =SUM(E14:Q14) -> 72666
C15: 5 | D15: =+'FY26'!B63 -> TBH - Albab | E15: 0 | F15: 0 | G15: 0 | H15: =+'FY26'!AE63 -> 42500 | I15: 0 | J15: 0 | K15: 0 | L15: 0 | M15: 0 | N15: 0 | O15: 0 | P15: 0 | Q15: 0 | R15: =SUM(E15:Q15) -> 42500
C16: 6 | D16: =+'FY26'!B76 -> TBH - Outreach Coordinator | E16: 25000 | F16: =+'FY26'!AY76 -> 13125 | G16: 0 | H16: 0 | I16: 0 | J16: 0 | K16: 0 | L16: 0 | M16: 0 | N16: 0 | O16: 0 | P16: 0 | Q16: 0 | R16: =SUM(E16:Q16) -> 38125
C17: 7 | D17: =+'FY26'!B77 -> TBH - Donation Assistant | E17: 25000 | F17: =+'FY26'!AY77 -> 13125 | G17: 0 | H17: 0 | I17: 0 | J17: 0 | K17: 0 | L17: 0 | M17: 0 | N17: 0 | O17: 0 | P17: 0 | Q17: 0 | R17: =SUM(E17:Q17) -> 38125
C18: 8 | D18: =+'FY26'!B78 -> TBH - Case Manager | E18: 0 | F18: 0 | G18: 0 | H18: 0 | I18: 0 | J18: =+'FY26'!AC78 -> 27500 | K18: 0 | L18: 0 | M18: 0 | N18: 0 | O18: 0 | P18: 0 | Q18: 0 | R18: =SUM(E18:Q18) -> 27500
C19: 9 | D19: =+'FY26'!B78 -> TBH - Case Manager | E19: 0 | F19: 0 | G19: 0 | H19: 0 | I19: 0 | J19: 0 | K19: 52500 | L19: 0 | M19: 0 | N19: 0 | O19: 0 | P19: 0 | Q19: 0 | R19: =SUM(E19:Q19) -> 52500
C20: 10 | D20: =+D19 -> TBH - Case Manager | E20: 0 | F20: 0 | G20: 0 | H20: 0 | I20: 0 | J20: 0 | K20: 0 | L20: 52500 | M20: 0 | N20: 0 | O20: 0 | P20: 0 | Q20: 0 | R20: =SUM(E20:Q20) -> 52500
C21: 11 | D21: =+D20 -> TBH - Case Manager | E21: 0 | F21: 0 | G21: 0 | H21: 52500 | I21: 0 | J21: 0 | K21: 0 | L21: 0 | M21: 0 | N21: 0 | O21: 0 | P21: 0 | Q21: 0 | R21: =SUM(E21:Q21) -> 52500
C22: 12 | D22: =+D21 -> TBH - Case Manager | E22: 0 | F22: 0 | G22: 0 | H22: 52500 | I22: 0 | J22: 0 | K22: 0 | L22: 0 | M22: 0 | N22: 0 | O22: 0 | P22: 0 | Q22: 0 | R22: =SUM(E22:Q22) -> 52500
C23: 13 | D23: =+D22 -> TBH - Case Manager | E23: 0 | F23: 0 | G23: 0 | H23: 0 | I23: 0 | J23: 0 | K23: 0 | L23: 52500 | M23: 0 | N23: 0 | O23: 0 | P23: 0 | Q23: 0 | R23: =SUM(E23:Q23) -> 52500
C24: 14 | D24: =+D22 -> TBH - Case Manager | E24: 50000 | F24: 0 | G24: 0 | H24: 0 | I24: 0 | J24: 0 | K24: 0 | L24: 0 | M24: 0 | N24: 0 | O24: 0 | P24: 0 | Q24: 0 | R24: =SUM(E24:Q24) -> 50000
C25: 15 | D25: =+'FY26'!B74 -> TBH - Annie Phillips | E25: 0 | F25: 0 | G25: 5712 | H25: 0 | I25: 0 | J25: 0 | K25: 0 | L25: 0 | M25: 7140 | N25: 17850 | O25: 0 | P25: 14280 | Q25: 14680 | R25: =SUM(E25:Q25) -> 59662
C26: 16 | D26: =+'FY26'!B91 -> TBH - Ferdawok | E26: 0 | F26: 0 | G26: 0 | H26: 0 | I26: 0 | J26: 0 | K26: 0 | L26: 0 | M26: 0 | N26: 0 | O26: 62062 | P26: 0 | Q26: 0 | R26: =SUM(E26:Q26) -> 62062
C27: 17 | D27: =+'FY26'!B93 -> TBH Job Developer VA | E27: 0 | F27: 0 | G27: 0 | H27: 0 | I27: 0 | J27: 0 | K27: 0 | L27: 0 | M27: 0 | N27: 0 | O27: 55000 | P27: 0 | Q27: 0 | R27: =SUM(E27:Q27) -> 55000
E28: =SUM(E11:E27) -> 100000 | F28: =SUM(F11:F27) -> 26250 | G28: =SUM(G11:G27) -> 5712 | H28: =SUM(H11:H27) -> 269369 | I28: =SUM(I11:I27) -> 105000 | J28: =SUM(J11:J27) -> 27500 | K28: =SUM(K11:K27) -> 52500 | L28: =SUM(L11:L27) -> 105000 | ... R28: =SUM(R11:R27) -> 862343
